Workbook

Sheet lc_detailed
B2: Asset Parameters (normalized by commodity feedstock) | Q2: Duals | AM2: LCOE for ethanol production ($/MWh-ethanol) | AO2: CI | AP2: CREDIT | AQ2: CI | AR2: CREDIT | BA2: NET CARBON INTENSITY + credit for capture | BD2: CREDIT for capture/storage + PAY for storage | BH2: Carbon Content | BL2: Carbon Inputs | BP2: Carbon Outputs | BU2: Sanity Checks
B3: id | C3: commodity | D3: elec_production (MWh/t-bio) | E3: elec_consumption (MWh/t-bio) | F3: ethanol_production (MWh-ethanol/t-bio) | G3: natgas_consumption (MWh/t-bio) | H3: co2_biomass_content (t-CO2/t-bio) | I3: capture_rate (t-CO2/t-bio) | J3: emission_rate (t-CO2/t-bio) | K3: calculated_emission_rate (t-CO2/t-bio) | L3: calculated_capture_rate (t-CO2/t-bio) | M3: investment_cost ($/yr per t-bio/hr) | N3: fixed_om_cost ($/yr per t-bio/hr) | O3: variable_om_cost ($/t-bio) | Q3: co2_sink ($/t) | R3: co2_captured ($/t) | S3: biocorn_supply ($/t) | T3: bioherb_supply ($/t) | U3: biowood_supply ($/t) | V3: bioagri_supply ($/t) | W3: ethanol_balance ($/MWh) | X3: ethanol_demand ($/MWh) | Y3: elec_demand ($/MWh) | Z3: h2_balance ($/MWh) | AA3: h2_demand ($/MWh) | AB3: gasoline_balance ($/MWh) | AC3: gasoline_demand ($/MWh) | AD3: diesel_balance ($/MWh) | AE3: diesel_demand ($/MWh) | AF3: jetfuel_balance ($/MWh) | AG3: jetfuel_demand ($/MWh) | AH3: ng_balance ($/MWh) | AI3: ng_demand ($/MWh) | AJ3: ethylene_balance ($/t) | AK3: ethylene_demand ($/t) | AM3: id_LC | AN3: commodity_LC | AO3: LCOE ($/MWh-ethanol) | AP3: LCOE ($/MWh-ethanol) | AQ3: LCOE ($/GJ-ethanol) | AR3: LCOE ($/GJ-ethanol) | AS3: Diff. Between Methods ($/MWh) | AT3: elec_production | AU3: elec_consumption | AV3: biomass_consumption | AW3: natgas_consumption | AX3: investment_cost | AY3: fixed_om_cost | AZ3: variable_om_cost | BA3: CI | BB3: modified capture cost | BC3: modified emissions cost | BD3: CI | BE3: modified capture cost | BF3: modified emissions cost | BH3: Biomass CO2 content (t-CO2/t-bio) | BI3: NG (t-CO2/MWh-NG) | BJ3: Ethanol (t-CO2/MWh-ethanol) | BL3: Biomass (t-CO2/MWh-ethanol) | BM3: NG (t-CO2/MWh-ethanol) | BN3: Total input (t-CO2/MWh-ethanol) | BP3: Ethanol (t-CO2/MWh-ethanol) | BQ3: Emissions (t-CO2/MWh-ethanol) | BR3: Captured (t-CO2/MWh-ethanol) | BS3: Total Output (t-CO2/MWh-ethanol) | BU3: Carbon INPUT - OUTPUT
B4: SE_Biochemical_CCS_20 | C4: Biomass_Agri | D4: 0.1227 | E4: 0 | F4: 1.5509 | G4: 0 | H4: 1.32 | I4: 0.19 | J4: 0.77 | K4: =(BM4+(BL4-BP4-BR4))*F4 | L4: =BR4*F4 | M4: 658128.84 | N4: 195838.97 | O4: 55.71 | Q4: 73.71884 | R4: -6.091002 | T4: 59.252833 | U4: 23.691089 | V4: 31.789762 | W4: -8.00727 | Y4: 21.266241 | Z4: 7.267779 | AB4: -128.07763 | AC4: -128.07763 | AH4: 7.96358 | AI4: 0 | AJ4: 822.26752 | AK4: 822.26752 | AM4: =B4 | AN4: =C4 | AO4: =SUM(AT4:AZ4)+BB4+BC4 | AP4: =SUM(AT4:AZ4)+BE4+BF4 | AQ4: =AO4/3.6 | AR4: =AP4/3.6 | AS4: =AO4-AP4 | AT4: =D4/F4*Y4*-1 | AU4: =E4/F4*Y4 | AV4: {=_xlfn.IFS(C4="Biomass_Corn", 1/F4*S4, C4="Biomass_Agri", 1/F4*V4, C4="Biomass_Wood", 1/F4*U4, C4="Biomass_Herb", 1/F4*T4)} | AW4: =G4/F4*AH4 | AX4: =M4/F4/(0.9*8760) | AY4: =N4/F4/(0.9*8760) | AZ4: =O4/F4 | BA4: =SUM(BP4:BR4)-BL4 | BB4: =(Q4+R4)*-1*I4/F4 | BC4: =BA4*Q4 | BD4: =SUM(BP4:BQ4)-BL4 | BE4: =I4/F4*-1*R4 | BF4: =BD4*Q4 | BH4: =H4 | BI4: 0.18104824 | BJ4: 0.230447 | BL4: =BH4/F4 | BM4: =BI4*G4/F4 | BN4: =SUM(BL4:BM4) | BP4: =BJ4 | BQ4: =J4/F4 | BR4: =I4/F4 | BS4: =SUM(BP4:BR4) | BU4: =BN4-BS4
B5: SE_Biochemical_CCS_86 | C5: Biomass_Agri | D5: 0.1227 | E5: 0.26 | F5: 1.5509 | G5: 0 | H5: 1.32 | I5: 0.83 | J5: 0.13 | K5: =(BM5+(BL5-BP5-BR5))*F5 | L5: =BR5*F5 | M5: 727064.6 | N5: 233553.61 | O5: 56.9 | Q5: 73.71884 | R5: -6.091002 | T5: 59.252833 | U5: 23.691089 | V5: 31.789762 | W5: -8.00727 | Y5: 21.266241 | Z5: 7.267779 | AB5: -128.07763 | AC5: -128.07763 | AH5: 7.96358 | AI5: 0 | AJ5: 822.26752 | AK5: 822.26752 | AM5: =B5 | AN5: =C5 | AO5: =SUM(AT5:AZ5)+BB5+BC5 | AP5: =SUM(AT5:AZ5)+BE5+BF5 | AQ5: =AO5/3.6 | AR5: =AP5/3.6 | AS5: =AO5-AP5 | AT5: =D5/F5*Y5*-1 | AU5: =E5/F5*Y5 | AV5: {=_xlfn.IFS(C5="Biomass_Corn", 1/F5*S5, C5="Biomass_Agri", 1/F5*V5, C5="Biomass_Wood", 1/F5*U5, C5="Biomass_Herb", 1/F5*T5)} | AW5: =G5/F5*AH5 | AX5: =M5/F5/(0.9*8760) | AY5: =N5/F5/(0.9*8760) | AZ5: =O5/F5 | BA5: =SUM(BP5:BR5)-BL5 | BB5: =(Q5+R5)*-1*I5/F5 | BC5: =BA5*Q5 | BD5: =SUM(BP5:BQ5)-BL5 | BE5: =I5/F5*-1*R5 | BF5: =BD5*Q5 | BH5: =H5 | BI5: 0.18104824 | BJ5: 0.230447 | BL5: =BH5/F5 | BM5: =BI5*G5/F5 | BN5: =SUM(BL5:BM5) | BP5: =BJ5 | BQ5: =J5/F5 | BR5: =I5/F5 | BS5: =SUM(BP5:BR5) | BU5: =BN5-BS5
B6: MIDAT_Biochemical_CCS_20 | C6: Biomass_Agri | D6: 0.1227 | E6: 0 | F6: 1.5509 | G6: 0 | H6: 1.32 | I6: 0.19 | J6: 0.77 | K6: =(BM6+(BL6-BP6-BR6))*F6 | L6: =BR6*F6 | M6: 658128.84 | N6: 195838.97 | O6: 55.71 | Q6: 73.71884 | R6: -16.179128 | T6: 58.461202 | U6: 19.647223 | V6: 40.820307 | W6: -2.203044 | Y6: 21.500722 | Z6: 7.532437 | AB6: -140.74133 | AC6: -140.74133 | AH6: 5.407672 | AI6: 0 | AJ6: 822.26752 | AK6: 822.26752 | AM6: =B6 | AN6: =C6 | AO6: =SUM(AT6:AZ6)+BB6+BC6 | AP6: =SUM(AT6:AZ6)+BE6+BF6 | AQ6: =AO6/3.6 | AR6: =AP6/3.6 | AS6: =AO6-AP6 | AT6: =D6/F6*Y6*-1 | AU6: =E6/F6*Y6 | AV6: {=_xlfn.IFS(C6="Biomass_Corn", 1/F6*S6, C6="Biomass_Agri", 1/F6*V6, C6="Biomass_Wood", 1/F6*U6, C6="Biomass_Herb", 1/F6*T6)} | AW6: =G6/F6*AH6 | AX6: =M6/F6/(0.9*8760) | AY6: =N6/F6/(0.9*8760) | AZ6: =O6/F6 | BA6: =SUM(BP6:BR6)-BL6 | BB6: =(Q6+R6)*-1*I6/F6 | BC6: =BA6*Q6 | BD6: =SUM(BP6:BQ6)-BL6 | BE6: =I6/F6*-1*R6 | BF6: =BD6*Q6 | BH6: =H6 | BI6: 0.18104824 | BJ6: 0.230447 | BL6: =BH6/F6 | BM6: =BI6*G6/F6 | BN6: =SUM(BL6:BM6) | BP6: =BJ6 | BQ6: =J6/F6 | BR6: =I6/F6 | BS6: =SUM(BP6:BR6) | BU6: =BN6-BS6
B7: MIDAT_Biochemical_CCS_86 | C7: Biomass_Agri | D7: 0.1227 | E7: 0.26 | F7: 1.5509 | G7: 0 | H7: 1.32 | I7: 0.83 | J7: 0.13 | K7: =(BM7+(BL7-BP7-BR7))*F7 | L7: =BR7*F7 | M7: 727064.6 | N7: 233553.61 | O7: 56.9 | Q7: 73.71884 | R7: -16.179128 | T7: 58.461202 | U7: 19.647223 | V7: 40.820307 | W7: -2.203044 | Y7: 21.500722 | Z7: 7.532437 | AB7: -140.74133 | AC7: -140.74133 | AH7: 5.407672 | AI7: 0 | AJ7: 822.26752 | AK7: 822.26752 | AM7: =B7 | AN7: =C7 | AO7: =SUM(AT7:AZ7)+BB7+BC7 | AP7: =SUM(AT7:AZ7)+BE7+BF7 | AQ7: =AO7/3.6 | AR7: =AP7/3.6 | AS7: =AO7-AP7 | AT7: =D7/F7*Y7*-1 | AU7: =E7/F7*Y7 | AV7: {=_xlfn.IFS(C7="Biomass_Corn", 1/F7*S7, C7="Biomass_Agri", 1/F7*V7, C7="Biomass_Wood", 1/F7*U7, C7="Biomass_Herb", 1/F7*T7)} | AW7: =G7/F7*AH7 | AX7: =M7/F7/(0.9*8760) | AY7: =N7/F7/(0.9*8760) | AZ7: =O7/F7 | BA7: =SUM(BP7:BR7)-BL7 | BB7: =(Q7+R7)*-1*I7/F7 | BC7: =BA7*Q7 | BD7: =SUM(BP7:BQ7)-BL7 | BE7: =I7/F7*-1*R7 | BF7: =BD7*Q7 | BH7: =H7 | BI7: 0.18104824 | BJ7: 0.230447 | BL7: =BH7/F7 | BM7: =BI7*G7/F7 | BN7: =SUM(BL7:BM7) | BP7: =BJ7 | BQ7: =J7/F7 | BR7: =I7/F7 | BS7: =SUM(BP7:BR7) | BU7: =BN7-BS7
B8: NE_Biochemical_CCS_20 | C8: Biomass_Agri | D8: 0.1227 | E8: 0 | F8: 1.5509 | G8: 0 | H8: 1.32 | I8: 0.19 | J8: 0.77 | K8: =(BM8+(BL8-BP8-BR8))*F8 | L8: =BR8*F8 | M8: 658128.84 | N8: 195838.97 | O8: 55.71 | Q8: 73.71884 | R8: -23.276809 | T8: 60.47681 | U8: 28.904358 | V8: 39.957475 | W8: -2.703157 | Y8: 20.789991 | Z8: 9.19598 | AB8: -150.75579 | AC8: -150.75579 | AH8: 8.960454 | AI8: 0 | AJ8: 822.26752 | AK8: 0 | AM8: =B8 | AN8: =C8 | AO8: =SUM(AT8:AZ8)+BB8+BC8 | AP8: =SUM(AT8:AZ8)+BE8+BF8 | AQ8: =AO8/3.6 | AR8: =AP8/3.6 | AS8: =AO8-AP8 | AT8: =D8/F8*Y8*-1 | AU8: =E8/F8*Y8 | AV8: {=_xlfn.IFS(C8="Biomass_Corn", 1/F8*S8, C8="Biomass_Agri", 1/F8*V8, C8="Biomass_Wood", 1/F8*U8, C8="Biomass_Herb", 1/F8*T8)} | AW8: =G8/F8*AH8 | AX8: =M8/F8/(0.9*8760) | AY8: =N8/F8/(0.9*8760) | AZ8: =O8/F8 | BA8: =SUM(BP8:BR8)-BL8 | BB8: =(Q8+R8)*-1*I8/F8 | BC8: =BA8*Q8 | BD8: =SUM(BP8:BQ8)-BL8 | BE8: =I8/F8*-1*R8 | BF8: =BD8*Q8 | BH8: =H8 | BI8: 0.18104824 | BJ8: 0.230447 | BL8: =BH8/F8 | BM8: =BI8*G8/F8 | BN8: =SUM(BL8:BM8) | BP8: =BJ8 | BQ8: =J8/F8 | BR8: =I8/F8 | BS8: =SUM(BP8:BR8) | BU8: =BN8-BS8
B9: NE_Biochemical_CCS_86 | C9: Biomass_Agri | D9: 0.1227 | E9: 0.26 | F9: 1.5509 | G9: 0 | H9: 1.32 | I9: 0.83 | J9: 0.13 | K9: =(BM9+(BL9-BP9-BR9))*F9 | L9: =BR9*F9 | M9: 727064.6 | N9: 233553.61 | O9: 56.9 | Q9: 73.71884 | R9: -23.276809 | T9: 60.47681 | U9: 28.904358 | V9: 39.957475 | W9: -2.703157 | Y9: 20.789991 | Z9: 9.19598 | AB9: -150.75579 | AC9: -150.75579 | AH9: 8.960454 | AI9: 0 | AJ9: 822.26752 | AK9: 0 | AM9: =B9 | AN9: =C9 | AO9: =SUM(AT9:AZ9)+BB9+BC9 | AP9: =SUM(AT9:AZ9)+BE9+BF9 | AQ9: =AO9/3.6 | AR9: =AP9/3.6 | AS9: =AO9-AP9 | AT9: =D9/F9*Y9*-1 | AU9: =E9/F9*Y9 | AV9: {=_xlfn.IFS(C9="Biomass_Corn", 1/F9*S9, C9="Biomass_Agri", 1/F9*V9, C9="Biomass_Wood", 1/F9*U9, C9="Biomass_Herb", 1/F9*T9)} | AW9: =G9/F9*AH9 | AX9: =M9/F9/(0.9*8760) | AY9: =N9/F9/(0.9*8760) | AZ9: =O9/F9 | BA9: =SUM(BP9:BR9)-BL9 | BB9: =(Q9+R9)*-1*I9/F9 | BC9: =BA9*Q9 | BD9: =SUM(BP9:BQ9)-BL9 | BE9: =I9/F9*-1*R9 | BF9: =BD9*Q9 | BH9: =H9 | BI9: 0.18104824 | BJ9: 0.230447 | BL9: =BH9/F9 | BM9: =BI9*G9/F9 | BN9: =SUM(BL9:BM9) | BP9: =BJ9 | BQ9: =J9/F9 | BR9: =I9/F9 | BS9: =SUM(BP9:BR9) | BU9: =BN9-BS9
B10: CA_Biochemical_CCS_20 | C10: Biomass_Agri | D10: 0.1227 | E10: 0 | F10: 1.5509 | G10: 0 | H10: 1.32 | I10: 0.19 | J10: 0.77 | K10: =(BM10+(BL10-BP10-BR10))*F10 | L10: =BR10*F10 | M10: 658128.84 | N10: 195838.97 | O10: 55.71 | Q10: 73.71884 | R10: 3.828238 | T10: 70.666428 | U10: 35.61527 | V10: 32.098216 | W10: -9.011429 | Y10: 20.274928 | Z10: 8.466452 | AB10: -116.15052 | AC10: -116.15052 | AH10: 12.963218 | AI10: 0 | AJ10: 822.26752 | AK10: 0 | AM10: =B10 | AN10: =C10 | AO10: =SUM(AT10:AZ10)+BB10+BC10 | AP10: =SUM(AT10:AZ10)+BE10+BF10 | AQ10: =AO10/3.6 | AR10: =AP10/3.6 | AS10: =AO10-AP10 | AT10: =D10/F10*Y10*-1 | AU10: =E10/F10*Y10 | AV10: {=_xlfn.IFS(C10="Biomass_Corn", 1/F10*S10, C10="Biomass_Agri", 1/F10*V10, C10="Biomass_Wood", 1/F10*U10, C10="Biomass_Herb", 1/F10*T10)} | AW10: =G10/F10*AH10 | AX10: =M10/F10/(0.9*8760) | AY10: =N10/F10/(0.9*8760) | AZ10: =O10/F10 | BA10: =SUM(BP10:BR10)-BL10 | BB10: =(Q10+R10)*-1*I10/F10 | BC10: =BA10*Q10 | BD10: =SUM(BP10:BQ10)-BL10 | BE10: =I10/F10*-1*R10 | BF10: =BD10*Q10 | BH10: =H10 | BI10: 0.18104824 | BJ10: 0.230447 | BL10: =BH10/F10 | BM10: =BI10*G10/F10 | BN10: =SUM(BL10:BM10) | BP10: =BJ10 | BQ10: =J10/F10 | BR10: =I10/F10 | BS10: =SUM(BP10:BR10) | BU10: =BN10-BS10
B11: CA_Biochemical_CCS_86 | C11: Biomass_Agri | D11: 0.1227 | E11: 0.26 | F11: 1.5509 | G11: 0 | H11: 1.32 | I11: 0.83 | J11: 0.13 | K11: =(BM11+(BL11-BP11-BR11))*F11 | L11: =BR11*F11 | M11: 727064.6 | N11: 233553.61 | O11: 56.9 | Q11: 73.71884 | R11: 3.828238 | T11: 70.666428 | U11: 35.61527 | V11: 32.098216 | W11: -9.011429 | Y11: 20.274928 | Z11: 8.466452 | AB11: -116.15052 | AC11: -116.15052 | AH11: 12.963218 | AI11: 0 | AJ11: 822.26752 | AK11: 0 | AM11: =B11 | AN11: =C11 | AO11: =SUM(AT11:AZ11)+BB11+BC11 | AP11: =SUM(AT11:AZ11)+BE11+BF11 | AQ11: =AO11/3.6 | AR11: =AP11/3.6 | AS11: =AO11-AP11 | AT11: =D11/F11*Y11*-1 | AU11: =E11/F11*Y11 | AV11: {=_xlfn.IFS(C11="Biomass_Corn", 1/F11*S11, C11="Biomass_Agri", 1/F11*V11, C11="Biomass_Wood", 1/F11*U11, C11="Biomass_Herb", 1/F11*T11)} | AW11: =G11/F11*AH11 | AX11: =M11/F11/(0.9*8760) | AY11: =N11/F11/(0.9*8760) | AZ11: =O11/F11 | BA11: =SUM(BP11:BR11)-BL11 | BB11: =(Q11+R11)*-1*I11/F11 | BC11: =BA11*Q11 | BD11: =SUM(BP11:BQ11)-BL11 | BE11: =I11/F11*-1*R11 | BF11: =BD11*Q11 | BH11: =H11 | BI11: 0.18104824 | BJ11: 0.230447 | BL11: =BH11/F11 | BM11: =BI11*G11/F11 | BN11: =SUM(BL11:BM11) | BP11: =BJ11 | BQ11: =J11/F11 | BR11: =I11/F11 | BS11: =SUM(BP11:BR11) | BU11: =BN11-BS11
B12: NW_Biochemical_CCS_20 | C12: Biomass_Agri | D12: 0.1227 | E12: 0 | F12: 1.5509 | G12: 0 | H12: 1.32 | I12: 0.19 | J12: 0.77 | K12: =(BM12+(BL12-BP12-BR12))*F12 | L12: =BR12*F12 | M12: 658128.84 | N12: 195838.97 | O12: 55.71 | Q12: 73.71884 | R12: 6.341225 | T12: 64.329805 | U12: 37.86581 | V12: 42.137908 | W12: -3.879455 | Y12: 20.232007 | Z12: 8.132036 | AB12: -112.98996 | AC12: -112.98996 | AH12: 12.309823 | AI12: 0 | AJ12: 822.26752 | AK12: 0 | AM12: =B12 | AN12: =C12 | AO12: =SUM(AT12:AZ12)+BB12+BC12 | AP12: =SUM(AT12:AZ12)+BE12+BF12 | AQ12: =AO12/3.6 | AR12: =AP12/3.6 | AS12: =AO12-AP12 | AT12: =D12/F12*Y12*-1 | AU12: =E12/F12*Y12 | AV12: {=_xlfn.IFS(C12="Biomass_Corn", 1/F12*S12, C12="Biomass_Agri", 1/F12*V12, C12="Biomass_Wood", 1/F12*U12, C12="Biomass_Herb", 1/F12*T12)} | AW12: =G12/F12*AH12 | AX12: =M12/F12/(0.9*8760) | AY12: =N12/F12/(0.9*8760) | AZ12: =O12/F12 | BA12: =SUM(BP12:BR12)-BL12 | BB12: =(Q12+R12)*-1*I12/F12 | BC12: =BA12*Q12 | BD12: =SUM(BP12:BQ12)-BL12 | BE12: =I12/F12*-1*R12 | BF12: =BD12*Q12 | BH12: =H12 | BI12: 0.18104824 | BJ12: 0.230447 | BL12: =BH12/F12 | BM12: =BI12*G12/F12 | BN12: =SUM(BL12:BM12) | BP12: =BJ12 | BQ12: =J12/F12 | BR12: =I12/F12 | BS12: =SUM(BP12:BR12) | BU12: =BN12-BS12
B13: NW_Biochemical_CCS_86 | C13: Biomass_Agri | D13: 0.1227 | E13: 0.26 | F13: 1.5509 | G13: 0 | H13: 1.32 | I13: 0.83 | J13: 0.13 | K13: =(BM13+(BL13-BP13-BR13))*F13 | L13: =BR13*F13 | M13: 727064.6 | N13: 233553.61 | O13: 56.9 | Q13: 73.71884 | R13: 6.341225 | T13: 64.329805 | U13: 37.86581 | V13: 42.137908 | W13: -3.879455 | Y13: 20.232007 | Z13: 8.132036 | AB13: -112.98996 | AC13: -112.98996 | AH13: 12.309823 | AI13: 0 | AJ13: 822.26752 | AK13: 0 | AM13: =B13 | AN13: =C13 | AO13: =SUM(AT13:AZ13)+BB13+BC13 | AP13: =SUM(AT13:AZ13)+BE13+BF13 | AQ13: =AO13/3.6 | AR13: =AP13/3.6 | AS13: =AO13-AP13 | AT13: =D13/F13*Y13*-1 | AU13: =E13/F13*Y13 | AV13: {=_xlfn.IFS(C13="Biomass_Corn", 1/F13*S13, C13="Biomass_Agri", 1/F13*V13, C13="Biomass_Wood", 1/F13*U13, C13="Biomass_Herb", 1/F13*T13)} | AW13: =G13/F13*AH13 | AX13: =M13/F13/(0.9*8760) | AY13: =N13/F13/(0.9*8760) | AZ13: =O13/F13 | BA13: =SUM(BP13:BR13)-BL13 | BB13: =(Q13+R13)*-1*I13/F13 | BC13: =BA13*Q13 | BD13: =SUM(BP13:BQ13)-BL13 | BE13: =I13/F13*-1*R13 | BF13: =BD13*Q13 | BH13: =H13 | BI13: 0.18104824 | BJ13: 0.230447 | BL13: =BH13/F13 | BM13: =BI13*G13/F13 | BN13: =SUM(BL13:BM13) | BP13: =BJ13 | BQ13: =J13/F13 | BR13: =I13/F13 | BS13: =SUM(BP13:BR13) | BU13: =BN13-BS13
B14: SW_Biochemical_CCS_20 | C14: Biomass_Agri | D14: 0.1227 | E14: 0 | F14: 1.5509 | G14: 0 | H14: 1.32 | I14: 0.19 | J14: 0.77 | K14: =(BM14+(BL14-BP14-BR14))*F14 | L14: =BR14*F14 | M14: 658128.84 | N14: 195838.97 | O14: 55.71 | Q14: 73.71884 | R14: -4.302149 | T14: 61.152787 | U14: 40.832246 | V14: 41.356795 | W14: -1.819211 | Y14: 21.021514 | Z14: 9.044068 | AB14: -126.2252 | AC14: -126.2252 | AH14: 10.321106 | AI14: 0 | AJ14: 822.26752 | AK14: 0 | AM14: =B14 | AN14: =C14 | AO14: =SUM(AT14:AZ14)+BB14+BC14 | AP14: =SUM(AT14:AZ14)+BE14+BF14 | AQ14: =AO14/3.6 | AR14: =AP14/3.6 | AS14: =AO14-AP14 | AT14: =D14/F14*Y14*-1 | AU14: =E14/F14*Y14 | AV14: {=_xlfn.IFS(C14="Biomass_Corn", 1/F14*S14, C14="Biomass_Agri", 1/F14*V14, C14="Biomass_Wood", 1/F14*U14, C14="Biomass_Herb", 1/F14*T14)} | AW14: =G14/F14*AH14 | AX14: =M14/F14/(0.9*8760) | AY14: =N14/F14/(0.9*8760) | AZ14: =O14/F14 | BA14: =SUM(BP14:BR14)-BL14 | BB14: =(Q14+R14)*-1*I14/F14 | BC14: =BA14*Q14 | BD14: =SUM(BP14:BQ14)-BL14 | BE14: =I14/F14*-1*R14 | BF14: =BD14*Q14 | BH14: =H14 | BI14: 0.18104824 | BJ14: 0.230447 | BL14: =BH14/F14 | BM14: =BI14*G14/F14 | BN14: =SUM(BL14:BM14) | BP14: =BJ14 | BQ14: =J14/F14 | BR14: =I14/F14 | BS14: =SUM(BP14:BR14) | BU14: =BN14-BS14
B15: SW_Biochemical_CCS_86 | C15: Biomass_Agri | D15: 0.1227 | E15: 0.26 | F15: 1.5509 | G15: 0 | H15: 1.32 | I15: 0.83 | J15: 0.13 | K15: =(BM15+(BL15-BP15-BR15))*F15 | L15: =BR15*F15 | M15: 727064.6 | N15: 233553.61 | O15: 56.9 | Q15: 73.71884 | R15: -4.302149 | T15: 61.152787 | U15: 40.832246 | V15: 41.356795 | W15: -1.819211 | Y15: 21.021514 | Z15: 9.044068 | AB15: -126.2252 | AC15: -126.2252 | AH15: 10.321106 | AI15: 0 | AJ15: 822.26752 | AK15: 0 | AM15: =B15 | AN15: =C15 | AO15: =SUM(AT15:AZ15)+BB15+BC15 | AP15: =SUM(AT15:AZ15)+BE15+BF15 | AQ15: =AO15/3.6 | AR15: =AP15/3.6 | AS15: =AO15-AP15 | AT15: =D15/F15*Y15*-1 | AU15: =E15/F15*Y15 | AV15: {=_xlfn.IFS(C15="Biomass_Corn", 1/F15*S15, C15="Biomass_Agri", 1/F15*V15, C15="Biomass_Wood", 1/F15*U15, C15="Biomass_Herb", 1/F15*T15)} | AW15: =G15/F15*AH15 | AX15: =M15/F15/(0.9*8760) | AY15: =N15/F15/(0.9*8760) | AZ15: =O15/F15 | BA15: =SUM(BP15:BR15)-BL15 | BB15: =(Q15+R15)*-1*I15/F15 | BC15: =BA15*Q15 | BD15: =SUM(BP15:BQ15)-BL15 | BE15: =I15/F15*-1*R15 | BF15: =BD15*Q15 | BH15: =H15 | BI15: 0.18104824 | BJ15: 0.230447 | BL15: =BH15/F15 | BM15: =BI15*G15/F15 | BN15: =SUM(BL15:BM15) | BP15: =BJ15 | BQ15: =J15/F15 | BR15: =I15/F15 | BS15: =SUM(BP15:BR15) | BU15: =BN15-BS15
B16: NCEN_Biochemical_CCS_20 | C16: Biomass_Agri | D16: 0.1227 | E16: 0 | F16: 1.5509 | G16: 0 | H16: 1.32 | I16: 0.19 | J16: 0.77 | K16: =(BM16+(BL16-BP16-BR16))*F16 | L16: =BR16*F16 | M16: 658128.84 | N16: 195838.97 | O16: 55.71 | Q16: 73.71884 | R16: -6.097314 | S16: 155 | T16: 61.343403 | U16: 33.004971 | V16: 42.19561 | W16: 51.423576 | Y16: 22.90669 | Z16: 13.197062 | AB16: -129.52898 | AC16: -129.52898 | AH16: 14.953878 | AI16: 0 | AJ16: 822.26752 | AK16: 822.26752 | AM16: =B16 | AN16: =C16 | AO16: =SUM(AT16:AZ16)+BB16+BC16 | AP16: =SUM(AT16:AZ16)+BE16+BF16 | AQ16: =AO16/3.6 | AR16: =AP16/3.6 | AS16: =AO16-AP16 | AT16: =D16/F16*Y16*-1 | AU16: =E16/F16*Y16 | AV16: {=_xlfn.IFS(C16="Biomass_Corn", 1/F16*S16, C16="Biomass_Agri", 1/F16*V16, C16="Biomass_Wood", 1/F16*U16, C16="Biomass_Herb", 1/F16*T16)} | AW16: =G16/F16*AH16 | AX16: =M16/F16/(0.9*8760) | AY16: =N16/F16/(0.9*8760) | AZ16: =O16/F16 | BA16: =SUM(BP16:BR16)-BL16 | BB16: =(Q16+R16)*-1*I16/F16 | BC16: =BA16*Q16 | BD16: =SUM(BP16:BQ16)-BL16 | BE16: =I16/F16*-1*R16 | BF16: =BD16*Q16 | BH16: =H16 | BI16: 0.18104824 | BJ16: 0.230447 | BL16: =BH16/F16 | BM16: =BI16*G16/F16 | BN16: =SUM(BL16:BM16) | BP16: =BJ16 | BQ16: =J16/F16 | BR16: =I16/F16 | BS16: =SUM(BP16:BR16) | BU16: =BN16-BS16
B17: NCEN_Biochemical_CCS_86 | C17: Biomass_Agri | D17: 0.1227 | E17: 0.26 | F17: 1.5509 | G17: 0 | H17: 1.32 | I17: 0.83 | J17: 0.13 | K17: =(BM17+(BL17-BP17-BR17))*F17 | L17: =BR17*F17 | M17: 727064.6 | N17: 233553.61 | O17: 56.9 | Q17: 73.71884 | R17: -6.097314 | S17: 155 | T17: 61.343403 | U17: 33.004971 | V17: 42.19561 | W17: 51.423576 | Y17: 22.90669 | Z17: 13.197062 | AB17: -129.52898 | AC17: -129.52898 | AH17: 14.953878 | AI17: 0 | AJ17: 822.26752 | AK17: 822.26752 | AM17: =B17 | AN17: =C17 | AO17: =SUM(AT17:AZ17)+BB17+BC17 | AP17: =SUM(AT17:AZ17)+BE17+BF17 | AQ17: =AO17/3.6 | AR17: =AP17/3.6 | AS17: =AO17-AP17 | AT17: =D17/F17*Y17*-1 | AU17: =E17/F17*Y17 | AV17: {=_xlfn.IFS(C17="Biomass_Corn", 1/F17*S17, C17="Biomass_Agri", 1/F17*V17, C17="Biomass_Wood", 1/F17*U17, C17="Biomass_Herb", 1/F17*T17)} | AW17: =G17/F17*AH17 | AX17: =M17/F17/(0.9*8760) | AY17: =N17/F17/(0.9*8760) | AZ17: =O17/F17 | BA17: =SUM(BP17:BR17)-BL17 | BB17: =(Q17+R17)*-1*I17/F17 | BC17: =BA17*Q17 | BD17: =SUM(BP17:BQ17)-BL17 | BE17: =I17/F17*-1*R17 | BF17: =BD17*Q17 | BH17: =H17 | BI17: 0.18104824 | BJ17: 0.230447 | BL17: =BH17/F17 | BM17: =BI17*G17/F17 | BN17: =SUM(BL17:BM17) | BP17: =BJ17 | BQ17: =J17/F17 | BR17: =I17/F17 | BS17: =SUM(BP17:BR17) | BU17: =BN17-BS17
B18: CEN_Biochemical_CCS_20 | C18: Biomass_Agri | D18: 0.1227 | E18: 0 | F18: 1.5509 | G18: 0 | H18: 1.32 | I18: 0.19 | J18: 0.77 | K18: =(BM18+(BL18-BP18-BR18))*F18 | L18: =BR18*F18 | M18: 658128.84 | N18: 195838.97 | O18: 55.71 | Q18: 73.71884 | R18: -6.199254 | S18: 155 | T18: 65.59151 | U18: 31.821489 | V18: 37.986239 | W18: 51.417555 | Y18: 22.465142 | Z18: 13.285634 | AB18: -129.68145 | AC18: -129.68145 | AH18: 15.046749 | AI18: 0 | AJ18: 822.26752 | AK18: 822.26752 | AM18: =B18 | AN18: =C18 | AO18: =SUM(AT18:AZ18)+BB18+BC18 | AP18: =SUM(AT18:AZ18)+BE18+BF18 | AQ18: =AO18/3.6 | AR18: =AP18/3.6 | AS18: =AO18-AP18 | AT18: =D18/F18*Y18*-1 | AU18: =E18/F18*Y18 | AV18: {=_xlfn.IFS(C18="Biomass_Corn", 1/F18*S18, C18="Biomass_Agri", 1/F18*V18, C18="Biomass_Wood", 1/F18*U18, C18="Biomass_Herb", 1/F18*T18)} | AW18: =G18/F18*AH18 | AX18: =M18/F18/(0.9*8760) | AY18: =N18/F18/(0.9*8760) | AZ18: =O18/F18 | BA18: =SUM(BP18:BR18)-BL18 | BB18: =(Q18+R18)*-1*I18/F18 | BC18: =BA18*Q18 | BD18: =SUM(BP18:BQ18)-BL18 | BE18: =I18/F18*-1*R18 | BF18: =BD18*Q18 | BH18: =H18 | BI18: 0.18104824 | BJ18: 0.230447 | BL18: =BH18/F18 | BM18: =BI18*G18/F18 | BN18: =SUM(BL18:BM18) | BP18: =BJ18 | BQ18: =J18/F18 | BR18: =I18/F18 | BS18: =SUM(BP18:BR18) | BU18: =BN18-BS18
B19: CEN_Biochemical_CCS_86 | C19: Biomass_Agri | D19: 0.1227 | E19: 0.26 | F19: 1.5509 | G19: 0 | H19: 1.32 | I19: 0.83 | J19: 0.13 | K19: =(BM19+(BL19-BP19-BR19))*F19 | L19: =BR19*F19 | M19: 727064.6 | N19: 233553.61 | O19: 56.9 | Q19: 73.71884 | R19: -6.199254 | S19: 155 | T19: 65.59151 | U19: 31.821489 | V19: 37.986239 | W19: 51.417555 | Y19: 22.465142 | Z19: 13.285634 | AB19: -129.68145 | AC19: -129.68145 | AH19: 15.046749 | AI19: 0 | AJ19: 822.26752 | AK19: 822.26752 | AM19: =B19 | AN19: =C19 | AO19: =SUM(AT19:AZ19)+BB19+BC19 | AP19: =SUM(AT19:AZ19)+BE19+BF19 | AQ19: =AO19/3.6 | AR19: =AP19/3.6 | AS19: =AO19-AP19 | AT19: =D19/F19*Y19*-1 | AU19: =E19/F19*Y19 | AV19: {=_xlfn.IFS(C19="Biomass_Corn", 1/F19*S19, C19="Biomass_Agri", 1/F19*V19, C19="Biomass_Wood", 1/F19*U19, C19="Biomass_Herb", 1/F19*T19)} | AW19: =G19/F19*AH19 | AX19: =M19/F19/(0.9*8760) | AY19: =N19/F19/(0.9*8760) | AZ19: =O19/F19 | BA19: =SUM(BP19:BR19)-BL19 | BB19: =(Q19+R19)*-1*I19/F19 | BC19: =BA19*Q19 | BD19: =SUM(BP19:BQ19)-BL19 | BE19: =I19/F19*-1*R19 | BF19: =BD19*Q19 | BH19: =H19 | BI19: 0.18104824 | BJ19: 0.230447 | BL19: =BH19/F19 | BM19: =BI19*G19/F19 | BN19: =SUM(BL19:BM19) | BP19: =BJ19 | BQ19: =J19/F19 | BR19: =I19/F19 | BS19: =SUM(BP19:BR19) | BU19: =BN19-BS19
B20: TX_Biochemical_CCS_20 | C20: Biomass_Agri | D20: 0.1227 | E20: 0 | F20: 1.5509 | G20: 0 | H20: 1.32 | I20: 0.19 | J20: 0.77 | K20: =(BM20+(BL20-BP20-BR20))*F20 | L20: =BR20*F20 | M20: 658128.84 | N20: 195838.97 | O20: 55.71 | Q20: 73.71884 | R20: -5.000084 | T20: 62.617055 | U20: 37.705083 | V20: 30.684852 | W20: -8.726944 | Y20: 21.357777 | Z20: 7.54831 | AB20: -126.78287 | AC20: -126.78287 | AH20: 8.60172 | AI20: 0 | AJ20: 822.26752 | AK20: 822.26752 | AM20: =B20 | AN20: =C20 | AO20: =SUM(AT20:AZ20)+BB20+BC20 | AP20: =SUM(AT20:AZ20)+BE20+BF20 | AQ20: =AO20/3.6 | AR20: =AP20/3.6 | AS20: =AO20-AP20 | AT20: =D20/F20*Y20*-1 | AU20: =E20/F20*Y20 | AV20: {=_xlfn.IFS(C20="Biomass_Corn", 1/F20*S20, C20="Biomass_Agri", 1/F20*V20, C20="Biomass_Wood", 1/F20*U20, C20="Biomass_Herb", 1/F20*T20)} | AW20: =G20/F20*AH20 | AX20: =M20/F20/(0.9*8760) | AY20: =N20/F20/(0.9*8760) | AZ20: =O20/F20 | BA20: =SUM(BP20:BR20)-BL20 | BB20: =(Q20+R20)*-1*I20/F20 | BC20: =BA20*Q20 | BD20: =SUM(BP20:BQ20)-BL20 | BE20: =I20/F20*-1*R20 | BF20: =BD20*Q20 | BH20: =H20 | BI20: 0.18104824 | BJ20: 0.230447 | BL20: =BH20/F20 | BM20: =BI20*G20/F20 | BN20: =SUM(BL20:BM20) | BP20: =BJ20 | BQ20: =J20/F20 | BR20: =I20/F20 | BS20: =SUM(BP20:BR20) | BU20: =BN20-BS20
B21: TX_Biochemical_CCS_86 | C21: Biomass_Agri | D21: 0.1227 | E21: 0.26 | F21: 1.5509 | G21: 0 | H21: 1.32 | I21: 0.83 | J21: 0.13 | K21: =(BM21+(BL21-BP21-BR21))*F21 | L21: =BR21*F21 | M21: 727064.6 | N21: 233553.61 | O21: 56.9 | Q21: 73.71884 | R21: -5.000084 | T21: 62.617055 | U21: 37.705083 | V21: 30.684852 | W21: -8.726944 | Y21: 21.357777 | Z21: 7.54831 | AB21: -126.78287 | AC21: -126.78287 | AH21: 8.60172 | AI21: 0 | AJ21: 822.26752 | AK21: 822.26752 | AM21: =B21 | AN21: =C21 | AO21: =SUM(AT21:AZ21)+BB21+BC21 | AP21: =SUM(AT21:AZ21)+BE21+BF21 | AQ21: =AO21/3.6 | AR21: =AP21/3.6 | AS21: =AO21-AP21 | AT21: =D21/F21*Y21*-1 | AU21: =E21/F21*Y21 | AV21: {=_xlfn.IFS(C21="Biomass_Corn", 1/F21*S21, C21="Biomass_Agri", 1/F21*V21, C21="Biomass_Wood", 1/F21*U21, C21="Biomass_Herb", 1/F21*T21)} | AW21: =G21/F21*AH21 | AX21: =M21/F21/(0.9*8760) | AY21: =N21/F21/(0.9*8760) | AZ21: =O21/F21 | BA21: =SUM(BP21:BR21)-BL21 | BB21: =(Q21+R21)*-1*I21/F21 | BC21: =BA21*Q21 | BD21: =SUM(BP21:BQ21)-BL21 | BE21: =I21/F21*-1*R21 | BF21: =BD21*Q21 | BH21: =H21 | BI21: 0.18104824 | BJ21: 0.230447 | BL21: =BH21/F21 | BM21: =BI21*G21/F21 | BN21: =SUM(BL21:BM21) | BP21: =BJ21 | BQ21: =J21/F21 | BR21: =I21/F21 | BS21: =SUM(BP21:BR21) | BU21: =BN21-BS21
B22: NCEN_Ethanol_DryMill | C22: Biomass_Corn | D22: 0 | E22: 0.06193 | F22: 3.2587 | G22: 0.7507 | H22: 1.65 | I22: 0 | J22: 0.73836 | K22: =(BM22+(BL22-BP22-BR22))*F22 | L22: =BR22*F22 | M22: 0 | N22: 154043.63 | O22: 79.652567 | Q22: 73.71884 | R22: -6.097314 | S22: 155 | T22: 61.343403 | U22: 33.004971 | V22: 42.19561 | W22: 51.423576 | Y22: 22.90669 | Z22: 13.197062 | AB22: -129.52898 | AC22: -129.52898 | AH22: 14.953878 | AI22: 0 | AJ22: 822.26752 | AK22: 822.26752 | AM22: =B22 | AN22: =C22 | AO22: =SUM(AT22:AZ22)+BB22+BC22 | AP22: =SUM(AT22:AZ22)+BE22+BF22 | AQ22: =AO22/3.6 | AR22: =AP22/3.6 | AS22: =AO22-AP22 | AT22: =D22/F22*Y22*-1 | AU22: =E22/F22*Y22 | AV22: {=_xlfn.IFS(C22="Biomass_Corn", 1/F22*S22, C22="Biomass_Agri", 1/F22*V22, C22="Biomass_Wood", 1/F22*U22, C22="Biomass_Herb", 1/F22*T22)} | AW22: =G22/F22*AH22 | AX22: =M22/F22/(0.9*8760) | AY22: =N22/F22/(0.9*8760) | AZ22: =O22/F22 | BA22: =SUM(BP22:BR22)-BL22 | BB22: =(Q22+R22)*-1*I22/F22 | BC22: =BA22*Q22 | BD22: =SUM(BP22:BQ22)-BL22 | BE22: =I22/F22*-1*R22 | BF22: =BD22*Q22 | BH22: =H22 | BI22: 0.18104824 | BJ22: 0.230447 | BL22: =BH22/F22 | BM22: =BI22*G22/F22 | BN22: =SUM(BL22:BM22) | BP22: =BJ22 | BQ22: =J22/F22 | BR22: =I22/F22 | BS22: =SUM(BP22:BR22) | BU22: =BN22-BS22
B23: CEN_Ethanol_DryMill | C23: Biomass_Corn | D23: 0 | E23: 0.06193 | F23: 3.2587 | G23: 0.7507 | H23: 1.65 | I23: 0 | J23: 0.73836 | K23: =(BM23+(BL23-BP23-BR23))*F23 | L23: =BR23*F23 | M23: 0 | N23: 154043.63 | O23: 79.652567 | Q23: 73.71884 | R23: -6.199254 | S23: 155 | T23: 65.59151 | U23: 31.821489 | V23: 37.986239 | W23: 51.417555 | Y23: 22.465142 | Z23: 13.285634 | AB23: -129.68145 | AC23: -129.68145 | AH23: 15.046749 | AI23: 0 | AJ23: 822.26752 | AK23: 822.26752 | AM23: =B23 | AN23: =C23 | AO23: =SUM(AT23:AZ23)+BB23+BC23 | AP23: =SUM(AT23:AZ23)+BE23+BF23 | AQ23: =AO23/3.6 | AR23: =AP23/3.6 | AS23: =AO23-AP23 | AT23: =D23/F23*Y23*-1 | AU23: =E23/F23*Y23 | AV23: {=_xlfn.IFS(C23="Biomass_Corn", 1/F23*S23, C23="Biomass_Agri", 1/F23*V23, C23="Biomass_Wood", 1/F23*U23, C23="Biomass_Herb", 1/F23*T23)} | AW23: =G23/F23*AH23 | AX23: =M23/F23/(0.9*8760) | AY23: =N23/F23/(0.9*8760) | AZ23: =O23/F23 | BA23: =SUM(BP23:BR23)-BL23 | BB23: =(Q23+R23)*-1*I23/F23 | BC23: =BA23*Q23 | BD23: =SUM(BP23:BQ23)-BL23 | BE23: =I23/F23*-1*R23 | BF23: =BD23*Q23 | BH23: =H23 | BI23: 0.18104824 | BJ23: 0.230447 | BL23: =BH23/F23 | BM23: =BI23*G23/F23 | BN23: =SUM(BL23:BM23) | BP23: =BJ23 | BQ23: =J23/F23 | BR23: =I23/F23 | BS23: =SUM(BP23:BR23) | BU23: =BN23-BS23
B24: NCEN_Ethanol_DryMillCCS_60 | C24: Biomass_Corn | D24: 0 | E24: 0.06193 | F24: 3.2587 | G24: 0.7507 | H24: 1.65 | I24: 0.44301831 | J24: 0.29535 | K24: =(BM24+(BL24-BP24-BR24))*F24 | L24: =BR24*F24 | M24: 0 | N24: 156598.49 | O24: 79.74 | Q24: 73.71884 | R24: -6.097314 | S24: 155 | T24: 61.343403 | U24: 33.004971 | V24: 42.19561 | W24: 51.423576 | Y24: 22.90669 | Z24: 13.197062 | AB24: -129.52898 | AC24: -129.52898 | AH24: 14.953878 | AI24: 0 | AJ24: 822.26752 | AK24: 822.26752 | AM24: =B24 | AN24: =C24 | AO24: =SUM(AT24:AZ24)+BB24+BC24 | AP24: =SUM(AT24:AZ24)+BE24+BF24 | AQ24: =AO24/3.6 | AR24: =AP24/3.6 | AS24: =AO24-AP24 | AT24: =D24/F24*Y24*-1 | AU24: =E24/F24*Y24 | AV24: {=_xlfn.IFS(C24="Biomass_Corn", 1/F24*S24, C24="Biomass_Agri", 1/F24*V24, C24="Biomass_Wood", 1/F24*U24, C24="Biomass_Herb", 1/F24*T24)} | AW24: =G24/F24*AH24 | AX24: =M24/F24/(0.9*8760) | AY24: =N24/F24/(0.9*8760) | AZ24: =O24/F24 | BA24: =SUM(BP24:BR24)-BL24 | BB24: =(Q24+R24)*-1*I24/F24 | BC24: =BA24*Q24 | BD24: =SUM(BP24:BQ24)-BL24 | BE24: =I24/F24*-1*R24 | BF24: =BD24*Q24 | BH24: =H24 | BI24: 0.18104824 | BJ24: 0.230447 | BL24: =BH24/F24 | BM24: =BI24*G24/F24 | BN24: =SUM(BL24:BM24) | BP24: =BJ24 | BQ24: =J24/F24 | BR24: =I24/F24 | BS24: =SUM(BP24:BR24) | BU24: =BN24-BS24
B25: NCEN_Ethanol_DryMillCCS_90 | C25: Biomass_Corn | D25: 0 | E25: 0.4049 | F25: 3.2587 | G25: 0.7507 | H25: 1.65 | I25: 0.66452746 | J25: 0.07384 | K25: =(BM25+(BL25-BP25-BR25))*F25 | L25: =BR25*F25 | M25: 0 | N25: 173741.51 | O25: 80.28 | Q25: 73.71884 | R25: -6.097314 | S25: 155 | T25: 61.343403 | U25: 33.004971 | V25: 42.19561 | W25: 51.423576 | Y25: 22.90669 | Z25: 13.197062 | AB25: -129.52898 | AC25: -129.52898 | AH25: 14.953878 | AI25: 0 | AJ25: 822.26752 | AK25: 822.26752 | AM25: =B25 | AN25: =C25 | AO25: =SUM(AT25:AZ25)+BB25+BC25 | AP25: =SUM(AT25:AZ25)+BE25+BF25 | AQ25: =AO25/3.6 | AR25: =AP25/3.6 | AS25: =AO25-AP25 | AT25: =D25/F25*Y25*-1 | AU25: =E25/F25*Y25 | AV25: {=_xlfn.IFS(C25="Biomass_Corn", 1/F25*S25, C25="Biomass_Agri", 1/F25*V25, C25="Biomass_Wood", 1/F25*U25, C25="Biomass_Herb", 1/F25*T25)} | AW25: =G25/F25*AH25 | AX25: =M25/F25/(0.9*8760) | AY25: =N25/F25/(0.9*8760) | AZ25: =O25/F25 | BA25: =SUM(BP25:BR25)-BL25 | BB25: =(Q25+R25)*-1*I25/F25 | BC25: =BA25*Q25 | BD25: =SUM(BP25:BQ25)-BL25 | BE25: =I25/F25*-1*R25 | BF25: =BD25*Q25 | BH25: =H25 | BI25: 0.18104824 | BJ25: 0.230447 | BL25: =BH25/F25 | BM25: =BI25*G25/F25 | BN25: =SUM(BL25:BM25) | BP25: =BJ25 | BQ25: =J25/F25 | BR25: =I25/F25 | BS25: =SUM(BP25:BR25) | BU25: =BN25-BS25
B26: CEN_Ethanol_DryMillCCS_60 | C26: Biomass_Corn | D26: 0 | E26: 0.06193 | F26: 3.2587 | G26: 0.7507 | H26: 1.65 | I26: 0.44301831 | J26: 0.29535 | K26: =(BM26+(BL26-BP26-BR26))*F26 | L26: =BR26*F26 | M26: 0 | N26: 156598.49 | O26: 79.74 | Q26: 73.71884 | R26: -6.199254 | S26: 155 | T26: 65.59151 | U26: 31.821489 | V26: 37.986239 | W26: 51.417555 | Y26: 22.465142 | Z26: 13.285634 | AB26: -129.68145 | AC26: -129.68145 | AH26: 15.046749 | AI26: 0 | AJ26: 822.26752 | AK26: 822.26752 | AM26: =B26 | AN26: =C26 | AO26: =SUM(AT26:AZ26)+BB26+BC26 | AP26: =SUM(AT26:AZ26)+BE26+BF26 | AQ26: =AO26/3.6 | AR26: =AP26/3.6 | AS26: =AO26-AP26 | AT26: =D26/F26*Y26*-1 | AU26: =E26/F26*Y26 | AV26: {=_xlfn.IFS(C26="Biomass_Corn", 1/F26*S26, C26="Biomass_Agri", 1/F26*V26, C26="Biomass_Wood", 1/F26*U26, C26="Biomass_Herb", 1/F26*T26)} | AW26: =G26/F26*AH26 | AX26: =M26/F26/(0.9*8760) | AY26: =N26/F26/(0.9*8760) | AZ26: =O26/F26 | BA26: =SUM(BP26:BR26)-BL26 | BB26: =(Q26+R26)*-1*I26/F26 | BC26: =BA26*Q26 | BD26: =SUM(BP26:BQ26)-BL26 | BE26: =I26/F26*-1*R26 | BF26: =BD26*Q26 | BH26: =H26 | BI26: 0.18104824 | BJ26: 0.230447 | BL26: =BH26/F26 | BM26: =BI26*G26/F26 | BN26: =SUM(BL26:BM26) | BP26: =BJ26 | BQ26: =J26/F26 | BR26: =I26/F26 | BS26: =SUM(BP26:BR26) | BU26: =BN26-BS26
B27: CEN_Ethanol_DryMillCCS_90 | C27: Biomass_Corn | D27: 0 | E27: 0.4049 | F27: 3.2587 | G27: 0.7507 | H27: 1.65 | I27: 0.66452746 | J27: 0.07384 | K27: =(BM27+(BL27-BP27-BR27))*F27 | L27: =BR27*F27 | M27: 0 | N27: 173741.51 | O27: 80.28 | Q27: 73.71884 | R27: -6.199254 | S27: 155 | T27: 65.59151 | U27: 31.821489 | V27: 37.986239 | W27: 51.417555 | Y27: 22.465142 | Z27: 13.285634 | AB27: -129.68145 | AC27: -129.68145 | AH27: 15.046749 | AI27: 0 | AJ27: 822.26752 | AK27: 822.26752 | AM27: =B27 | AN27: =C27 | AO27: =SUM(AT27:AZ27)+BB27+BC27 | AP27: =SUM(AT27:AZ27)+BE27+BF27 | AQ27: =AO27/3.6 | AR27: =AP27/3.6 | AS27: =AO27-AP27 | AT27: =D27/F27*Y27*-1 | AU27: =E27/F27*Y27 | AV27: {=_xlfn.IFS(C27="Biomass_Corn", 1/F27*S27, C27="Biomass_Agri", 1/F27*V27, C27="Biomass_Wood", 1/F27*U27, C27="Biomass_Herb", 1/F27*T27)} | AW27: =G27/F27*AH27 | AX27: =M27/F27/(0.9*8760) | AY27: =N27/F27/(0.9*8760) | AZ27: =O27/F27 | BA27: =SUM(BP27:BR27)-BL27 | BB27: =(Q27+R27)*-1*I27/F27 | BC27: =BA27*Q27 | BD27: =SUM(BP27:BQ27)-BL27 | BE27: =I27/F27*-1*R27 | BF27: =BD27*Q27 | BH27: =H27 | BI27: 0.18104824 | BJ27: 0.230447 | BL27: =BH27/F27 | BM27: =BI27*G27/F27 | BN27: =SUM(BL27:BM27) | BP27: =BJ27 | BQ27: =J27/F27 | BR27: =I27/F27 | BS27: =SUM(BP27:BR27) | BU27: =BN27-BS27

Sheet lc_summary
B2: LC for bioethanol production $/GJ | R2: Conversion | V2: LC for bioethanol production $/GJ - SORTED
B3: id_LC | C3: commodity_LC | D3: elec_production | E3: elec_consumption | F3: biomass_consumption | G3: natgas_consumption | H3: investment_cost | I3: fixed_om_cost | J3: variable_om_cost | K3: modified capture cost | L3: modified emissions cost | M3: CI | N3: LCOE ($/MWh-ethanol) | O3: LCOE ($/GJ-ethanol) | P3: CHECK LCOE ($/GJ-ethanol) | R3: Conversion | S3: 3.6 | T3: GJ/MWh | V3: id_LC | W3: commodity_LC | X3: elec_production | Y3: elec_consumption | Z3: biomass_consumption | AA3: natgas_consumption | AB3: investment_cost | AC3: fixed_om_cost | AD3: variable_om_cost | AE3: modified capture cost | AF3: modified emissions cost | AG3: CI | AH3: LCOE ($/MWh-ethanol) | AI3: LCOE ($/GJ-ethanol) | AJ3: CHECK LCOE ($/GJ-ethanol)
B4: =lc_detailed!AM4 | C4: =lc_detailed!AN4 | D4: =lc_detailed!AT4/$S$3 | E4: =lc_detailed!AU4/$S$3 | F4: =lc_detailed!AV4/$S$3 | G4: =lc_detailed!AW4/$S$3 | H4: =lc_detailed!AX4/$S$3 | I4: =lc_detailed!AY4/$S$3 | J4: =lc_detailed!AZ4/$S$3 | K4: =lc_detailed!BB4/$S$3 | L4: =lc_detailed!BC4/$S$3 | M4: =lc_detailed!BA4 | N4: =lc_detailed!AO4 | O4: =N4/$S$3 | P4: =SUM(D4:L4) | V4: {=_xlfn._xlws.SORT(B4:P39, 13, 1)} | W4: Biomass_Corn | X4: 0 | Y4: 0.77624875 | Z4: 13.212494 | AA4: 0.96275228 | AB4: 0.39044498 | AC4: 1.8784952 | AD4: 6.8432197 | AE4: -3.824994 | AF4: -1.0097342 | AG4: -0.049306441 | AH4: 69.224137 | AI4: 19.228927 | AJ4: 19.228927
B5: =lc_detailed!AM5 | C5: =lc_detailed!AN5 | D5: =lc_detailed!AT5/$S$3 | E5: =lc_detailed!AU5/$S$3 | F5: =lc_detailed!AV5/$S$3 | G5: =lc_detailed!AW5/$S$3 | H5: =lc_detailed!AX5/$S$3 | I5: =lc_detailed!AY5/$S$3 | J5: =lc_detailed!AZ5/$S$3 | K5: =lc_detailed!BB5/$S$3 | L5: =lc_detailed!BC5/$S$3 | M5: =lc_detailed!BA5 | N5: =lc_detailed!AO5 | O5: =N5/$S$3 | P5: =SUM(D5:L5) | V5: NCEN_Ethanol_DryMillCCS_90 | W5: Biomass_Corn | X5: 0 | Y5: 0.79439624 | Z5: 13.212494 | AA5: 0.95568747 | AB5: 0.39044498 | AC5: 1.8784952 | AD5: 6.8432197 | AE5: -3.8312271 | AF5: -1.0097342 | AG5: -0.049306441 | AH5: 69.241596 | AI5: 19.233777 | AJ5: 19.233777
B6: =lc_detailed!AM6 | C6: =lc_detailed!AN6 | D6: =lc_detailed!AT6/$S$3 | E6: =lc_detailed!AU6/$S$3 | F6: =lc_detailed!AV6/$S$3 | G6: =lc_detailed!AW6/$S$3 | H6: =lc_detailed!AX6/$S$3 | I6: =lc_detailed!AY6/$S$3 | J6: =lc_detailed!AZ6/$S$3 | K6: =lc_detailed!BB6/$S$3 | L6: =lc_detailed!BC6/$S$3 | M6: =lc_detailed!BA6 | N6: =lc_detailed!AO6 | O6: =N6/$S$3 | P6: =SUM(D6:L6) | V6: NCEN_Ethanol_DryMillCCS_60 | W6: Biomass_Corn | X6: 0 | Y6: 0.12150397 | Z6: 13.212494 | AA6: 0.95568747 | AB6: 0.051656656 | AC6: 1.6931447 | AD6: 6.7971891 | AE6: -2.5541514 | AF6: -1.0097289 | AG6: -0.049306181 | AH6: 69.364065 | AI6: 19.267796 | AJ6: 19.267796
B7: =lc_detailed!AM7 | C7: =lc_detailed!AN7 | D7: =lc_detailed!AT7/$S$3 | E7: =lc_detailed!AU7/$S$3 | F7: =lc_detailed!AV7/$S$3 | G7: =lc_detailed!AW7/$S$3 | H7: =lc_detailed!AX7/$S$3 | I7: =lc_detailed!AY7/$S$3 | J7: =lc_detailed!AZ7/$S$3 | K7: =lc_detailed!BB7/$S$3 | L7: =lc_detailed!BC7/$S$3 | M7: =lc_detailed!BA7 | N7: =lc_detailed!AO7 | O7: =N7/$S$3 | P7: =SUM(D7:L7) | V7: CEN_Ethanol_DryMillCCS_60 | W7: Biomass_Corn | X7: 0 | Y7: 0.11872829 | Z7: 13.212494 | AA7: 0.96275228 | AB7: 0.051656656 | AC7: 1.6931447 | AD7: 6.7971891 | AE7: -2.549996 | AF7: -1.0097289 | AG7: -0.049306181 | AH7: 69.394466 | AI7: 19.27624 | AJ7: 19.27624
B8: =lc_detailed!AM8 | C8: =lc_detailed!AN8 | D8: =lc_detailed!AT8/$S$3 | E8: =lc_detailed!AU8/$S$3 | F8: =lc_detailed!AV8/$S$3 | G8: =lc_detailed!AW8/$S$3 | H8: =lc_detailed!AX8/$S$3 | I8: =lc_detailed!AY8/$S$3 | J8: =lc_detailed!AZ8/$S$3 | K8: =lc_detailed!BB8/$S$3 | L8: =lc_detailed!BC8/$S$3 | M8: =lc_detailed!BA8 | N8: =lc_detailed!AO8 | O8: =N8/$S$3 | P8: =SUM(D8:L8) | V8: NCEN_Ethanol_DryMill | W8: Biomass_Corn | X8: 0 | Y8: 0.12150397 | Z8: 13.212494 | AA8: 0.95568747 | AB8: 0 | AC8: 1.6655215 | AD8: 6.7897361 | AE8: 0 | AF8: -1.0097811 | AG8: -0.049308731 | AH8: 78.246584 | AI8: 21.735162 | AJ8: 21.735162
B9: =lc_detailed!AM9 | C9: =lc_detailed!AN9 | D9: =lc_detailed!AT9/$S$3 | E9: =lc_detailed!AU9/$S$3 | F9: =lc_detailed!AV9/$S$3 | G9: =lc_detailed!AW9/$S$3 | H9: =lc_detailed!AX9/$S$3 | I9: =lc_detailed!AY9/$S$3 | J9: =lc_detailed!AZ9/$S$3 | K9: =lc_detailed!BB9/$S$3 | L9: =lc_detailed!BC9/$S$3 | M9: =lc_detailed!BA9 | N9: =lc_detailed!AO9 | O9: =N9/$S$3 | P9: =SUM(D9:L9) | V9: CEN_Ethanol_DryMill | W9: Biomass_Corn | X9: 0 | Y9: 0.11872829 | Z9: 13.212494 | AA9: 0.96275228 | AB9: 0 | AC9: 1.6655215 | AD9: 6.7897361 | AE9: 0 | AF9: -1.0097811 | AG9: -0.049308731 | AH9: 78.262025 | AI9: 21.739451 | AJ9: 21.739451
B10: =lc_detailed!AM10 | C10: =lc_detailed!AN10 | D10: =lc_detailed!AT10/$S$3 | E10: =lc_detailed!AU10/$S$3 | F10: =lc_detailed!AV10/$S$3 | G10: =lc_detailed!AW10/$S$3 | H10: =lc_detailed!AX10/$S$3 | I10: =lc_detailed!AY10/$S$3 | J10: =lc_detailed!AZ10/$S$3 | K10: =lc_detailed!BB10/$S$3 | L10: =lc_detailed!BC10/$S$3 | M10: =lc_detailed!BA10 | N10: =lc_detailed!AO10 | O10: =N10/$S$3 | P10: =SUM(D10:L10) | V10: CA_Biochemical_CCS_86 | W10: Biomass_Agri | X10: -0.44277461 | Y10: 0.9382347 | Z10: 6.5194552 | AA10: 0 | AB10: 16.517339 | AC10: 5.3058342 | AD10: 10.191215 | AE10: -11.407335 | AF10: -0.034328185 | AG10: -0.0016762833 | AH10: 99.315508 | AI10: 27.587641 | AJ10: 27.587641
B11: =lc_detailed!AM11 | C11: =lc_detailed!AN11 | D11: =lc_detailed!AT11/$S$3 | E11: =lc_detailed!AU11/$S$3 | F11: =lc_detailed!AV11/$S$3 | G11: =lc_detailed!AW11/$S$3 | H11: =lc_detailed!AX11/$S$3 | I11: =lc_detailed!AY11/$S$3 | J11: =lc_detailed!AZ11/$S$3 | K11: =lc_detailed!BB11/$S$3 | L11: =lc_detailed!BC11/$S$3 | M11: =lc_detailed!BA11 | N11: =lc_detailed!AO11 | O11: =N11/$S$3 | P11: =SUM(D11:L11) | V11: NW_Biochemical_CCS_86 | W11: Biomass_Agri | X11: -0.44008372 | Y11: 0.93253274 | Z11: 7.3637241 | AA11: 0 | AB11: 16.517339 | AC11: 5.3058342 | AD11: 10.191215 | AE11: -11.794796 | AF11: -0.034328185 | AG11: -0.0016762833 | AH11: 100.94917 | AI11: 28.041437 | AJ11: 28.041437
B12: =lc_detailed!AM12 | C12: =lc_detailed!AN12 | D12: =lc_detailed!AT12/$S$3 | E12: =lc_detailed!AU12/$S$3 | F12: =lc_detailed!AV12/$S$3 | G12: =lc_detailed!AW12/$S$3 | H12: =lc_detailed!AX12/$S$3 | I12: =lc_detailed!AY12/$S$3 | J12: =lc_detailed!AZ12/$S$3 | K12: =lc_detailed!BB12/$S$3 | L12: =lc_detailed!BC12/$S$3 | M12: =lc_detailed!BA12 | N12: =lc_detailed!AO12 | O12: =N12/$S$3 | P12: =SUM(D12:L12) | V12: SW_Biochemical_CCS_86 | W12: Biomass_Agri | X12: -0.46138555 | Y12: 0.97767109 | Z12: 6.1613871 | AA12: 0 | AB12: 16.517339 | AC12: 5.3058342 | AD12: 10.191215 | AE12: -10.307754 | AF12: -0.034328185 | AG12: -0.0016762833 | AH12: 102.05992 | AI12: 28.349979 | AJ12: 28.349979
B13: =lc_detailed!AM13 | C13: =lc_detailed!AN13 | D13: =lc_detailed!AT13/$S$3 | E13: =lc_detailed!AU13/$S$3 | F13: =lc_detailed!AV13/$S$3 | G13: =lc_detailed!AW13/$S$3 | H13: =lc_detailed!AX13/$S$3 | I13: =lc_detailed!AY13/$S$3 | J13: =lc_detailed!AZ13/$S$3 | K13: =lc_detailed!BB13/$S$3 | L13: =lc_detailed!BC13/$S$3 | M13: =lc_detailed!BA13 | N13: =lc_detailed!AO13 | O13: =N13/$S$3 | P13: =SUM(D13:L13) | V13: TX_Biochemical_CCS_86 | W13: Biomass_Agri | X13: -0.46992278 | Y13: 0.99576139 | Z13: 6.580517 | AA13: 0 | AB13: 16.517339 | AC13: 5.3058342 | AD13: 10.191215 | AE13: -10.216707 | AF13: -0.034328185 | AG13: -0.0016762833 | AH13: 103.93095 | AI13: 28.869709 | AJ13: 28.869709
B14: =lc_detailed!AM14 | C14: =lc_detailed!AN14 | D14: =lc_detailed!AT14/$S$3 | E14: =lc_detailed!AU14/$S$3 | F14: =lc_detailed!AV14/$S$3 | G14: =lc_detailed!AW14/$S$3 | H14: =lc_detailed!AX14/$S$3 | I14: =lc_detailed!AY14/$S$3 | J14: =lc_detailed!AZ14/$S$3 | K14: =lc_detailed!BB14/$S$3 | L14: =lc_detailed!BC14/$S$3 | M14: =lc_detailed!BA14 | N14: =lc_detailed!AO14 | O14: =N14/$S$3 | P14: =SUM(D14:L14) | V14: SE_Biochemical_CCS_86 | W14: Biomass_Agri | X14: -0.46721578 | Y14: 0.99002529 | Z14: 6.7355888 | AA14: 0 | AB14: 16.517339 | AC14: 5.3058342 | AD14: 10.191215 | AE14: -10.054759 | AF14: -0.034328185 | AG14: -0.0016762833 | AH14: 105.06132 | AI14: 29.1837 | AJ14: 29.1837
B15: =lc_detailed!AM15 | C15: =lc_detailed!AN15 | D15: =lc_detailed!AT15/$S$3 | E15: =lc_detailed!AU15/$S$3 | F15: =lc_detailed!AV15/$S$3 | G15: =lc_detailed!AW15/$S$3 | H15: =lc_detailed!AX15/$S$3 | I15: =lc_detailed!AY15/$S$3 | J15: =lc_detailed!AZ15/$S$3 | K15: =lc_detailed!BB15/$S$3 | L15: =lc_detailed!BC15/$S$3 | M15: =lc_detailed!BA15 | N15: =lc_detailed!AO15 | O15: =N15/$S$3 | P15: =SUM(D15:L15) | V15: CEN_Biochemical_CCS_86 | W15: Biomass_Agri | X15: -0.49426321 | Y15: 1.0473385 | Z15: 7.2653284 | AA15: 0 | AB15: 16.517339 | AC15: 5.3058342 | AD15: 10.191215 | AE15: -10.038215 | AF15: -0.034328185 | AG15: -0.0016762833 | AH15: 107.1369 | AI15: 29.760249 | AJ15: 29.760249
B16: =lc_detailed!AM16 | C16: =lc_detailed!AN16 | D16: =lc_detailed!AT16/$S$3 | E16: =lc_detailed!AU16/$S$3 | F16: =lc_detailed!AV16/$S$3 | G16: =lc_detailed!AW16/$S$3 | H16: =lc_detailed!AX16/$S$3 | I16: =lc_detailed!AY16/$S$3 | J16: =lc_detailed!AZ16/$S$3 | K16: =lc_detailed!BB16/$S$3 | L16: =lc_detailed!BC16/$S$3 | M16: =lc_detailed!BA16 | N16: =lc_detailed!AO16 | O16: =N16/$S$3 | P16: =SUM(D16:L16) | V16: NCEN_Biochemical_CCS_86 | W16: Biomass_Agri | X16: -0.50581831 | Y16: 1.0718236 | Z16: 7.4620602 | AA16: 0 | AB16: 16.517339 | AC16: 5.3058342 | AD16: 10.191215 | AE16: -10.054573 | AF16: -0.034328185 | AG16: -0.0016762833 | AH16: 107.83279 | AI16: 29.953553 | AJ16: 29.953553
... B27: =lc_detailed!AM27 | C27: =lc_detailed!AN27 | D27: =lc_detailed!AT27/$S$3 | E27: =lc_detailed!AU27/$S$3 | F27: =lc_detailed!AV27/$S$3 | G27: =lc_detailed!AW27/$S$3 | H27: =lc_detailed!AX27/$S$3 | I27: =lc_detailed!AY27/$S$3 | J27: =lc_detailed!AZ27/$S$3 | K27: =lc_detailed!BB27/$S$3 | L27: =lc_detailed!BC27/$S$3 | M27: =lc_detailed!BA27 | N27: =lc_detailed!AO27 | O27: =N27/$S$3 | P27: =SUM(D27:L27) | V27: NE_Biochemical_CCS_20 | W27: Biomass_Agri | X27: -0.45689015 | Y27: 0 | Z27: 7.1682935 | AA27: 0 | AB27: 14.951267 | AC27: 4.4490389 | AD27: 9.9780772 | AE27: -1.7715716 | AF27: -0.034328185 | AG27: -0.0016762833 | AH27: 123.42199 | AI27: 34.283887 | AJ27: 34.283887
V28: 0 | W28: 0 | X28: 0 | Y28: 0 | Z28: 0 | AA28: 0 | AB28: 0 | AC28: 0 | AD28: 0 | AE28: 0 | AF28: 0 | AG28: 0 | AH28: 0 | AI28: 0 | AJ28: 0
V29: 0 | W29: 0 | X29: 0 | Y29: 0 | Z29: 0 | AA29: 0 | AB29: 0 | AC29: 0 | AD29: 0 | AE29: 0 | AF29: 0 | AG29: 0 | AH29: 0 | AI29: 0 | AJ29: 0
V30: 0 | W30: 0 | X30: 0 | Y30: 0 | Z30: 0 | AA30: 0 | AB30: 0 | AC30: 0 | AD30: 0 | AE30: 0 | AF30: 0 | AG30: 0 | AH30: 0 | AI30: 0 | AJ30: 0
V31: 0 | W31: 0 | X31: 0 | Y31: 0 | Z31: 0 | AA31: 0 | AB31: 0 | AC31: 0 | AD31: 0 | AE31: 0 | AF31: 0 | AG31: 0 | AH31: 0 | AI31: 0 | AJ31: 0
V32: 0 | W32: 0 | X32: 0 | Y32: 0 | Z32: 0 | AA32: 0 | AB32: 0 | AC32: 0 | AD32: 0 | AE32: 0 | AF32: 0 | AG32: 0 | AH32: 0 | AI32: 0 | AJ32: 0
V33: 0 | W33: 0 | X33: 0 | Y33: 0 | Z33: 0 | AA33: 0 | AB33: 0 | AC33: 0 | AD33: 0 | AE33: 0 | AF33: 0 | AG33: 0 | AH33: 0 | AI33: 0 | AJ33: 0
V34: 0 | W34: 0 | X34: 0 | Y34: 0 | Z34: 0 | AA34: 0 | AB34: 0 | AC34: 0 | AD34: 0 | AE34: 0 | AF34: 0 | AG34: 0 | AH34: 0 | AI34: 0 | AJ34: 0
V35: 0 | W35: 0 | X35: 0 | Y35: 0 | Z35: 0 | AA35: 0 | AB35: 0 | AC35: 0 | AD35: 0 | AE35: 0 | AF35: 0 | AG35: 0 | AH35: 0 | AI35: 0 | AJ35: 0
V36: 0 | W36: 0 | X36: 0 | Y36: 0 | Z36: 0 | AA36: 0 | AB36: 0 | AC36: 0 | AD36: 0 | AE36: 0 | AF36: 0 | AG36: 0 | AH36: 0 | AI36: 0 | AJ36: 0
V37: 0 | W37: 0 | X37: 0 | Y37: 0 | Z37: 0 | AA37: 0 | AB37: 0 | AC37: 0 | AD37: 0 | AE37: 0 | AF37: 0 | AG37: 0 | AH37: 0 | AI37: 0 | AJ37: 0
V38: 0 | W38: 0 | X38: 0 | Y38: 0 | Z38: 0 | AA38: 0 | AB38: 0 | AC38: 0 | AD38: 0 | AE38: 0 | AF38: 0 | AG38: 0 | AH38: 0 | AI38: 0 | AJ38: 0
V39: 0 | W39: 0 | X39: 0 | Y39: 0 | Z39: 0 | AA39: 0 | AB39: 0 | AC39: 0 | AD39: 0 | AE39: 0 | AF39: 0 | AG39: 0 | AH39: 0 | AI39: 0 | AJ39: 0
