Workbook

Sheet lc_detailed
B2: Asset Parameters (normalized by commodity feedstock) | Q2: Duals | Z2: LCOE for ethanol production ($/MWh-ethanol) | AB2: CI | AC2: CREDIT | AL2: NET CARBON INTENSITY + credit for capture | AO2: CREDIT for capture/storage + PAY for storage | AS2: Carbon Content | AW2: Carbon Inputs | AZ2: Carbon Outputs | BF2: Sanity Checks
B3: id | C3: commodity | D3: elec_production (MWh/t-bio) | E3: elec_consumption (MWh/t-bio) | F3: ethanol_production (MWh-ethanol/t-bio) | G3: natgas_consumption (MWh/t-bio) | H3: co2_biomass_content (t-CO2/t-bio) | I3: process_capture_rate (t-CO2/t-bio) | J3: process_emission_rate (t-CO2/t-bio) | K3: fuel_capture_rate (t-CO2/t-bio) | L3: fuel_emission_rate (t-CO2/t-bio) | M3: investment_cost ($/yr per t-bio/hr) | N3: fixed_om_cost ($/yr per t-bio/hr) | O3: variable_om_cost ($/t-bio) | Q3: co2_sink ($/t) | R3: co2_captured ($/t) | S3: biocorn_supply ($/t) | T3: bioherb_supply ($/t) | U3: biowood_supply ($/t) | V3: bioagri_supply ($/t) | W3: elec_demand ($/MWh) | X3: ng_balance ($/MWh) | Z3: id_LC | AA3: commodity_LC | AB3: LCOE ($/MWh-ethanol) | AC3: LCOE ($/MWh-ethanol) | AD3: Diff. Between Methods ($/MWh) | AE3: elec_production | AF3: elec_consumption | AG3: biomass_consumption | AH3: natgas_consumption | AI3: investment_cost | AJ3: fixed_om_cost | AK3: variable_om_cost | AL3: CI | AM3: modified capture cost | AN3: modified emissions cost | AO3: CI | AP3: modified capture cost | AQ3: modified emissions cost | AS3: Biomass CO2 content (t-CO2/t-bio) | AT3: NG (t-CO2/MWh-NG) | AU3: Ethanol (t-CO2/MWh-ethanol) | AW3: Biomass (t-CO2/MWh-ethanol) | AX3: NG (t-CO2/MWh-ethanol) | AZ3: Ethanol (t-CO2/MWh-ethanol) | BA3: Process Emissions (t-CO2/MWh-ethanol) | BB3: Fuel Emissions (t-CO2/MWh-ethanol) | BC3: Process Captured (t-CO2/MWh-ethanol) | BD3: Fuel Captured (t-CO2/MWh-ethanol) | BF3: Carbon INPUT - OUTPUT
B4: CEN_Bio_Ethanol_Herb | C4: Biomass_Herb | D4: 0.2142 | E4: 0 | F4: 1.9848 | G4: 0 | H4: 1.723 | I4: 0 | J4: 1.2657602 | K4: 0 | L4: 0 | M4: 273134.22 | N4: 144062.46 | O4: 0.45 | Q4: 109.47979 | R4: -31.70346 | S4: 170 | T4: 110.46152 | U4: 127.40875 | V4: 98.832478 | W4: 25.324637 | X4: 13.421913 | Z4: =B4 | AA4: =C4 | AB4: =SUM(AE4:AK4)+AM4+AN4 | AC4: =SUM(AE4:AK4)+AP4+AQ4 | AD4: =AB4-AC4 | AE4: =D4/F4*W4*-1 | AF4: =E4/F4*W4 | AG4: {=_xlfn.IFS(C4="Biomass_Corn", 1/F4*S4, C4="Biomass_Agri", 1/F4*V4, C4="Biomass_Wood", 1/F4*U4, C4="Biomass_Herb", 1/F4*T4)} | AH4: =G4/F4*X4 | AI4: =M4/F4/(0.9*8760) | AJ4: =N4/F4/(0.9*8760) | AK4: =O4/F4 | AL4: =SUM(AZ4:BD4)-AW4 | AM4: =(Q4+R4)*-1*(I4+K4)/F4 | AN4: =AL4*Q4 | AO4: =SUM(AZ4:BB4)-AW4 | AP4: =(I4+K4)/F4*-1*R4 | AQ4: =AO4*Q4 | AS4: =H4 | AT4: 0.18289084 | AU4: 0.23037491 | AW4: =AS4/F4 | AX4: =AT4*G4/F4 | AZ4: =AU4 | BA4: =J4/F4 | BB4: =L4/F4 | BC4: =I4/F4 | BD4: =K4/F4 | BF4: =SUM(AW4:AX4)-SUM(AZ4:BD4)
B5: MIDAT_Bio_Ethanol_Herb | C5: Biomass_Herb | D5: 0.215 | E5: 0 | F5: 1.9924 | G5: 0 | H5: 1.736 | I5: 0 | J5: 1.2770045 | K5: 0 | L5: 0 | M5: 273134.22 | N5: 144062.46 | O5: 0.45 | Q5: 109.47979 | R5: -54.115443 | S5: 170 | T5: 100.77374 | U5: 108.66807 | V5: 89.424565 | W5: 39.359472 | X5: 13.423122 | Z5: =B5 | AA5: =C5 | AB5: =SUM(AE5:AK5)+AM5+AN5 | AC5: =SUM(AE5:AK5)+AP5+AQ5 | AD5: =AB5-AC5 | AE5: =D5/F5*W5*-1 | AF5: =E5/F5*W5 | AG5: {=_xlfn.IFS(C5="Biomass_Corn", 1/F5*S5, C5="Biomass_Agri", 1/F5*V5, C5="Biomass_Wood", 1/F5*U5, C5="Biomass_Herb", 1/F5*T5)} | AH5: =G5/F5*X5 | AI5: =M5/F5/(0.9*8760) | AJ5: =N5/F5/(0.9*8760) | AK5: =O5/F5 | AL5: =SUM(AZ5:BD5)-AW5 | AM5: =(Q5+R5)*-1*(I5+K5)/F5 | AN5: =AL5*Q5 | AO5: =SUM(AZ5:BB5)-AW5 | AP5: =(I5+K5)/F5*-1*R5 | AQ5: =AO5*Q5 | AS5: =H5 | AT5: 0.18289084 | AU5: 0.23037491 | AW5: =AS5/F5 | AX5: =AT5*G5/F5 | AZ5: =AU5 | BA5: =J5/F5 | BB5: =L5/F5 | BC5: =I5/F5 | BD5: =K5/F5 | BF5: =SUM(AW5:AX5)-SUM(AZ5:BD5)
B6: NCEN_Bio_Ethanol_Herb | C6: Biomass_Herb | D6: 0.2155 | E6: 0 | F6: 1.9967 | G6: 0 | H6: 1.74 | I6: 0 | J6: 1.2800012 | K6: 0 | L6: 0 | M6: 273134.22 | N6: 144062.46 | O6: 0.45 | Q6: 109.47979 | R6: -41.717135 | S6: 170 | T6: 104.16738 | U6: 115.52639 | V6: 92.044978 | W6: 30.708173 | X6: 13.422003 | Z6: =B6 | AA6: =C6 | AB6: =SUM(AE6:AK6)+AM6+AN6 | AC6: =SUM(AE6:AK6)+AP6+AQ6 | AD6: =AB6-AC6 | AE6: =D6/F6*W6*-1 | AF6: =E6/F6*W6 | AG6: {=_xlfn.IFS(C6="Biomass_Corn", 1/F6*S6, C6="Biomass_Agri", 1/F6*V6, C6="Biomass_Wood", 1/F6*U6, C6="Biomass_Herb", 1/F6*T6)} | AH6: =G6/F6*X6 | AI6: =M6/F6/(0.9*8760) | AJ6: =N6/F6/(0.9*8760) | AK6: =O6/F6 | AL6: =SUM(AZ6:BD6)-AW6 | AM6: =(Q6+R6)*-1*(I6+K6)/F6 | AN6: =AL6*Q6 | AO6: =SUM(AZ6:BB6)-AW6 | AP6: =(I6+K6)/F6*-1*R6 | AQ6: =AO6*Q6 | AS6: =H6 | AT6: 0.18289084 | AU6: 0.23037491 | AW6: =AS6/F6 | AX6: =AT6*G6/F6 | AZ6: =AU6 | BA6: =J6/F6 | BB6: =L6/F6 | BC6: =I6/F6 | BD6: =K6/F6 | BF6: =SUM(AW6:AX6)-SUM(AZ6:BD6)
B7: SE_Bio_Ethanol_Herb | C7: Biomass_Herb | D7: 0.2138 | E7: 0 | F7: 1.9815 | G7: 0 | H7: 1.717 | I7: 0 | J7: 1.2605127 | K7: 0 | L7: 0 | M7: 273134.22 | N7: 144062.46 | O7: 0.45 | Q7: 109.47979 | R7: -47.70091 | S7: 170 | T7: 99.632843 | U7: 113.22702 | V7: 88.855315 | W7: 38.218446 | X7: 13.421908 | Z7: =B7 | AA7: =C7 | AB7: =SUM(AE7:AK7)+AM7+AN7 | AC7: =SUM(AE7:AK7)+AP7+AQ7 | AD7: =AB7-AC7 | AE7: =D7/F7*W7*-1 | AF7: =E7/F7*W7 | AG7: {=_xlfn.IFS(C7="Biomass_Corn", 1/F7*S7, C7="Biomass_Agri", 1/F7*V7, C7="Biomass_Wood", 1/F7*U7, C7="Biomass_Herb", 1/F7*T7)} | AH7: =G7/F7*X7 | AI7: =M7/F7/(0.9*8760) | AJ7: =N7/F7/(0.9*8760) | AK7: =O7/F7 | AL7: =SUM(AZ7:BD7)-AW7 | AM7: =(Q7+R7)*-1*(I7+K7)/F7 | AN7: =AL7*Q7 | AO7: =SUM(AZ7:BB7)-AW7 | AP7: =(I7+K7)/F7*-1*R7 | AQ7: =AO7*Q7 | AS7: =H7 | AT7: 0.18289084 | AU7: 0.23037491 | AW7: =AS7/F7 | AX7: =AT7*G7/F7 | AZ7: =AU7 | BA7: =J7/F7 | BB7: =L7/F7 | BC7: =I7/F7 | BD7: =K7/F7 | BF7: =SUM(AW7:AX7)-SUM(AZ7:BD7)
B8: TX_Bio_Ethanol_Herb | C8: Biomass_Herb | D8: 0.2132 | E8: 0 | F8: 1.9761 | G8: 0 | H8: 1.714 | I8: 0 | J8: 1.2587667 | K8: 0 | L8: 0 | M8: 273134.22 | N8: 144062.46 | O8: 0.45 | Q8: 109.47979 | R8: -21.506692 | S8: 170 | T8: 137.93465 | U8: 157.88135 | V8: 111.36485 | W8: 20.230252 | X8: 13.325948 | Z8: =B8 | AA8: =C8 | AB8: =SUM(AE8:AK8)+AM8+AN8 | AC8: =SUM(AE8:AK8)+AP8+AQ8 | AD8: =AB8-AC8 | AE8: =D8/F8*W8*-1 | AF8: =E8/F8*W8 | AG8: {=_xlfn.IFS(C8="Biomass_Corn", 1/F8*S8, C8="Biomass_Agri", 1/F8*V8, C8="Biomass_Wood", 1/F8*U8, C8="Biomass_Herb", 1/F8*T8)} | AH8: =G8/F8*X8 | AI8: =M8/F8/(0.9*8760) | AJ8: =N8/F8/(0.9*8760) | AK8: =O8/F8 | AL8: =SUM(AZ8:BD8)-AW8 | AM8: =(Q8+R8)*-1*(I8+K8)/F8 | AN8: =AL8*Q8 | AO8: =SUM(AZ8:BB8)-AW8 | AP8: =(I8+K8)/F8*-1*R8 | AQ8: =AO8*Q8 | AS8: =H8 | AT8: 0.18289084 | AU8: 0.23037491 | AW8: =AS8/F8 | AX8: =AT8*G8/F8 | AZ8: =AU8 | BA8: =J8/F8 | BB8: =L8/F8 | BC8: =I8/F8 | BD8: =K8/F8 | BF8: =SUM(AW8:AX8)-SUM(AZ8:BD8)
B9: CEN_Bio_Ethanol_Wood | C9: Biomass_Wood | D9: 0.2241 | E9: 0 | F9: 2.0762 | G9: 0 | H9: 1.802 | I9: 0 | J9: 1.3236916 | K9: 0 | L9: 0 | M9: 273134.22 | N9: 144062.46 | O9: 0.45 | Q9: 109.47979 | R9: -31.70346 | S9: 170 | T9: 110.46152 | U9: 127.40875 | V9: 98.832478 | W9: 25.324637 | X9: 13.421913 | Z9: =B9 | AA9: =C9 | AB9: =SUM(AE9:AK9)+AM9+AN9 | AC9: =SUM(AE9:AK9)+AP9+AQ9 | AD9: =AB9-AC9 | AE9: =D9/F9*W9*-1 | AF9: =E9/F9*W9 | AG9: {=_xlfn.IFS(C9="Biomass_Corn", 1/F9*S9, C9="Biomass_Agri", 1/F9*V9, C9="Biomass_Wood", 1/F9*U9, C9="Biomass_Herb", 1/F9*T9)} | AH9: =G9/F9*X9 | AI9: =M9/F9/(0.9*8760) | AJ9: =N9/F9/(0.9*8760) | AK9: =O9/F9 | AL9: =SUM(AZ9:BD9)-AW9 | AM9: =(Q9+R9)*-1*(I9+K9)/F9 | AN9: =AL9*Q9 | AO9: =SUM(AZ9:BB9)-AW9 | AP9: =(I9+K9)/F9*-1*R9 | AQ9: =AO9*Q9 | AS9: =H9 | AT9: 0.18289084 | AU9: 0.23037491 | AW9: =AS9/F9 | AX9: =AT9*G9/F9 | AZ9: =AU9 | BA9: =J9/F9 | BB9: =L9/F9 | BC9: =I9/F9 | BD9: =K9/F9 | BF9: =SUM(AW9:AX9)-SUM(AZ9:BD9)
B10: MIDAT_Bio_Ethanol_Wood | C10: Biomass_Wood | D10: 0.2233 | E10: 0 | F10: 2.0697 | G10: 0 | H10: 1.806 | I10: 0 | J10: 1.3291965 | K10: 0 | L10: 0 | M10: 273134.22 | N10: 144062.46 | O10: 0.45 | Q10: 109.47979 | R10: -54.115443 | S10: 170 | T10: 100.77374 | U10: 108.66807 | V10: 89.424565 | W10: 39.359472 | X10: 13.423122 | Z10: =B10 | AA10: =C10 | AB10: =SUM(AE10:AK10)+AM10+AN10 | AC10: =SUM(AE10:AK10)+AP10+AQ10 | AD10: =AB10-AC10 | AE10: =D10/F10*W10*-1 | AF10: =E10/F10*W10 | AG10: {=_xlfn.IFS(C10="Biomass_Corn", 1/F10*S10, C10="Biomass_Agri", 1/F10*V10, C10="Biomass_Wood", 1/F10*U10, C10="Biomass_Herb", 1/F10*T10)} | AH10: =G10/F10*X10 | AI10: =M10/F10/(0.9*8760) | AJ10: =N10/F10/(0.9*8760) | AK10: =O10/F10 | AL10: =SUM(AZ10:BD10)-AW10 | AM10: =(Q10+R10)*-1*(I10+K10)/F10 | AN10: =AL10*Q10 | AO10: =SUM(AZ10:BB10)-AW10 | AP10: =(I10+K10)/F10*-1*R10 | AQ10: =AO10*Q10 | AS10: =H10 | AT10: 0.18289084 | AU10: 0.23037491 | AW10: =AS10/F10 | AX10: =AT10*G10/F10 | AZ10: =AU10 | BA10: =J10/F10 | BB10: =L10/F10 | BC10: =I10/F10 | BD10: =K10/F10 | BF10: =SUM(AW10:AX10)-SUM(AZ10:BD10)
B11: NCEN_Bio_Ethanol_Wood | C11: Biomass_Wood | D11: 0.2239 | E11: 0 | F11: 2.0751 | G11: 0 | H11: 1.802 | I11: 0 | J11: 1.3239424 | K11: 0 | L11: 0 | M11: 273134.22 | N11: 144062.46 | O11: 0.45 | Q11: 109.47979 | R11: -41.717135 | S11: 170 | T11: 104.16738 | U11: 115.52639 | V11: 92.044978 | W11: 30.708173 | X11: 13.422003 | Z11: =B11 | AA11: =C11 | AB11: =SUM(AE11:AK11)+AM11+AN11 | AC11: =SUM(AE11:AK11)+AP11+AQ11 | AD11: =AB11-AC11 | AE11: =D11/F11*W11*-1 | AF11: =E11/F11*W11 | AG11: {=_xlfn.IFS(C11="Biomass_Corn", 1/F11*S11, C11="Biomass_Agri", 1/F11*V11, C11="Biomass_Wood", 1/F11*U11, C11="Biomass_Herb", 1/F11*T11)} | AH11: =G11/F11*X11 | AI11: =M11/F11/(0.9*8760) | AJ11: =N11/F11/(0.9*8760) | AK11: =O11/F11 | AL11: =SUM(AZ11:BD11)-AW11 | AM11: =(Q11+R11)*-1*(I11+K11)/F11 | AN11: =AL11*Q11 | AO11: =SUM(AZ11:BB11)-AW11 | AP11: =(I11+K11)/F11*-1*R11 | AQ11: =AO11*Q11 | AS11: =H11 | AT11: 0.18289084 | AU11: 0.23037491 | AW11: =AS11/F11 | AX11: =AT11*G11/F11 | AZ11: =AU11 | BA11: =J11/F11 | BB11: =L11/F11 | BC11: =I11/F11 | BD11: =K11/F11 | BF11: =SUM(AW11:AX11)-SUM(AZ11:BD11)
B12: SE_Bio_Ethanol_Wood | C12: Biomass_Wood | D12: 0.2249 | E12: 0 | F12: 2.0838 | G12: 0 | H12: 1.821 | I12: 0 | J12: 1.3409358 | K12: 0 | L12: 0 | M12: 273134.22 | N12: 144062.46 | O12: 0.45 | Q12: 109.47979 | R12: -47.70091 | S12: 170 | T12: 99.632843 | U12: 113.22702 | V12: 88.855315 | W12: 38.218446 | X12: 13.421908 | Z12: =B12 | AA12: =C12 | AB12: =SUM(AE12:AK12)+AM12+AN12 | AC12: =SUM(AE12:AK12)+AP12+AQ12 | AD12: =AB12-AC12 | AE12: =D12/F12*W12*-1 | AF12: =E12/F12*W12 | AG12: {=_xlfn.IFS(C12="Biomass_Corn", 1/F12*S12, C12="Biomass_Agri", 1/F12*V12, C12="Biomass_Wood", 1/F12*U12, C12="Biomass_Herb", 1/F12*T12)} | AH12: =G12/F12*X12 | AI12: =M12/F12/(0.9*8760) | AJ12: =N12/F12/(0.9*8760) | AK12: =O12/F12 | AL12: =SUM(AZ12:BD12)-AW12 | AM12: =(Q12+R12)*-1*(I12+K12)/F12 | AN12: =AL12*Q12 | AO12: =SUM(AZ12:BB12)-AW12 | AP12: =(I12+K12)/F12*-1*R12 | AQ12: =AO12*Q12 | AS12: =H12 | AT12: 0.18289084 | AU12: 0.23037491 | AW12: =AS12/F12 | AX12: =AT12*G12/F12 | AZ12: =AU12 | BA12: =J12/F12 | BB12: =L12/F12 | BC12: =I12/F12 | BD12: =K12/F12 | BF12: =SUM(AW12:AX12)-SUM(AZ12:BD12)
B13: TX_Bio_Ethanol_Wood | C13: Biomass_Wood | D13: 0.2221 | E13: 0 | F13: 2.0577 | G13: 0 | H13: 1.821 | I13: 0 | J13: 1.3469554 | K13: 0 | L13: 0 | M13: 273134.22 | N13: 144062.46 | O13: 0.45 | Q13: 109.47979 | R13: -21.506692 | S13: 170 | T13: 137.93465 | U13: 157.88135 | V13: 111.36485 | W13: 20.230252 | X13: 13.325948 | Z13: =B13 | AA13: =C13 | AB13: =SUM(AE13:AK13)+AM13+AN13 | AC13: =SUM(AE13:AK13)+AP13+AQ13 | AD13: =AB13-AC13 | AE13: =D13/F13*W13*-1 | AF13: =E13/F13*W13 | AG13: {=_xlfn.IFS(C13="Biomass_Corn", 1/F13*S13, C13="Biomass_Agri", 1/F13*V13, C13="Biomass_Wood", 1/F13*U13, C13="Biomass_Herb", 1/F13*T13)} | AH13: =G13/F13*X13 | AI13: =M13/F13/(0.9*8760) | AJ13: =N13/F13/(0.9*8760) | AK13: =O13/F13 | AL13: =SUM(AZ13:BD13)-AW13 | AM13: =(Q13+R13)*-1*(I13+K13)/F13 | AN13: =AL13*Q13 | AO13: =SUM(AZ13:BB13)-AW13 | AP13: =(I13+K13)/F13*-1*R13 | AQ13: =AO13*Q13 | AS13: =H13 | AT13: 0.18289084 | AU13: 0.23037491 | AW13: =AS13/F13 | AX13: =AT13*G13/F13 | AZ13: =AU13 | BA13: =J13/F13 | BB13: =L13/F13 | BC13: =I13/F13 | BD13: =K13/F13 | BF13: =SUM(AW13:AX13)-SUM(AZ13:BD13)
B14: CEN_Bio_Ethanol_Agri | C14: Biomass_Agri | D14: 0.2017 | E14: 0 | F14: 1.8694 | G14: 0 | H14: 1.7 | I14: 0 | J14: 1.2693468 | K14: 0 | L14: 0 | M14: 273134.22 | N14: 144062.46 | O14: 0.45 | Q14: 109.47979 | R14: -31.70346 | S14: 170 | T14: 110.46152 | U14: 127.40875 | V14: 98.832478 | W14: 25.324637 | X14: 13.421913 | Z14: =B14 | AA14: =C14 | AB14: =SUM(AE14:AK14)+AM14+AN14 | AC14: =SUM(AE14:AK14)+AP14+AQ14 | AD14: =AB14-AC14 | AE14: =D14/F14*W14*-1 | AF14: =E14/F14*W14 | AG14: {=_xlfn.IFS(C14="Biomass_Corn", 1/F14*S14, C14="Biomass_Agri", 1/F14*V14, C14="Biomass_Wood", 1/F14*U14, C14="Biomass_Herb", 1/F14*T14)} | AH14: =G14/F14*X14 | AI14: =M14/F14/(0.9*8760) | AJ14: =N14/F14/(0.9*8760) | AK14: =O14/F14 | AL14: =SUM(AZ14:BD14)-AW14 | AM14: =(Q14+R14)*-1*(I14+K14)/F14 | AN14: =AL14*Q14 | AO14: =SUM(AZ14:BB14)-AW14 | AP14: =(I14+K14)/F14*-1*R14 | AQ14: =AO14*Q14 | AS14: =H14 | AT14: 0.18289084 | AU14: 0.23037491 | AW14: =AS14/F14 | AX14: =AT14*G14/F14 | AZ14: =AU14 | BA14: =J14/F14 | BB14: =L14/F14 | BC14: =I14/F14 | BD14: =K14/F14 | BF14: =SUM(AW14:AX14)-SUM(AZ14:BD14)
B15: MIDAT_Bio_Ethanol_Agri | C15: Biomass_Agri | D15: 0.203 | E15: 0 | F15: 1.8813 | G15: 0 | H15: 1.708 | I15: 0 | J15: 1.2745878 | K15: 0 | L15: 0 | M15: 273134.22 | N15: 144062.46 | O15: 0.45 | Q15: 109.47979 | R15: -54.115443 | S15: 170 | T15: 100.77374 | U15: 108.66807 | V15: 89.424565 | W15: 39.359472 | X15: 13.423122 | Z15: =B15 | AA15: =C15 | AB15: =SUM(AE15:AK15)+AM15+AN15 | AC15: =SUM(AE15:AK15)+AP15+AQ15 | AD15: =AB15-AC15 | AE15: =D15/F15*W15*-1 | AF15: =E15/F15*W15 | AG15: {=_xlfn.IFS(C15="Biomass_Corn", 1/F15*S15, C15="Biomass_Agri", 1/F15*V15, C15="Biomass_Wood", 1/F15*U15, C15="Biomass_Herb", 1/F15*T15)} | AH15: =G15/F15*X15 | AI15: =M15/F15/(0.9*8760) | AJ15: =N15/F15/(0.9*8760) | AK15: =O15/F15 | AL15: =SUM(AZ15:BD15)-AW15 | AM15: =(Q15+R15)*-1*(I15+K15)/F15 | AN15: =AL15*Q15 | AO15: =SUM(AZ15:BB15)-AW15 | AP15: =(I15+K15)/F15*-1*R15 | AQ15: =AO15*Q15 | AS15: =H15 | AT15: 0.18289084 | AU15: 0.23037491 | AW15: =AS15/F15 | AX15: =AT15*G15/F15 | AZ15: =AU15 | BA15: =J15/F15 | BB15: =L15/F15 | BC15: =I15/F15 | BD15: =K15/F15 | BF15: =SUM(AW15:AX15)-SUM(AZ15:BD15)
... B75: NE_DryMill_CCS_Fermentation_Exhaust | C75: Biomass_Corn | D75: 0 | E75: 0.085342825 | F75: 3.104338 | G75: 1.0133975 | H75: 1.7588667 | I75: 0.35768767 | J75: 0.68601739 | K75: 0.15290642 | L75: 0.032434696 | M75: 45179.42 | N75: 201481.25 | O75: -25.28 | Q75: 109.47979 | R75: -62.623761 | S75: 170 | T75: 101.59236 | U75: 107.35132 | V75: 91.70665 | W75: 47.446025 | X75: 13.422786 | Z75: =B75 | AA75: =C75 | AB75: =SUM(AE75:AK75)+AM75+AN75 | AC75: =SUM(AE75:AK75)+AP75+AQ75 | AD75: =AB75-AC75 | AE75: =D75/F75*W75*-1 | AF75: =E75/F75*W75 | AG75: {=_xlfn.IFS(C75="Biomass_Corn", 1/F75*S75, C75="Biomass_Agri", 1/F75*V75, C75="Biomass_Wood", 1/F75*U75, C75="Biomass_Herb", 1/F75*T75)} | AH75: =G75/F75*X75 | AI75: =M75/F75/(0.9*8760) | AJ75: =N75/F75/(0.9*8760) | AK75: =O75/F75 | AL75: =SUM(AZ75:BD75)-AW75 | AM75: =(Q75+R75)*-1*(I75+K75)/F75 | AN75: =AL75*Q75 | AO75: =SUM(AZ75:BB75)-AW75 | AP75: =(I75+K75)/F75*-1*R75 | AQ75: =AO75*Q75 | AS75: =H75 | AT75: 0.18289084 | AU75: 0.23037491 | AW75: =AS75/F75 | AX75: =AT75*G75/F75 | AZ75: =AU75 | BA75: =J75/F75 | BB75: =L75/F75 | BC75: =I75/F75 | BD75: =K75/F75 | BF75: =SUM(AW75:AX75)-SUM(AZ75:BD75)

Sheet lc_summary
B1: UNSORTED | O1: SORTED
B2: id | C2: elec_production | D2: elec_consumption | E2: biomass_consumption | F2: natgas_consumption | G2: investment_cost | H2: fixed_om_cost | I2: variable_om_cost | J2: modified capture cost | K2: modified emissions cost | L2: LCOE ($/MWh-ethanol) | M2: LCOE ($/GJ-ethanol) | O2: id | P2: elec_production | Q2: elec_consumption | R2: biomass_consumption | S2: natgas_consumption | T2: investment_cost | U2: fixed_om_cost | V2: variable_om_cost | W2: modified capture cost | X2: modified emissions cost | Y2: LCOE ($/MWh-ethanol) | Z2: LCOE ($/GJ-ethanol)
B3: =lc_detailed!B4 | C3: =lc_detailed!AE4 | D3: =lc_detailed!AF4 | E3: =lc_detailed!AG4 | F3: =lc_detailed!AH4 | G3: =lc_detailed!AI4 | H3: =lc_detailed!AJ4 | I3: =lc_detailed!AK4 | J3: =lc_detailed!AM4 | K3: =lc_detailed!AN4 | L3: =lc_detailed!AC4 | M3: =lc_detailed!#REF! | O3: {=_xlfn._xlws.SORT(B3:M74, 11, 1)} | P3: 0 | Q3: 0.73605181 | R3: 54.762078 | S3: 4.465838 | T3: 1.8459717 | U3: 8.2322589 | V3: -8.1434432 | W3: -16.797273 | X3: 6.5363717 | Y3: 51.637854 | Z3: #REF!
B4: =lc_detailed!B5 | C4: =lc_detailed!AE5 | D4: =lc_detailed!AF5 | E4: =lc_detailed!AG5 | F4: =lc_detailed!AH5 | G4: =lc_detailed!AI5 | H4: =lc_detailed!AJ5 | I4: =lc_detailed!AK5 | J4: =lc_detailed!AM5 | K4: =lc_detailed!AN5 | L4: =lc_detailed!AC5 | M4: =lc_detailed!#REF! | O4: CA_DryMill_CCS_Fermentation_Exhaust | P4: 0 | Q4: 1.0048324 | R4: 54.762078 | S4: 4.4652582 | T4: 1.8459717 | U4: 8.2322589 | V4: -8.1434432 | W4: -16.93854 | X4: 6.5363717 | Y4: 51.764788 | Z4: #REF!
B5: =lc_detailed!B6 | C5: =lc_detailed!AE6 | D5: =lc_detailed!AF6 | E5: =lc_detailed!AG6 | F5: =lc_detailed!AH6 | G5: =lc_detailed!AI6 | H5: =lc_detailed!AJ6 | I5: =lc_detailed!AK6 | J5: =lc_detailed!AM6 | K5: =lc_detailed!AN6 | L5: =lc_detailed!AC6 | M5: =lc_detailed!#REF! | O5: SW_DryMill_CCS_Fermentation_Exhaust | P5: 0 | Q5: 0.76970088 | R5: 54.762078 | S5: 4.4657884 | T5: 1.8459717 | U5: 8.2322589 | V5: -8.1434432 | W5: -15.276872 | X5: 6.5363717 | Y5: 53.191854 | Z5: #REF!
B6: =lc_detailed!B7 | C6: =lc_detailed!AE7 | D6: =lc_detailed!AF7 | E6: =lc_detailed!AG7 | F6: =lc_detailed!AH7 | G6: =lc_detailed!AI7 | H6: =lc_detailed!AJ7 | I6: =lc_detailed!AK7 | J6: =lc_detailed!AM7 | K6: =lc_detailed!AN7 | L6: =lc_detailed!AC7 | M6: =lc_detailed!#REF! | O6: TX_DryMill_CCS_Fermentation_Exhaust | P6: 0 | Q6: 0.55615943 | R6: 54.762078 | S6: 4.3501973 | T6: 1.8459717 | U6: 8.2322589 | V6: -8.1434432 | W6: -14.469606 | X6: 6.5363717 | Y6: 53.669988 | Z6: #REF!
B7: =lc_detailed!B8 | C7: =lc_detailed!AE8 | D7: =lc_detailed!AF8 | E7: =lc_detailed!AG8 | F7: =lc_detailed!AH8 | G7: =lc_detailed!AI8 | H7: =lc_detailed!AJ8 | I7: =lc_detailed!AK8 | J7: =lc_detailed!AM8 | K7: =lc_detailed!AN8 | L7: =lc_detailed!AC8 | M7: =lc_detailed!#REF! | O7: NW_DryMill_CCS_Fermentation | P7: 0 | Q7: 0.73605181 | R7: 54.762078 | S7: 4.465838 | T7: 1.1219174 | U7: 7.8355578 | V7: -8.1724348 | W7: -11.767033 | X7: 6.5363717 | Y7: 55.518347 | Z7: #REF!
B8: =lc_detailed!B9 | C8: =lc_detailed!AE9 | D8: =lc_detailed!AF9 | E8: =lc_detailed!AG9 | F8: =lc_detailed!AH9 | G8: =lc_detailed!AI9 | H8: =lc_detailed!AJ9 | I8: =lc_detailed!AK9 | J8: =lc_detailed!AM9 | K8: =lc_detailed!AN9 | L8: =lc_detailed!AC9 | M8: =lc_detailed!#REF! | O8: CEN_DryMill_CCS_Fermentation_Exhaust | P8: 0 | Q8: 0.69621158 | R8: 54.762078 | S8: 4.3815246 | T8: 1.8459717 | U8: 8.2322589 | V8: -8.1434432 | W8: -12.792466 | X8: 6.5363717 | Y8: 55.518508 | Z8: #REF!
B9: =lc_detailed!B10 | C9: =lc_detailed!AE10 | D9: =lc_detailed!AF10 | E9: =lc_detailed!AG10 | F9: =lc_detailed!AH10 | G9: =lc_detailed!AI10 | H9: =lc_detailed!AJ10 | I9: =lc_detailed!AK10 | J9: =lc_detailed!AM10 | K9: =lc_detailed!AN10 | L9: =lc_detailed!AC10 | M9: =lc_detailed!#REF! | O9: CA_DryMill_CCS_Fermentation | P9: 0 | Q9: 1.0048324 | R9: 54.762078 | S9: 4.4652582 | T9: 1.1219174 | U9: 7.8355578 | V9: -8.1724348 | W9: -11.865995 | X9: 6.5363717 | Y9: 55.687586 | Z9: #REF!
B10: =lc_detailed!B11 | C10: =lc_detailed!AE11 | D10: =lc_detailed!AF11 | E10: =lc_detailed!AG11 | F10: =lc_detailed!AH11 | G10: =lc_detailed!AI11 | H10: =lc_detailed!AJ11 | I10: =lc_detailed!AK11 | J10: =lc_detailed!AM11 | K10: =lc_detailed!AN11 | L10: =lc_detailed!AC11 | M10: =lc_detailed!#REF! | O10: SW_DryMill_CCS_Fermentation | P10: 0 | Q10: 0.76970088 | R10: 54.762078 | S10: 4.4657884 | T10: 1.1219174 | U10: 7.8355578 | V10: -8.1724348 | W10: -10.701943 | X10: 6.5363717 | Y10: 56.617037 | Z10: #REF!
B11: =lc_detailed!B12 | C11: =lc_detailed!AE12 | D11: =lc_detailed!AF12 | E11: =lc_detailed!AG12 | F11: =lc_detailed!AH12 | G11: =lc_detailed!AI12 | H11: =lc_detailed!AJ12 | I11: =lc_detailed!AK12 | J11: =lc_detailed!AM12 | K11: =lc_detailed!AN12 | L11: =lc_detailed!AC12 | M11: =lc_detailed!#REF! | O11: TX_DryMill_CCS_Fermentation | P11: 0 | Q11: 0.55615943 | R11: 54.762078 | S11: 4.3501973 | T11: 1.1219174 | U11: 7.8355578 | V11: -8.1724348 | W11: -10.136427 | X11: 6.5363717 | Y11: 56.85342 | Z11: #REF!
B12: =lc_detailed!B13 | C12: =lc_detailed!AE13 | D12: =lc_detailed!AF13 | E12: =lc_detailed!AG13 | F12: =lc_detailed!AH13 | G12: =lc_detailed!AI13 | H12: =lc_detailed!AJ13 | I12: =lc_detailed!AK13 | J12: =lc_detailed!AM13 | K12: =lc_detailed!AN13 | L12: =lc_detailed!AC13 | M12: =lc_detailed!#REF! | O12: NCEN_DryMill_CCS_Fermentation_Exhaust | P12: 0 | Q12: 0.84421292 | R12: 54.762078 | S12: 4.381554 | T12: 1.8459717 | U12: 8.2322589 | V12: -8.1434432 | W12: -11.14544 | X12: 6.5363717 | Y12: 57.313564 | Z12: #REF!
B13: =lc_detailed!B14 | C13: =lc_detailed!AE14 | D13: =lc_detailed!AF14 | E13: =lc_detailed!AG14 | F13: =lc_detailed!AH14 | G13: =lc_detailed!AI14 | H13: =lc_detailed!AJ14 | I13: =lc_detailed!AK14 | J13: =lc_detailed!AM14 | K13: =lc_detailed!AN14 | L13: =lc_detailed!AC14 | M13: =lc_detailed!#REF! | O13: CEN_DryMill_CCS_Fermentation | P13: 0 | Q13: 0.69621158 | R13: 54.762078 | S13: 4.3815246 | T13: 1.1219174 | U13: 7.8355578 | V13: -8.1724348 | W13: -8.9615358 | X13: 6.5363717 | Y13: 58.199691 | Z13: #REF!
B14: =lc_detailed!B15 | C14: =lc_detailed!AE15 | D14: =lc_detailed!AF15 | E14: =lc_detailed!AG15 | F14: =lc_detailed!AH15 | G14: =lc_detailed!AI15 | H14: =lc_detailed!AJ15 | I14: =lc_detailed!AK15 | J14: =lc_detailed!AM15 | K14: =lc_detailed!AN15 | L14: =lc_detailed!AC15 | M14: =lc_detailed!#REF! | O14: SE_DryMill_CCS_Fermentation_Exhaust | P14: 0 | Q14: 1.0506814 | R14: 54.762078 | S14: 4.381523 | T14: 1.8459717 | U14: 8.2322589 | V14: -8.1434432 | W14: -10.161243 | X14: 6.5363717 | Y14: 58.504198 | Z14: #REF!
B15: =lc_detailed!B16 | C15: =lc_detailed!AE16 | D15: =lc_detailed!AF16 | E15: =lc_detailed!AG16 | F15: =lc_detailed!AH16 | G15: =lc_detailed!AI16 | H15: =lc_detailed!AJ16 | I15: =lc_detailed!AK16 | J15: =lc_detailed!AM16 | K15: =lc_detailed!AN16 | L15: =lc_detailed!AC16 | M15: =lc_detailed!#REF! | O15: NCEN_DryMill_CCS_Fermentation | P15: 0 | Q15: 0.84421292 | R15: 54.762078 | S15: 4.381554 | T15: 1.1219174 | U15: 7.8355578 | V15: -8.1724348 | W15: -7.8077413 | X15: 6.5363717 | Y15: 59.501516 | Z15: #REF!
... B74: =lc_detailed!B75 | C74: =lc_detailed!AE75 | D74: =lc_detailed!AF75 | E74: =lc_detailed!AG75 | F74: =lc_detailed!AH75 | G74: =lc_detailed!AI75 | H74: =lc_detailed!AJ75 | I74: =lc_detailed!AK75 | J74: =lc_detailed!AM75 | K74: =lc_detailed!AN75 | L74: =lc_detailed!AC75 | M74: =lc_detailed!#REF! | O74: TX_Bio_Ethanol_Wood | P74: -2.1835734 | Q74: 0 | R74: 76.727099 | S74: 0 | T74: 16.83633 | U74: 8.8801879 | V74: 0.21869077 | W74: 0 | X74: -0.0001117938 | Y74: 100.47862 | Z74: #REF!
