Workbook

Sheet lc_detailed
B2: Ethanol Upgrade Asset Parameters (normalized by MWh ethanol) | D2: Ethanol feedstock asset | AG2: Duals | AQ2: LCOE for assets with ethane capacity ($/t-ethylene) | AS2: CI | AT2: CREDIT | BI2: CHEM SEQUESTRATION - CARBON INTENSITY | BL2: CHEM SEQUESTRATION - CREDIT | BP2: Ethanol Production LCOE parameters ($/t-ethylene) | BY2: Carbon Content | CD2: Carbon Inputs - Ethanol Production | CF2: Carbon Inputs - Ethanol Dehydration | CI2: Carbon Outputs - Ethanol Production | CK2: Carbon Outputs - Ethanol Dehydration | CN2: Sanity Checks | CP2: Asset Parameters (normalized by commodity feedstock)
B3: id | C3: commodity | D3: production_asset | E3: id_name | F3: h2_consumption (MWh/MWh-ethanol) | G3: elec_consumption (MWh/MWh-ethanol) | H3: ethylene_production (t-ethylene/MWh-ethanol) | I3: natgas_consumption (MWh/MWh-ethanol) | J3: process_capture_rate (t-CO2/MWh-ethanol) | K3: fuel_capture_rate (t-CO2/MWh-ethanol) | L3: process_emission_rate (t-CO2/MWh-ethanol) | M3: fuel_emission_rate (t-CO2/MWh-ethanol) | N3: investment_cost ($/yr per MW ethanol) | O3: fixed_om_cost ($/yr per MW ethanol) | P3: variable_om_cost ($/MWh-ethanol) | R3: id_ethanol_prod_ref | S3: commodity_ethanol_prod_ref | T3: elec_production (MWh/t-bio) | U3: elec_consumption (MWh/t-bio) | V3: ethanol_production (MWh-ethanol/t-bio) | W3: natgas_consumption (MWh/t-bio) | X3: co2_biomass_content (t-CO2/t-bio) | Y3: process_capture_rate (t-CO2/t-bio) | Z3: process_emission_rate (t-CO2/t-bio) | AA3: fuel_capture_rate (t-CO2/t-bio) | AB3: fuel_emission_rate (t-CO2/t-bio) | AC3: investment_cost ($/yr per t-bio/hr) | AD3: fixed_om_cost ($/yr per t-bio/hr) | AE3: variable_om_cost ($/t-bio) | AG3: co2_sink ($/t) | AH3: co2_captured ($/t) | AI3: bioherb_supply ($/t) | AJ3: biowood_supply ($/t) | AK3: bioagri_supply ($/t) | AL3: biocorn_supply ($/t) | AM3: elec_demand ($/MWh) | AN3: h2_balance ($/MWh) | AO3: ng_balance ($/MWh) | AQ3: id_LC | AR3: commodity_LC | AS3: LCOE ($/t-ethylene) | AT3: LCOE ($/t-ethylene) | AU3: Diff. Between Methods | AV3: h2_consumption | AW3: elec_consumption | AX3: elec_consumption - ethanol prod. | AY3: elec_production - ethanol prod. | AZ3: biomass_consumption - ethanol prod. | BA3: natgas_consumption | BB3: natgas_consumption - ethanol prod. | BC3: investment_cost | BD3: investment_cost - ethanol prod. | BE3: fixed_om_cost | BF3: fixed_om_cost - ethanol prod. | BG3: variable_om_cost | BH3: variable_om_cost - ethanol prod. | BI3: CI | BJ3: modified capture cost | BK3: modified emissions cost | BL3: CI | BM3: modified capture cost | BN3: modified emissions cost | BP3: id_LC_ethanol | BQ3: elec_production | BR3: elec_consumption | BS3: biomass_consumption | BT3: natgas_consumption | BU3: investment_cost | BV3: fixed_om_cost | BW3: variable_om_cost | BY3: Ethylene (t-CO2/t-ethylene) | BZ3: Biomass CO2 content (t-CO2/t-bio) | CA3: NG (t-CO2/MWh-NG) | CB3: Ethanol (t-CO2/MWh-ethanol) | CD3: Biomass (t-CO2/t-ethylene) | CE3: NG (t-CO2/t-ethylene) | CF3: Ethanol (t-CO2/t-ethylene) | CG3: NG (t-CO2/t-ethylene) | CI3: Emissions (t-CO2/t-ethylene) | CJ3: Captured (t-CO2/t-ethylene) | CK3: Ethylene (t-CO2/t-ethylene) | CL3: Emissions (t-CO2/t-ethylene) | CN3: CARBON INPUT - OUTPUT | CP3: ethanol_production_asset | CQ3: id_ethanol_prod_ref | CR3: commodity_ethanol_prod_ref | CS3: elec_production (MWh/t-bio) | CT3: elec_consumption (MWh/t-bio) | CU3: ethanol_production (MWh-ethanol/t-bio) | CV3: natgas_consumption (MWh/t-bio) | CW3: co2_biomass_content (t-CO2/t-bio) | CX3: process_capture_rate (t-CO2/t-bio) | CY3: process_emission_rate (t-CO2/t-bio) | CZ3: fuel_capture_rate (t-CO2/t-bio) | DA3: fuel_emission_rate (t-CO2/t-bio) | DB3: investment_cost ($/yr per t-bio/hr) | DC3: fixed_om_cost ($/yr per t-bio/hr) | DD3: variable_om_cost ($/t-bio)
B4: CA_B-NGin | D4: 6 | E4: =R4 -> Drymill CCS Fermentation Exhaust | F4: 0 | G4: 0.0162 | H4: 0.070452767 | I4: 0.1159 | J4: 0 | K4: 0 | L4: 0.008951928 | M4: 0.021192192 | N4: 6578.32 | O4: 6324.47 | P4: 0.11 | R4: {=_xlfn.XLOOKUP(D4, CP:CP, CQ:DD)} -> Drymill CCS Fermentation Exhaust | S4: Biomass_Corn | T4: 0 | U4: 0.085342825 | V4: 3.104338 | W4: 1.0133975 | X4: 1.7588667 | Y4: 0.35768767 | Z4: 0.68601739 | AA4: 0.15290642 | AB4: 0.032434696 | AC4: 45179.42 | AD4: 201481.25 | AE4: -25.28 | AG4: 107.50256 | AH4: -6.5 | AI4: 135.39897 | AJ4: 157.55382 | AK4: 136.23865 | AL4: 160 | AM4: 36.528548 | AN4: 29.772263 | AO4: 13.696721 | AQ4: =B4 -> CA_B-NGin | AR4: =C4 -> 0 | AS4: =SUM(AV4:BH4)+BJ4+BK4 -> 462.67035 | AT4: =SUM(AV4:BH4)+BM4+BN4 -> 462.67035 | AU4: =AS4-AT4 -> 0 | AV4: =F4/H4*AN4 -> 0 | AW4: =G4/H4*AM4 -> 8.3994214 | AX4: =BR4 -> 14.253856 | AY4: =BQ4 -> 0 | AZ4: =BS4 -> 731.56501 | BA4: =I4/H4*AO4 -> 22.532117 | BB4: =BT4 -> 63.464285 | BC4: =N4/H4/(0.9*8760) -> 11.843234 | BD4: =BU4 -> 26.20155 | BE4: =O4/H4/(0.9*8760) -> 11.386217 | BF4: =BV4 -> 116.84791 | BG4: =P4/H4 -> 1.5613297 | BH4: =BW4 -> -115.58727 | BI4: =SUM(CI4:CL4)-CD4 -> 1.1482317 | BJ4: =(AG4+AH4)*-1*(CJ4+CK4) -> -553.23517 | BK4: =BI4*AG4 -> 123.43785 | BL4: =CI4+CL4-CD4 -> -4.3292053 | BM4: =(CJ4+CK4)*AH4*-1 -> 35.60334 | BN4: =BL4*AG4 -> -465.40066 | BP4: =R4 -> Drymill CCS Fermentation Exhaust | BQ4: =T4/V4/H4*AM4*-1 -> 0 | BR4: =U4/V4/H4*AM4 -> 14.253856 | BS4: {=_xlfn.IFS(S4="Biomass_Corn", 1/V4/H4*AL4, S4="Biomass_Agri", 1/V4/H4*AK4, S4="Biomass_Wood", 1/V4/H4*AJ4, S4="Biomass_Herb", 1/V4/H4*AI4)} -> 731.56501 | BT4: =W4/V4/H4*AO4 -> 63.464285 | BU4: =AC4/V4/H4/(0.9*8760) -> 26.20155 | BV4: =AD4/V4/H4/(0.9*8760) -> 116.84791 | BW4: =AE4/V4/H4 -> -115.58727 | BY4: =22/7 -> 3.1428571 | BZ4: =X4 -> 1.7588667 | CA4: 0.18289084 | CB4: 0.23037491 | CD4: =BZ4/V4/H4 -> 8.0420332 | CE4: =IF(W4=0, 0, CA4*W4/V4/H4) -> 0.84743174 | CF4: =CB4/H4 -> 3.26992 | CG4: =IF(I4=0, 0, CA4*I4/H4) -> 0.30086892 | CI4: =(Z4+AB4)/V4/H4 -> 3.2849651 | CJ4: =(Y4+AA4)/V4/H4 -> 2.3345798 | CK4: =BY4 -> 3.1428571 | CL4: =(L4+M4)/H4 -> 0.42786283 | CN4: =CD4+CE4+CG4-SUM(CI4:CL4) -> 6.8940689e-05 | CP4: 1 | CQ4: DryMill_Existing_Non_CCS | CR4: Biomass_Corn | CS4: 0 | CT4: 0.085342825 | CU4: 3.104338 | CV4: 1.0133975 | CW4: 1.7588667 | CX4: 0 | CY4: 1.0437051 | CZ4: 0 | DA4: 0.18534112 | DB4: 0 | DC4: 176727.97 | DD4: -25.41
B5: NW_B-NGin | D5: 6 | E5: =R5 -> Drymill CCS Fermentation Exhaust | F5: 0 | G5: 0.0162 | H5: 0.070452767 | I5: 0.1159 | J5: 0 | K5: 0 | L5: 0.008951928 | M5: 0.021192192 | N5: 6578.32 | O5: 6324.47 | P5: 0.11 | R5: {=_xlfn.XLOOKUP(D5, CP:CP, CQ:DD)} -> Drymill CCS Fermentation Exhaust | S5: Biomass_Corn | T5: 0 | U5: 0.085342825 | V5: 3.104338 | W5: 1.0133975 | X5: 1.7588667 | Y5: 0.35768767 | Z5: 0.68601739 | AA5: 0.15290642 | AB5: 0.032434696 | AC5: 45179.42 | AD5: 201481.25 | AE5: -25.28 | AG5: 107.50256 | AH5: -7.4 | AI5: 134.90067 | AJ5: 153.19849 | AK5: 116.05317 | AL5: 160 | AM5: 26.79773 | AN5: 27.883397 | AO5: 13.696721 | AQ5: =B5 -> NW_B-NGin | AR5: =C5 -> 0 | AS5: =SUM(AV5:BH5)+BJ5+BK5 -> 461.56545 | AT5: =SUM(AV5:BH5)+BM5+BN5 -> 461.56545 | AU5: =AS5-AT5 -> 0 | AV5: =F5/H5*AN5 -> 0 | AW5: =G5/H5*AM5 -> 6.1619046 | AX5: =BR5 -> 10.45678 | AY5: =BQ5 -> 0 | AZ5: =BS5 -> 731.56501 | BA5: =I5/H5*AO5 -> 22.532117 | BB5: =BT5 -> 63.464285 | BC5: =N5/H5/(0.9*8760) -> 11.843234 | BD5: =BU5 -> 26.20155 | BE5: =O5/H5/(0.9*8760) -> 11.386217 | BF5: =BV5 -> 116.84791 | BG5: =P5/H5 -> 1.5613297 | BH5: =BW5 -> -115.58727 | BI5: =SUM(CI5:CL5)-CD5 -> 1.1482317 | BJ5: =(AG5+AH5)*-1*(CJ5+CK5) -> -548.30548 | BK5: =BI5*AG5 -> 123.43785 | BL5: =CI5+CL5-CD5 -> -4.3292053 | BM5: =(CJ5+CK5)*AH5*-1 -> 40.533034 | BN5: =BL5*AG5 -> -465.40066 | BP5: =R5 -> Drymill CCS Fermentation Exhaust | BQ5: =T5/V5/H5*AM5*-1 -> 0 | BR5: =U5/V5/H5*AM5 -> 10.45678 | BS5: {=_xlfn.IFS(S5="Biomass_Corn", 1/V5/H5*AL5, S5="Biomass_Agri", 1/V5/H5*AK5, S5="Biomass_Wood", 1/V5/H5*AJ5, S5="Biomass_Herb", 1/V5/H5*AI5)} -> 731.56501 | BT5: =W5/V5/H5*AO5 -> 63.464285 | BU5: =AC5/V5/H5/(0.9*8760) -> 26.20155 | BV5: =AD5/V5/H5/(0.9*8760) -> 116.84791 | BW5: =AE5/V5/H5 -> -115.58727 | BY5: =22/7 -> 3.1428571 | BZ5: =X5 -> 1.7588667 | CA5: 0.18289084 | CB5: 0.23037491 | CD5: =BZ5/V5/H5 -> 8.0420332 | CE5: =IF(W5=0, 0, CA5*W5/V5/H5) -> 0.84743174 | CF5: =CB5/H5 -> 3.26992 | CG5: =IF(I5=0, 0, CA5*I5/H5) -> 0.30086892 | CI5: =(Z5+AB5)/V5/H5 -> 3.2849651 | CJ5: =(Y5+AA5)/V5/H5 -> 2.3345798 | CK5: =BY5 -> 3.1428571 | CL5: =(L5+M5)/H5 -> 0.42786283 | CN5: =CD5+CE5+CG5-SUM(CI5:CL5) -> 6.8940689e-05 | CP5: 2 | CQ5: Biochemical_Non_CCS | CR5: Biomass_Agri | CS5: 0.2142 | CT5: 0 | CU5: 1.9848 | CV5: 0 | CW5: 1.723 | CX5: 0 | CY5: 1.2657602 | CZ5: 0 | DA5: 0 | DB5: 273134.22 | DC5: 144062.46 | DD5: 0.45
B6: SW_B-NGin | D6: 6 | E6: =R6 -> Drymill CCS Fermentation Exhaust | F6: 0 | G6: 0.0162 | H6: 0.070452767 | I6: 0.1159 | J6: 0 | K6: 0 | L6: 0.008951928 | M6: 0.021192192 | N6: 6578.32 | O6: 6324.47 | P6: 0.11 | R6: {=_xlfn.XLOOKUP(D6, CP:CP, CQ:DD)} -> Drymill CCS Fermentation Exhaust | S6: Biomass_Corn | T6: 0 | U6: 0.085342825 | V6: 3.104338 | W6: 1.0133975 | X6: 1.7588667 | Y6: 0.35768767 | Z6: 0.68601739 | AA6: 0.15290642 | AB6: 0.032434696 | AC6: 45179.42 | AD6: 201481.25 | AE6: -25.28 | AG6: 107.50256 | AH6: -16.458953 | AI6: 121.90098 | AJ6: 139.17763 | AK6: 109.07949 | AL6: 160 | AM6: 27.982243 | AN6: 26.416189 | AO6: 13.696721 | AQ6: =B6 -> SW_B-NGin | AR6: =C6 -> 0 | AS6: =SUM(AV6:BH6)+BJ6+BK6 -> 511.91987 | AT6: =SUM(AV6:BH6)+BM6+BN6 -> 511.91987 | AU6: =AS6-AT6 -> 0 | AV6: =F6/H6*AN6 -> 0 | AW6: =G6/H6*AM6 -> 6.434273 | AX6: =BR6 -> 10.91899 | AY6: =BQ6 -> 0 | AZ6: =BS6 -> 731.56501 | BA6: =I6/H6*AO6 -> 22.532117 | BB6: =BT6 -> 63.464285 | BC6: =N6/H6/(0.9*8760) -> 11.843234 | BD6: =BU6 -> 26.20155 | BE6: =O6/H6/(0.9*8760) -> 11.386217 | BF6: =BV6 -> 116.84791 | BG6: =P6/H6 -> 1.5613297 | BH6: =BW6 -> -115.58727 | BI6: =SUM(CI6:CL6)-CD6 -> 1.1482317 | BJ6: =(AG6+AH6)*-1*(CJ6+CK6) -> -498.68563 | BK6: =BI6*AG6 -> 123.43785 | BL6: =CI6+CL6-CD6 -> -4.3292053 | BM6: =(CJ6+CK6)*AH6*-1 -> 90.152878 | BN6: =BL6*AG6 -> -465.40066 | BP6: =R6 -> Drymill CCS Fermentation Exhaust | BQ6: =T6/V6/H6*AM6*-1 -> 0 | BR6: =U6/V6/H6*AM6 -> 10.91899 | BS6: {=_xlfn.IFS(S6="Biomass_Corn", 1/V6/H6*AL6, S6="Biomass_Agri", 1/V6/H6*AK6, S6="Biomass_Wood", 1/V6/H6*AJ6, S6="Biomass_Herb", 1/V6/H6*AI6)} -> 731.56501 | BT6: =W6/V6/H6*AO6 -> 63.464285 | BU6: =AC6/V6/H6/(0.9*8760) -> 26.20155 | BV6: =AD6/V6/H6/(0.9*8760) -> 116.84791 | BW6: =AE6/V6/H6 -> -115.58727 | BY6: =22/7 -> 3.1428571 | BZ6: =X6 -> 1.7588667 | CA6: 0.18289084 | CB6: 0.23037491 | CD6: =BZ6/V6/H6 -> 8.0420332 | CE6: =IF(W6=0, 0, CA6*W6/V6/H6) -> 0.84743174 | CF6: =CB6/H6 -> 3.26992 | CG6: =IF(I6=0, 0, CA6*I6/H6) -> 0.30086892 | CI6: =(Z6+AB6)/V6/H6 -> 3.2849651 | CJ6: =(Y6+AA6)/V6/H6 -> 2.3345798 | CK6: =BY6 -> 3.1428571 | CL6: =(L6+M6)/H6 -> 0.42786283 | CN6: =CD6+CE6+CG6-SUM(CI6:CL6) -> 6.8940689e-05 | CP6: 3 | CQ6: Biochemical_CCS_20 | CR6: Biomass_Agri | CS6: 0 | CT6: 0 | CU6: 1.9848 | CV6: 0 | CW6: 1.723 | CX6: 0.25912643 | CY6: 1.0066338 | CZ6: 0 | DA6: 0 | DB6: 293026.95 | DC6: 154950.42 | DD6: 0.48
B7: TX_B-NGin | D7: 6 | E7: =R7 -> Drymill CCS Fermentation Exhaust | F7: 0 | G7: 0.0162 | H7: 0.070452767 | I7: 0.1159 | J7: 0 | K7: 0 | L7: 0.008951928 | M7: 0.021192192 | N7: 6578.32 | O7: 6324.47 | P7: 0.11 | R7: {=_xlfn.XLOOKUP(D7, CP:CP, CQ:DD)} -> Drymill CCS Fermentation Exhaust | S7: Biomass_Corn | T7: 0 | U7: 0.085342825 | V7: 3.104338 | W7: 1.0133975 | X7: 1.7588667 | Y7: 0.35768767 | Z7: 0.68601739 | AA7: 0.15290642 | AB7: 0.032434696 | AC7: 45179.42 | AD7: 201481.25 | AE7: -25.28 | AG7: 107.50256 | AH7: -21.358133 | AI7: 134.78594 | AJ7: 154.49711 | AK7: 108.34628 | AL7: 160 | AM7: 20.1955 | AN7: 18.588213 | AO7: 13.326111 | AQ7: =B7 -> TX_B-NGin | AR7: =C7 -> 0 | AS7: =SUM(AV7:BH7)+BJ7+BK7 -> 531.59893 | AT7: =SUM(AV7:BH7)+BM7+BN7 -> 531.59893 | AU7: =AS7-AT7 -> 0 | AV7: =F7/H7*AN7 -> 0 | AW7: =G7/H7*AM7 -> 4.6437793 | AX7: =BR7 -> 7.8805144 | AY7: =BQ7 -> 0 | AZ7: =BS7 -> 731.56501 | BA7: =I7/H7*AO7 -> 21.922436 | BB7: =BT7 -> 61.747049 | BC7: =N7/H7/(0.9*8760) -> 11.843234 | BD7: =BU7 -> 26.20155 | BE7: =O7/H7/(0.9*8760) -> 11.386217 | BF7: =BV7 -> 116.84791 | BG7: =P7/H7 -> 1.5613297 | BH7: =BW7 -> -115.58727 | BI7: =SUM(CI7:CL7)-CD7 -> 1.1482317 | BJ7: =(AG7+AH7)*-1*(CJ7+CK7) -> -471.85068 | BK7: =BI7*AG7 -> 123.43785 | BL7: =CI7+CL7-CD7 -> -4.3292053 | BM7: =(CJ7+CK7)*AH7*-1 -> 116.98783 | BN7: =BL7*AG7 -> -465.40066 | BP7: =R7 -> Drymill CCS Fermentation Exhaust | BQ7: =T7/V7/H7*AM7*-1 -> 0 | BR7: =U7/V7/H7*AM7 -> 7.8805144 | BS7: {=_xlfn.IFS(S7="Biomass_Corn", 1/V7/H7*AL7, S7="Biomass_Agri", 1/V7/H7*AK7, S7="Biomass_Wood", 1/V7/H7*AJ7, S7="Biomass_Herb", 1/V7/H7*AI7)} -> 731.56501 | BT7: =W7/V7/H7*AO7 -> 61.747049 | BU7: =AC7/V7/H7/(0.9*8760) -> 26.20155 | BV7: =AD7/V7/H7/(0.9*8760) -> 116.84791 | BW7: =AE7/V7/H7 -> -115.58727 | BY7: =22/7 -> 3.1428571 | BZ7: =X7 -> 1.7588667 | CA7: 0.18289084 | CB7: 0.23037491 | CD7: =BZ7/V7/H7 -> 8.0420332 | CE7: =IF(W7=0, 0, CA7*W7/V7/H7) -> 0.84743174 | CF7: =CB7/H7 -> 3.26992 | CG7: =IF(I7=0, 0, CA7*I7/H7) -> 0.30086892 | CI7: =(Z7+AB7)/V7/H7 -> 3.2849651 | CJ7: =(Y7+AA7)/V7/H7 -> 2.3345798 | CK7: =BY7 -> 3.1428571 | CL7: =(L7+M7)/H7 -> 0.42786283 | CN7: =CD7+CE7+CG7-SUM(CI7:CL7) -> 6.8940689e-05 | CP7: 4 | CQ7: Biochemical_CCS_86 | CR7: Biomass_Agri | CS7: 0 | CT7: 0.2632 | CU7: 1.9848 | CV7: 0 | CW7: 1.723 | CX7: 1.0913384 | CY7: 0.17442176 | CZ7: 0 | DA7: 0 | DB7: 520155.64 | DC7: 279265.62 | DD7: 1.67
B8: NCEN_B-NGin | D8: 6 | F8: 0 | G8: 0.0162 | H8: 0.070452767 | I8: 0.1159 | J8: 0 | K8: 0 | L8: 0.008951928 | M8: 0.021192192 | N8: 6578.32 | O8: 6324.47 | P8: 0.11 | R8: {=_xlfn.XLOOKUP(D8, CP:CP, CQ:DD)} -> Drymill CCS Fermentation Exhaust | S8: Biomass_Corn | T8: 0 | U8: 0.085342825 | V8: 3.104338 | W8: 1.0133975 | X8: 1.7588667 | Y8: 0.35768767 | Z8: 0.68601739 | AA8: 0.15290642 | AB8: 0.032434696 | AC8: 45179.42 | AD8: 201481.25 | AE8: -25.28 | AG8: 107.50256 | AH8: -41.580336 | AI8: 102.40263 | AJ8: 113.69796 | AK8: 90.50509 | AL8: 160 | AM8: 30.751318 | AN8: 27.653755 | AO8: 13.422023 | AQ8: =B8 -> NCEN_B-NGin | AR8: =C8 -> 0 | AS8: =SUM(AV8:BH8)+BJ8+BK8 -> 649.51319 | AT8: =SUM(AV8:BH8)+BM8+BN8 -> 649.51319 | AU8: =AS8-AT8 -> 0 | AV8: =F8/H8*AN8 -> 0 | AW8: =G8/H8*AM8 -> 7.0709977 | AX8: =BR8 -> 11.999515 | AY8: =BQ8 -> 0 | AZ8: =BS8 -> 731.56501 | BA8: =I8/H8*AO8 -> 22.080218 | BB8: =BT8 -> 62.191461 | BC8: =N8/H8/(0.9*8760) -> 11.843234 | BD8: =BU8 -> 26.20155 | BE8: =O8/H8/(0.9*8760) -> 11.386217 | BF8: =BV8 -> 116.84791 | BG8: =P8/H8 -> 1.5613297 | BH8: =BW8 -> -115.58727 | BI8: =SUM(CI8:CL8)-CD8 -> 1.1482317 | BJ8: =(AG8+AH8)*-1*(CJ8+CK8) -> -361.08484 | BK8: =BI8*AG8 -> 123.43785 | BL8: =CI8+CL8-CD8 -> -4.3292053 | BM8: =(CJ8+CK8)*AH8*-1 -> 227.75367 | BN8: =BL8*AG8 -> -465.40066 | BP8: =R8 -> Drymill CCS Fermentation Exhaust | BQ8: =T8/V8/H8*AM8*-1 -> 0 | BR8: =U8/V8/H8*AM8 -> 11.999515 | BS8: {=_xlfn.IFS(S8="Biomass_Corn", 1/V8/H8*AL8, S8="Biomass_Agri", 1/V8/H8*AK8, S8="Biomass_Wood", 1/V8/H8*AJ8, S8="Biomass_Herb", 1/V8/H8*AI8)} -> 731.56501 | BT8: =W8/V8/H8*AO8 -> 62.191461 | BU8: =AC8/V8/H8/(0.9*8760) -> 26.20155 | BV8: =AD8/V8/H8/(0.9*8760) -> 116.84791 | BW8: =AE8/V8/H8 -> -115.58727 | BY8: =22/7 -> 3.1428571 | BZ8: =X8 -> 1.7588667 | CA8: 0.18289084 | CB8: 0.23037491 | CD8: =BZ8/V8/H8 -> 8.0420332 | CE8: =IF(W8=0, 0, CA8*W8/V8/H8) -> 0.84743174 | CF8: =CB8/H8 -> 3.26992 | CG8: =IF(I8=0, 0, CA8*I8/H8) -> 0.30086892 | CI8: =(Z8+AB8)/V8/H8 -> 3.2849651 | CJ8: =(Y8+AA8)/V8/H8 -> 2.3345798 | CK8: =BY8 -> 3.1428571 | CL8: =(L8+M8)/H8 -> 0.42786283 | CN8: =CD8+CE8+CG8-SUM(CI8:CL8) -> 6.8940689e-05 | CP8: 5 | CQ8: Drymill CCS Fermentation | CR8: Biomass_Corn | CS8: 0 | CT8: 0.08534283 | CU8: 3.104338 | CV8: 1.0133975 | CW8: 1.7588667 | CX8: 0.35768767 | CY8: 0.68601739 | CZ8: 0 | DA8: 0.18534112 | DB8: 27458.48 | DC8: 191772.15 | DD8: -25.37
B9: CEN_B-NGin | D9: 6 | F9: 0 | G9: 0.0162 | H9: 0.070452767 | I9: 0.1159 | J9: 0 | K9: 0 | L9: 0.008951928 | M9: 0.021192192 | N9: 6578.32 | O9: 6324.47 | P9: 0.11 | R9: {=_xlfn.XLOOKUP(D9, CP:CP, CQ:DD)} -> Drymill CCS Fermentation Exhaust | S9: Biomass_Corn | T9: 0 | U9: 0.085342825 | V9: 3.104338 | W9: 1.0133975 | X9: 1.7588667 | Y9: 0.35768767 | Z9: 0.68601739 | AA9: 0.15290642 | AB9: 0.032434696 | AC9: 45179.42 | AD9: 201481.25 | AE9: -25.28 | AG9: 107.50256 | AH9: -31.564237 | AI9: 108.66061 | AJ9: 124.76345 | AK9: 95.964114 | AL9: 160 | AM9: 25.147071 | AN9: 25.749803 | AO9: 13.422023 | AQ9: =B9 -> CEN_B-NGin | AR9: =C9 -> 0 | AS9: =SUM(AV9:BH9)+BJ9+BK9 -> 591.17515 | AT9: =SUM(AV9:BH9)+BM9+BN9 -> 591.17515 | AU9: =AS9-AT9 -> 0 | AV9: =F9/H9*AN9 -> 0 | AW9: =G9/H9*AM9 -> 5.7823499 | AX9: =BR9 -> 9.8126739 | AY9: =BQ9 -> 0 | AZ9: =BS9 -> 731.56501 | BA9: =I9/H9*AO9 -> 22.080218 | BB9: =BT9 -> 62.191461 | BC9: =N9/H9/(0.9*8760) -> 11.843234 | BD9: =BU9 -> 26.20155 | BE9: =O9/H9/(0.9*8760) -> 11.386217 | BF9: =BV9 -> 116.84791 | BG9: =P9/H9 -> 1.5613297 | BH9: =BW9 -> -115.58727 | BI9: =SUM(CI9:CL9)-CD9 -> 1.1482317 | BJ9: =(AG9+AH9)*-1*(CJ9+CK9) -> -415.94739 | BK9: =BI9*AG9 -> 123.43785 | BL9: =CI9+CL9-CD9 -> -4.3292053 | BM9: =(CJ9+CK9)*AH9*-1 -> 172.89112 | BN9: =BL9*AG9 -> -465.40066 | BP9: =R9 -> Drymill CCS Fermentation Exhaust | BQ9: =T9/V9/H9*AM9*-1 -> 0 | BR9: =U9/V9/H9*AM9 -> 9.8126739 | BS9: {=_xlfn.IFS(S9="Biomass_Corn", 1/V9/H9*AL9, S9="Biomass_Agri", 1/V9/H9*AK9, S9="Biomass_Wood", 1/V9/H9*AJ9, S9="Biomass_Herb", 1/V9/H9*AI9)} -> 731.56501 | BT9: =W9/V9/H9*AO9 -> 62.191461 | BU9: =AC9/V9/H9/(0.9*8760) -> 26.20155 | BV9: =AD9/V9/H9/(0.9*8760) -> 116.84791 | BW9: =AE9/V9/H9 -> -115.58727 | BY9: =22/7 -> 3.1428571 | BZ9: =X9 -> 1.7588667 | CA9: 0.18289084 | CB9: 0.23037491 | CD9: =BZ9/V9/H9 -> 8.0420332 | CE9: =IF(W9=0, 0, CA9*W9/V9/H9) -> 0.84743174 | CF9: =CB9/H9 -> 3.26992 | CG9: =IF(I9=0, 0, CA9*I9/H9) -> 0.30086892 | CI9: =(Z9+AB9)/V9/H9 -> 3.2849651 | CJ9: =(Y9+AA9)/V9/H9 -> 2.3345798 | CK9: =BY9 -> 3.1428571 | CL9: =(L9+M9)/H9 -> 0.42786283 | CN9: =CD9+CE9+CG9-SUM(CI9:CL9) -> 6.8940689e-05 | CP9: 6 | CQ9: Drymill CCS Fermentation Exhaust | CR9: Biomass_Corn | CS9: 0 | CT9: 0.085342825 | CU9: 3.104338 | CV9: 1.0133975 | CW9: 1.7588667 | CX9: 0.35768767 | CY9: 0.68601739 | CZ9: 0.15290642 | DA9: 0.032434696 | DB9: 45179.42 | DC9: 201481.25 | DD9: -25.28
B10: SE_B-NGin | D10: 6 | F10: 0 | G10: 0.0162 | H10: 0.070452767 | I10: 0.1159 | J10: 0 | K10: 0 | L10: 0.008951928 | M10: 0.021192192 | N10: 6578.32 | O10: 6324.47 | P10: 0.11 | R10: {=_xlfn.XLOOKUP(D10, CP:CP, CQ:DD)} -> Drymill CCS Fermentation Exhaust | S10: Biomass_Corn | T10: 0 | U10: 0.085342825 | V10: 3.104338 | W10: 1.0133975 | X10: 1.7588667 | Y10: 0.35768767 | Z10: 0.68601739 | AA10: 0.15290642 | AB10: 0.032434696 | AC10: 45179.42 | AD10: 201481.25 | AE10: -25.28 | AG10: 107.50256 | AH10: -47.666124 | AI10: 98.762212 | AJ10: 111.24126 | AK10: 88.010631 | AL10: 160 | AM10: 38.144019 | AN10: 30.118994 | AO10: 13.422023 | AQ10: =B10 -> SE_B-NGin | AR10: =C10 -> 0 | AS10: =SUM(AV10:BH10)+BJ10+BK10 -> 687.43231 | AT10: =SUM(AV10:BH10)+BM10+BN10 -> 687.43231 | AU10: =AS10-AT10 -> 0 | AV10: =F10/H10*AN10 -> 0 | AW10: =G10/H10*AM10 -> 8.7708849 | AX10: =BR10 -> 14.884231 | AY10: =BQ10 -> 0 | AZ10: =BS10 -> 731.56501 | BA10: =I10/H10*AO10 -> 22.080218 | BB10: =BT10 -> 62.191461 | BC10: =N10/H10/(0.9*8760) -> 11.843234 | BD10: =BU10 -> 26.20155 | BE10: =O10/H10/(0.9*8760) -> 11.386217 | BF10: =BV10 -> 116.84791 | BG10: =P10/H10 -> 1.5613297 | BH10: =BW10 -> -115.58727 | BI10: =SUM(CI10:CL10)-CD10 -> 1.1482317 | BJ10: =(AG10+AH10)*-1*(CJ10+CK10) -> -327.75032 | BK10: =BI10*AG10 -> 123.43785 | BL10: =CI10+CL10-CD10 -> -4.3292053 | BM10: =(CJ10+CK10)*AH10*-1 -> 261.08819 | BN10: =BL10*AG10 -> -465.40066 | BP10: =R10 -> Drymill CCS Fermentation Exhaust | BQ10: =T10/V10/H10*AM10*-1 -> 0 | BR10: =U10/V10/H10*AM10 -> 14.884231 | BS10: {=_xlfn.IFS(S10="Biomass_Corn", 1/V10/H10*AL10, S10="Biomass_Agri", 1/V10/H10*AK10, S10="Biomass_Wood", 1/V10/H10*AJ10, S10="Biomass_Herb", 1/V10/H10*AI10)} -> 731.56501 | BT10: =W10/V10/H10*AO10 -> 62.191461 | BU10: =AC10/V10/H10/(0.9*8760) -> 26.20155 | BV10: =AD10/V10/H10/(0.9*8760) -> 116.84791 | BW10: =AE10/V10/H10 -> -115.58727 | BY10: =22/7 -> 3.1428571 | BZ10: =X10 -> 1.7588667 | CA10: 0.18289084 | CB10: 0.23037491 | CD10: =BZ10/V10/H10 -> 8.0420332 | CE10: =IF(W10=0, 0, CA10*W10/V10/H10) -> 0.84743174 | CF10: =CB10/H10 -> 3.26992 | CG10: =IF(I10=0, 0, CA10*I10/H10) -> 0.30086892 | CI10: =(Z10+AB10)/V10/H10 -> 3.2849651 | CJ10: =(Y10+AA10)/V10/H10 -> 2.3345798 | CK10: =BY10 -> 3.1428571 | CL10: =(L10+M10)/H10 -> 0.42786283 | CN10: =CD10+CE10+CG10-SUM(CI10:CL10) -> 6.8940689e-05
B11: MIDAT_B-NGin | D11: 6 | F11: 0 | G11: 0.0162 | H11: 0.070452767 | I11: 0.1159 | J11: 0 | K11: 0 | L11: 0.008951928 | M11: 0.021192192 | N11: 6578.32 | O11: 6324.47 | P11: 0.11 | R11: {=_xlfn.XLOOKUP(D11, CP:CP, CQ:DD)} -> Drymill CCS Fermentation Exhaust | S11: Biomass_Corn | T11: 0 | U11: 0.085342825 | V11: 3.104338 | W11: 1.0133975 | X11: 1.7588667 | Y11: 0.35768767 | Z11: 0.68601739 | AA11: 0.15290642 | AB11: 0.032434696 | AC11: 45179.42 | AD11: 201481.25 | AE11: -25.28 | AG11: 107.50256 | AH11: -49.879537 | AI11: 99.878528 | AJ11: 107.75134 | AK11: 88.568333 | AL11: 160 | AM11: 39.370157 | AN11: 31.385136 | AO11: 13.422023 | AQ11: =B11 -> MIDAT_B-NGin | AR11: =C11 -> 0 | AS11: =SUM(AV11:BH11)+BJ11+BK11 -> 700.31654 | AT11: =SUM(AV11:BH11)+BM11+BN11 -> 700.31654 | AU11: =AS11-AT11 -> 0 | AV11: =F11/H11*AN11 -> 0 | AW11: =G11/H11*AM11 -> 9.0528246 | AX11: =BR11 -> 15.362684 | AY11: =BQ11 -> 0 | AZ11: =BS11 -> 731.56501 | BA11: =I11/H11*AO11 -> 22.080218 | BB11: =BT11 -> 62.191461 | BC11: =N11/H11/(0.9*8760) -> 11.843234 | BD11: =BU11 -> 26.20155 | BE11: =O11/H11/(0.9*8760) -> 11.386217 | BF11: =BV11 -> 116.84791 | BG11: =P11/H11 -> 1.5613297 | BH11: =BW11 -> -115.58727 | BI11: =SUM(CI11:CL11)-CD11 -> 1.1482317 | BJ11: =(AG11+AH11)*-1*(CJ11+CK11) -> -315.62649 | BK11: =BI11*AG11 -> 123.43785 | BL11: =CI11+CL11-CD11 -> -4.3292053 | BM11: =(CJ11+CK11)*AH11*-1 -> 273.21202 | BN11: =BL11*AG11 -> -465.40066 | BP11: =R11 -> Drymill CCS Fermentation Exhaust | BQ11: =T11/V11/H11*AM11*-1 -> 0 | BR11: =U11/V11/H11*AM11 -> 15.362684 | BS11: {=_xlfn.IFS(S11="Biomass_Corn", 1/V11/H11*AL11, S11="Biomass_Agri", 1/V11/H11*AK11, S11="Biomass_Wood", 1/V11/H11*AJ11, S11="Biomass_Herb", 1/V11/H11*AI11)} -> 731.56501 | BT11: =W11/V11/H11*AO11 -> 62.191461 | BU11: =AC11/V11/H11/(0.9*8760) -> 26.20155 | BV11: =AD11/V11/H11/(0.9*8760) -> 116.84791 | BW11: =AE11/V11/H11 -> -115.58727 | BY11: =22/7 -> 3.1428571 | BZ11: =X11 -> 1.7588667 | CA11: 0.18289084 | CB11: 0.23037491 | CD11: =BZ11/V11/H11 -> 8.0420332 | CE11: =IF(W11=0, 0, CA11*W11/V11/H11) -> 0.84743174 | CF11: =CB11/H11 -> 3.26992 | CG11: =IF(I11=0, 0, CA11*I11/H11) -> 0.30086892 | CI11: =(Z11+AB11)/V11/H11 -> 3.2849651 | CJ11: =(Y11+AA11)/V11/H11 -> 2.3345798 | CK11: =BY11 -> 3.1428571 | CL11: =(L11+M11)/H11 -> 0.42786283 | CN11: =CD11+CE11+CG11-SUM(CI11:CL11) -> 6.8940689e-05
B12: NE_B-NGin | D12: 6 | F12: 0 | G12: 0.0162 | H12: 0.070452767 | I12: 0.1159 | J12: 0 | K12: 0 | L12: 0.008951928 | M12: 0.021192192 | N12: 6578.32 | O12: 6324.47 | P12: 0.11 | R12: {=_xlfn.XLOOKUP(D12, CP:CP, CQ:DD)} -> Drymill CCS Fermentation Exhaust | S12: Biomass_Corn | T12: 0 | U12: 0.085342825 | V12: 3.104338 | W12: 1.0133975 | X12: 1.7588667 | Y12: 0.35768767 | Z12: 0.68601739 | AA12: 0.15290642 | AB12: 0.032434696 | AC12: 45179.42 | AD12: 201481.25 | AE12: -25.28 | AG12: 107.50256 | AH12: -59.252961 | AI12: 100.64964 | AJ12: 106.42207 | AK12: 90.784433 | AL12: 160 | AM12: 47.412137 | AN12: 33.344947 | AO12: 13.422023 | AQ12: =B12 -> NE_B-NGin | AR12: =C12 -> 0 | AS12: =SUM(AV12:BH12)+BJ12+BK12 -> 756.64613 | AT12: =SUM(AV12:BH12)+BM12+BN12 -> 756.64613 | AU12: =AS12-AT12 -> 0 | AV12: =F12/H12*AN12 -> 0 | AW12: =G12/H12*AM12 -> 10.902008 | AX12: =BR12 -> 18.500757 | AY12: =BQ12 -> 0 | AZ12: =BS12 -> 731.56501 | BA12: =I12/H12*AO12 -> 22.080218 | BB12: =BT12 -> 62.191461 | BC12: =N12/H12/(0.9*8760) -> 11.843234 | BD12: =BU12 -> 26.20155 | BE12: =O12/H12/(0.9*8760) -> 11.386217 | BF12: =BV12 -> 116.84791 | BG12: =P12/H12 -> 1.5613297 | BH12: =BW12 -> -115.58727 | BI12: =SUM(CI12:CL12)-CD12 -> 1.1482317 | BJ12: =(AG12+AH12)*-1*(CJ12+CK12) -> -264.28415 | BK12: =BI12*AG12 -> 123.43785 | BL12: =CI12+CL12-CD12 -> -4.3292053 | BM12: =(CJ12+CK12)*AH12*-1 -> 324.55436 | BN12: =BL12*AG12 -> -465.40066 | BP12: =R12 -> Drymill CCS Fermentation Exhaust | BQ12: =T12/V12/H12*AM12*-1 -> 0 | BR12: =U12/V12/H12*AM12 -> 18.500757 | BS12: {=_xlfn.IFS(S12="Biomass_Corn", 1/V12/H12*AL12, S12="Biomass_Agri", 1/V12/H12*AK12, S12="Biomass_Wood", 1/V12/H12*AJ12, S12="Biomass_Herb", 1/V12/H12*AI12)} -> 731.56501 | BT12: =W12/V12/H12*AO12 -> 62.191461 | BU12: =AC12/V12/H12/(0.9*8760) -> 26.20155 | BV12: =AD12/V12/H12/(0.9*8760) -> 116.84791 | BW12: =AE12/V12/H12 -> -115.58727 | BY12: =22/7 -> 3.1428571 | BZ12: =X12 -> 1.7588667 | CA12: 0.18289084 | CB12: 0.23037491 | CD12: =BZ12/V12/H12 -> 8.0420332 | CE12: =IF(W12=0, 0, CA12*W12/V12/H12) -> 0.84743174 | CF12: =CB12/H12 -> 3.26992 | CG12: =IF(I12=0, 0, CA12*I12/H12) -> 0.30086892 | CI12: =(Z12+AB12)/V12/H12 -> 3.2849651 | CJ12: =(Y12+AA12)/V12/H12 -> 2.3345798 | CK12: =BY12 -> 3.1428571 | CL12: =(L12+M12)/H12 -> 0.42786283 | CN12: =CD12+CE12+CG12-SUM(CI12:CL12) -> 6.8940689e-05
B13: CA_B-H2in | D13: 6 | F13: 0.11587061 | G13: 0.0162 | H13: 0.070452767 | I13: 0 | J13: 0 | K13: 0 | L13: 0.008951928 | M13: 0 | N13: 6578.32 | O13: 6324.47 | P13: 0.11 | R13: {=_xlfn.XLOOKUP(D13, CP:CP, CQ:DD)} -> Drymill CCS Fermentation Exhaust | S13: Biomass_Corn | T13: 0 | U13: 0.085342825 | V13: 3.104338 | W13: 1.0133975 | X13: 1.7588667 | Y13: 0.35768767 | Z13: 0.68601739 | AA13: 0.15290642 | AB13: 0.032434696 | AC13: 45179.42 | AD13: 201481.25 | AE13: -25.28 | AG13: 107.50256 | AH13: -6.5 | AI13: 135.39897 | AJ13: 157.55382 | AK13: 136.23865 | AL13: 160 | AM13: 36.528548 | AN13: 29.772263 | AO13: 13.696721 | AQ13: =B13 -> CA_B-H2in | AR13: =C13 -> 0 | AS13: =SUM(AV13:BH13)+BJ13+BK13 -> 456.76661 | AT13: =SUM(AV13:BH13)+BM13+BN13 -> 456.76661 | AU13: =AS13-AT13 -> 0 | AV13: =F13/H13*AN13 -> 48.965151 | AW13: =G13/H13*AM13 -> 8.3994214 | AX13: =BR13 -> 14.253856 | AY13: =BQ13 -> 0 | AZ13: =BS13 -> 731.56501 | BA13: =I13/H13*AO13 -> 0 | BB13: =BT13 -> 63.464285 | BC13: =N13/H13/(0.9*8760) -> 11.843234 | BD13: =BU13 -> 26.20155 | BE13: =O13/H13/(0.9*8760) -> 11.386217 | BF13: =BV13 -> 116.84791 | BG13: =P13/H13 -> 1.5613297 | BH13: =BW13 -> -115.58727 | BI13: =SUM(CI13:CL13)-CD13 -> 0.84743172 | BJ13: =(AG13+AH13)*-1*(CJ13+CK13) -> -553.23517 | BK13: =BI13*AG13 -> 91.10108 | BL13: =CI13+CL13-CD13 -> -4.6300053 | BM13: =(CJ13+CK13)*AH13*-1 -> 35.60334 | BN13: =BL13*AG13 -> -497.73743 | BP13: =R13 -> Drymill CCS Fermentation Exhaust | BQ13: =T13/V13/H13*AM13*-1 -> 0 | BR13: =U13/V13/H13*AM13 -> 14.253856 | BS13: {=_xlfn.IFS(S13="Biomass_Corn", 1/V13/H13*AL13, S13="Biomass_Agri", 1/V13/H13*AK13, S13="Biomass_Wood", 1/V13/H13*AJ13, S13="Biomass_Herb", 1/V13/H13*AI13)} -> 731.56501 | BT13: =W13/V13/H13*AO13 -> 63.464285 | BU13: =AC13/V13/H13/(0.9*8760) -> 26.20155 | BV13: =AD13/V13/H13/(0.9*8760) -> 116.84791 | BW13: =AE13/V13/H13 -> -115.58727 | BY13: =22/7 -> 3.1428571 | BZ13: =X13 -> 1.7588667 | CA13: 0.18289084 | CB13: 0.23037491 | CD13: =BZ13/V13/H13 -> 8.0420332 | CE13: =IF(W13=0, 0, CA13*W13/V13/H13) -> 0.84743174 | CF13: =CB13/H13 -> 3.26992 | CG13: =IF(I13=0, 0, CA13*I13/H13) -> 0 | CI13: =(Z13+AB13)/V13/H13 -> 3.2849651 | CJ13: =(Y13+AA13)/V13/H13 -> 2.3345798 | CK13: =BY13 -> 3.1428571 | CL13: =(L13+M13)/H13 -> 0.12706283 | CN13: =CD13+CE13+CG13-SUM(CI13:CL13) -> 2.2441986e-08
B14: NW_B-H2in | D14: 6 | F14: 0.11587061 | G14: 0.0162 | H14: 0.070452767 | I14: 0 | J14: 0 | K14: 0 | L14: 0.008951928 | M14: 0 | N14: 6578.32 | O14: 6324.47 | P14: 0.11 | R14: {=_xlfn.XLOOKUP(D14, CP:CP, CQ:DD)} -> Drymill CCS Fermentation Exhaust | S14: Biomass_Corn | T14: 0 | U14: 0.085342825 | V14: 3.104338 | W14: 1.0133975 | X14: 1.7588667 | Y14: 0.35768767 | Z14: 0.68601739 | AA14: 0.15290642 | AB14: 0.032434696 | AC14: 45179.42 | AD14: 201481.25 | AE14: -25.28 | AG14: 107.50256 | AH14: -7.4 | AI14: 134.90067 | AJ14: 153.19849 | AK14: 116.05317 | AL14: 160 | AM14: 26.79773 | AN14: 27.883397 | AO14: 13.696721 | AQ14: =B14 -> NW_B-H2in | AR14: =C14 -> 0 | AS14: =SUM(AV14:BH14)+BJ14+BK14 -> 452.55518 | AT14: =SUM(AV14:BH14)+BM14+BN14 -> 452.55518 | AU14: =AS14-AT14 -> 0 | AV14: =F14/H14*AN14 -> 45.858615 | AW14: =G14/H14*AM14 -> 6.1619046 | AX14: =BR14 -> 10.45678 | AY14: =BQ14 -> 0 | AZ14: =BS14 -> 731.56501 | BA14: =I14/H14*AO14 -> 0 | BB14: =BT14 -> 63.464285 | BC14: =N14/H14/(0.9*8760) -> 11.843234 | BD14: =BU14 -> 26.20155 | BE14: =O14/H14/(0.9*8760) -> 11.386217 | BF14: =BV14 -> 116.84791 | BG14: =P14/H14 -> 1.5613297 | BH14: =BW14 -> -115.58727 | BI14: =SUM(CI14:CL14)-CD14 -> 0.84743172 | BJ14: =(AG14+AH14)*-1*(CJ14+CK14) -> -548.30548 | BK14: =BI14*AG14 -> 91.10108 | BL14: =CI14+CL14-CD14 -> -4.6300053 | BM14: =(CJ14+CK14)*AH14*-1 -> 40.533034 | BN14: =BL14*AG14 -> -497.73743 | BP14: =R14 -> Drymill CCS Fermentation Exhaust | BQ14: =T14/V14/H14*AM14*-1 -> 0 | BR14: =U14/V14/H14*AM14 -> 10.45678 | BS14: {=_xlfn.IFS(S14="Biomass_Corn", 1/V14/H14*AL14, S14="Biomass_Agri", 1/V14/H14*AK14, S14="Biomass_Wood", 1/V14/H14*AJ14, S14="Biomass_Herb", 1/V14/H14*AI14)} -> 731.56501 | BT14: =W14/V14/H14*AO14 -> 63.464285 | BU14: =AC14/V14/H14/(0.9*8760) -> 26.20155 | BV14: =AD14/V14/H14/(0.9*8760) -> 116.84791 | BW14: =AE14/V14/H14 -> -115.58727 | BY14: =22/7 -> 3.1428571 | BZ14: =X14 -> 1.7588667 | CA14: 0.18289084 | CB14: 0.23037491 | CD14: =BZ14/V14/H14 -> 8.0420332 | CE14: =IF(W14=0, 0, CA14*W14/V14/H14) -> 0.84743174 | CF14: =CB14/H14 -> 3.26992 | CG14: =IF(I14=0, 0, CA14*I14/H14) -> 0 | CI14: =(Z14+AB14)/V14/H14 -> 3.2849651 | CJ14: =(Y14+AA14)/V14/H14 -> 2.3345798 | CK14: =BY14 -> 3.1428571 | CL14: =(L14+M14)/H14 -> 0.12706283 | CN14: =CD14+CE14+CG14-SUM(CI14:CL14) -> 2.2441986e-08
B15: SW_B-H2in | D15: 6 | F15: 0.11587061 | G15: 0.0162 | H15: 0.070452767 | I15: 0 | J15: 0 | K15: 0 | L15: 0.008951928 | M15: 0 | N15: 6578.32 | O15: 6324.47 | P15: 0.11 | R15: {=_xlfn.XLOOKUP(D15, CP:CP, CQ:DD)} -> Drymill CCS Fermentation Exhaust | S15: Biomass_Corn | T15: 0 | U15: 0.085342825 | V15: 3.104338 | W15: 1.0133975 | X15: 1.7588667 | Y15: 0.35768767 | Z15: 0.68601739 | AA15: 0.15290642 | AB15: 0.032434696 | AC15: 45179.42 | AD15: 201481.25 | AE15: -25.28 | AG15: 107.50256 | AH15: -16.458953 | AI15: 121.90098 | AJ15: 139.17763 | AK15: 109.07949 | AL15: 160 | AM15: 27.982243 | AN15: 26.416189 | AO15: 13.696721 | AQ15: =B15 -> SW_B-H2in | AR15: =C15 -> 0 | AS15: =SUM(AV15:BH15)+BJ15+BK15 -> 500.49654 | AT15: =SUM(AV15:BH15)+BM15+BN15 -> 500.49654 | AU15: =AS15-AT15 -> 0 | AV15: =F15/H15*AN15 -> 43.445561 | AW15: =G15/H15*AM15 -> 6.434273 | AX15: =BR15 -> 10.91899 | AY15: =BQ15 -> 0 | AZ15: =BS15 -> 731.56501 | BA15: =I15/H15*AO15 -> 0 | BB15: =BT15 -> 63.464285 | BC15: =N15/H15/(0.9*8760) -> 11.843234 | BD15: =BU15 -> 26.20155 | BE15: =O15/H15/(0.9*8760) -> 11.386217 | BF15: =BV15 -> 116.84791 | BG15: =P15/H15 -> 1.5613297 | BH15: =BW15 -> -115.58727 | BI15: =SUM(CI15:CL15)-CD15 -> 0.84743172 | BJ15: =(AG15+AH15)*-1*(CJ15+CK15) -> -498.68563 | BK15: =BI15*AG15 -> 91.10108 | BL15: =CI15+CL15-CD15 -> -4.6300053 | BM15: =(CJ15+CK15)*AH15*-1 -> 90.152878 | BN15: =BL15*AG15 -> -497.73743 | BP15: =R15 -> Drymill CCS Fermentation Exhaust | BQ15: =T15/V15/H15*AM15*-1 -> 0 | BR15: =U15/V15/H15*AM15 -> 10.91899 | BS15: {=_xlfn.IFS(S15="Biomass_Corn", 1/V15/H15*AL15, S15="Biomass_Agri", 1/V15/H15*AK15, S15="Biomass_Wood", 1/V15/H15*AJ15, S15="Biomass_Herb", 1/V15/H15*AI15)} -> 731.56501 | BT15: =W15/V15/H15*AO15 -> 63.464285 | BU15: =AC15/V15/H15/(0.9*8760) -> 26.20155 | BV15: =AD15/V15/H15/(0.9*8760) -> 116.84791 | BW15: =AE15/V15/H15 -> -115.58727 | BY15: =22/7 -> 3.1428571 | BZ15: =X15 -> 1.7588667 | CA15: 0.18289084 | CB15: 0.23037491 | CD15: =BZ15/V15/H15 -> 8.0420332 | CE15: =IF(W15=0, 0, CA15*W15/V15/H15) -> 0.84743174 | CF15: =CB15/H15 -> 3.26992 | CG15: =IF(I15=0, 0, CA15*I15/H15) -> 0 | CI15: =(Z15+AB15)/V15/H15 -> 3.2849651 | CJ15: =(Y15+AA15)/V15/H15 -> 2.3345798 | CK15: =BY15 -> 3.1428571 | CL15: =(L15+M15)/H15 -> 0.12706283 | CN15: =CD15+CE15+CG15-SUM(CI15:CL15) -> 2.2441986e-08
B16: TX_B-H2in | D16: 6 | F16: 0.11587061 | G16: 0.0162 | H16: 0.070452767 | I16: 0 | J16: 0 | K16: 0 | L16: 0.008951928 | M16: 0 | N16: 6578.32 | O16: 6324.47 | P16: 0.11 | R16: {=_xlfn.XLOOKUP(D16, CP:CP, CQ:DD)} -> Drymill CCS Fermentation Exhaust | S16: Biomass_Corn | T16: 0 | U16: 0.085342825 | V16: 3.104338 | W16: 1.0133975 | X16: 1.7588667 | Y16: 0.35768767 | Z16: 0.68601739 | AA16: 0.15290642 | AB16: 0.032434696 | AC16: 45179.42 | AD16: 201481.25 | AE16: -25.28 | AG16: 107.50256 | AH16: -21.358133 | AI16: 134.78594 | AJ16: 154.49711 | AK16: 108.34628 | AL16: 160 | AM16: 20.1955 | AN16: 18.588213 | AO16: 13.326111 | AQ16: =B16 -> TX_B-H2in | AR16: =C16 -> 0 | AS16: =SUM(AV16:BH16)+BJ16+BK16 -> 507.91096 | AT16: =SUM(AV16:BH16)+BM16+BN16 -> 507.91096 | AU16: =AS16-AT16 -> 0 | AV16: =F16/H16*AN16 -> 30.571228 | AW16: =G16/H16*AM16 -> 4.6437793 | AX16: =BR16 -> 7.8805144 | AY16: =BQ16 -> 0 | AZ16: =BS16 -> 731.56501 | BA16: =I16/H16*AO16 -> 0 | BB16: =BT16 -> 61.747049 | BC16: =N16/H16/(0.9*8760) -> 11.843234 | BD16: =BU16 -> 26.20155 | BE16: =O16/H16/(0.9*8760) -> 11.386217 | BF16: =BV16 -> 116.84791 | BG16: =P16/H16 -> 1.5613297 | BH16: =BW16 -> -115.58727 | BI16: =SUM(CI16:CL16)-CD16 -> 0.84743172 | BJ16: =(AG16+AH16)*-1*(CJ16+CK16) -> -471.85068 | BK16: =BI16*AG16 -> 91.10108 | BL16: =CI16+CL16-CD16 -> -4.6300053 | BM16: =(CJ16+CK16)*AH16*-1 -> 116.98783 | BN16: =BL16*AG16 -> -497.73743 | BP16: =R16 -> Drymill CCS Fermentation Exhaust | BQ16: =T16/V16/H16*AM16*-1 -> 0 | BR16: =U16/V16/H16*AM16 -> 7.8805144 | BS16: {=_xlfn.IFS(S16="Biomass_Corn", 1/V16/H16*AL16, S16="Biomass_Agri", 1/V16/H16*AK16, S16="Biomass_Wood", 1/V16/H16*AJ16, S16="Biomass_Herb", 1/V16/H16*AI16)} -> 731.56501 | BT16: =W16/V16/H16*AO16 -> 61.747049 | BU16: =AC16/V16/H16/(0.9*8760) -> 26.20155 | BV16: =AD16/V16/H16/(0.9*8760) -> 116.84791 | BW16: =AE16/V16/H16 -> -115.58727 | BY16: =22/7 -> 3.1428571 | BZ16: =X16 -> 1.7588667 | CA16: 0.18289084 | CB16: 0.23037491 | CD16: =BZ16/V16/H16 -> 8.0420332 | CE16: =IF(W16=0, 0, CA16*W16/V16/H16) -> 0.84743174 | CF16: =CB16/H16 -> 3.26992 | CG16: =IF(I16=0, 0, CA16*I16/H16) -> 0 | CI16: =(Z16+AB16)/V16/H16 -> 3.2849651 | CJ16: =(Y16+AA16)/V16/H16 -> 2.3345798 | CK16: =BY16 -> 3.1428571 | CL16: =(L16+M16)/H16 -> 0.12706283 | CN16: =CD16+CE16+CG16-SUM(CI16:CL16) -> 2.2441986e-08
B17: NCEN_B-H2in | D17: 6 | F17: 0.11587061 | G17: 0.0162 | H17: 0.070452767 | I17: 0 | J17: 0 | K17: 0 | L17: 0.008951928 | M17: 0 | N17: 6578.32 | O17: 6324.47 | P17: 0.11 | R17: {=_xlfn.XLOOKUP(D17, CP:CP, CQ:DD)} -> Drymill CCS Fermentation Exhaust | S17: Biomass_Corn | T17: 0 | U17: 0.085342825 | V17: 3.104338 | W17: 1.0133975 | X17: 1.7588667 | Y17: 0.35768767 | Z17: 0.68601739 | AA17: 0.15290642 | AB17: 0.032434696 | AC17: 45179.42 | AD17: 201481.25 | AE17: -25.28 | AG17: 107.50256 | AH17: -41.580336 | AI17: 102.40263 | AJ17: 113.69796 | AK17: 90.50509 | AL17: 160 | AM17: 30.751318 | AN17: 27.653755 | AO17: 13.422023 | AQ17: =B17 -> NCEN_B-H2in | AR17: =C17 -> 0 | AS17: =SUM(AV17:BH17)+BJ17+BK17 -> 640.57713 | AT17: =SUM(AV17:BH17)+BM17+BN17 -> 640.57713 | AU17: =AS17-AT17 -> 0 | AV17: =F17/H17*AN17 -> 45.480932 | AW17: =G17/H17*AM17 -> 7.0709977 | AX17: =BR17 -> 11.999515 | AY17: =BQ17 -> 0 | AZ17: =BS17 -> 731.56501 | BA17: =I17/H17*AO17 -> 0 | BB17: =BT17 -> 62.191461 | BC17: =N17/H17/(0.9*8760) -> 11.843234 | BD17: =BU17 -> 26.20155 | BE17: =O17/H17/(0.9*8760) -> 11.386217 | BF17: =BV17 -> 116.84791 | BG17: =P17/H17 -> 1.5613297 | BH17: =BW17 -> -115.58727 | BI17: =SUM(CI17:CL17)-CD17 -> 0.84743172 | BJ17: =(AG17+AH17)*-1*(CJ17+CK17) -> -361.08484 | BK17: =BI17*AG17 -> 91.10108 | BL17: =CI17+CL17-CD17 -> -4.6300053 | BM17: =(CJ17+CK17)*AH17*-1 -> 227.75367 | BN17: =BL17*AG17 -> -497.73743 | BP17: =R17 -> Drymill CCS Fermentation Exhaust | BQ17: =T17/V17/H17*AM17*-1 -> 0 | BR17: =U17/V17/H17*AM17 -> 11.999515 | BS17: {=_xlfn.IFS(S17="Biomass_Corn", 1/V17/H17*AL17, S17="Biomass_Agri", 1/V17/H17*AK17, S17="Biomass_Wood", 1/V17/H17*AJ17, S17="Biomass_Herb", 1/V17/H17*AI17)} -> 731.56501 | BT17: =W17/V17/H17*AO17 -> 62.191461 | BU17: =AC17/V17/H17/(0.9*8760) -> 26.20155 | BV17: =AD17/V17/H17/(0.9*8760) -> 116.84791 | BW17: =AE17/V17/H17 -> -115.58727 | BY17: =22/7 -> 3.1428571 | BZ17: =X17 -> 1.7588667 | CA17: 0.18289084 | CB17: 0.23037491 | CD17: =BZ17/V17/H17 -> 8.0420332 | CE17: =IF(W17=0, 0, CA17*W17/V17/H17) -> 0.84743174 | CF17: =CB17/H17 -> 3.26992 | CG17: =IF(I17=0, 0, CA17*I17/H17) -> 0 | CI17: =(Z17+AB17)/V17/H17 -> 3.2849651 | CJ17: =(Y17+AA17)/V17/H17 -> 2.3345798 | CK17: =BY17 -> 3.1428571 | CL17: =(L17+M17)/H17 -> 0.12706283 | CN17: =CD17+CE17+CG17-SUM(CI17:CL17) -> 2.2441986e-08
B18: CEN_B-H2in | D18: 6 | F18: 0.11587061 | G18: 0.0162 | H18: 0.070452767 | I18: 0 | J18: 0 | K18: 0 | L18: 0.008951928 | M18: 0 | N18: 6578.32 | O18: 6324.47 | P18: 0.11 | R18: {=_xlfn.XLOOKUP(D18, CP:CP, CQ:DD)} -> Drymill CCS Fermentation Exhaust | S18: Biomass_Corn | T18: 0 | U18: 0.085342825 | V18: 3.104338 | W18: 1.0133975 | X18: 1.7588667 | Y18: 0.35768767 | Z18: 0.68601739 | AA18: 0.15290642 | AB18: 0.032434696 | AC18: 45179.42 | AD18: 201481.25 | AE18: -25.28 | AG18: 107.50256 | AH18: -31.564237 | AI18: 108.66061 | AJ18: 124.76345 | AK18: 95.964114 | AL18: 160 | AM18: 25.147071 | AN18: 25.749803 | AO18: 13.422023 | AQ18: =B18 -> CEN_B-H2in | AR18: =C18 -> 0 | AS18: =SUM(AV18:BH18)+BJ18+BK18 -> 579.10775 | AT18: =SUM(AV18:BH18)+BM18+BN18 -> 579.10775 | AU18: =AS18-AT18 -> 0 | AV18: =F18/H18*AN18 -> 42.349585 | AW18: =G18/H18*AM18 -> 5.7823499 | AX18: =BR18 -> 9.8126739 | AY18: =BQ18 -> 0 | AZ18: =BS18 -> 731.56501 | BA18: =I18/H18*AO18 -> 0 | BB18: =BT18 -> 62.191461 | BC18: =N18/H18/(0.9*8760) -> 11.843234 | BD18: =BU18 -> 26.20155 | BE18: =O18/H18/(0.9*8760) -> 11.386217 | BF18: =BV18 -> 116.84791 | BG18: =P18/H18 -> 1.5613297 | BH18: =BW18 -> -115.58727 | BI18: =SUM(CI18:CL18)-CD18 -> 0.84743172 | BJ18: =(AG18+AH18)*-1*(CJ18+CK18) -> -415.94739 | BK18: =BI18*AG18 -> 91.10108 | BL18: =CI18+CL18-CD18 -> -4.6300053 | BM18: =(CJ18+CK18)*AH18*-1 -> 172.89112 | BN18: =BL18*AG18 -> -497.73743 | BP18: =R18 -> Drymill CCS Fermentation Exhaust | BQ18: =T18/V18/H18*AM18*-1 -> 0 | BR18: =U18/V18/H18*AM18 -> 9.8126739 | BS18: {=_xlfn.IFS(S18="Biomass_Corn", 1/V18/H18*AL18, S18="Biomass_Agri", 1/V18/H18*AK18, S18="Biomass_Wood", 1/V18/H18*AJ18, S18="Biomass_Herb", 1/V18/H18*AI18)} -> 731.56501 | BT18: =W18/V18/H18*AO18 -> 62.191461 | BU18: =AC18/V18/H18/(0.9*8760) -> 26.20155 | BV18: =AD18/V18/H18/(0.9*8760) -> 116.84791 | BW18: =AE18/V18/H18 -> -115.58727 | BY18: =22/7 -> 3.1428571 | BZ18: =X18 -> 1.7588667 | CA18: 0.18289084 | CB18: 0.23037491 | CD18: =BZ18/V18/H18 -> 8.0420332 | CE18: =IF(W18=0, 0, CA18*W18/V18/H18) -> 0.84743174 | CF18: =CB18/H18 -> 3.26992 | CG18: =IF(I18=0, 0, CA18*I18/H18) -> 0 | CI18: =(Z18+AB18)/V18/H18 -> 3.2849651 | CJ18: =(Y18+AA18)/V18/H18 -> 2.3345798 | CK18: =BY18 -> 3.1428571 | CL18: =(L18+M18)/H18 -> 0.12706283 | CN18: =CD18+CE18+CG18-SUM(CI18:CL18) -> 2.2441986e-08
B19: SE_B-H2in | D19: 6 | F19: 0.11587061 | G19: 0.0162 | H19: 0.070452767 | I19: 0 | J19: 0 | K19: 0 | L19: 0.008951928 | M19: 0 | N19: 6578.32 | O19: 6324.47 | P19: 0.11 | R19: {=_xlfn.XLOOKUP(D19, CP:CP, CQ:DD)} -> Drymill CCS Fermentation Exhaust | S19: Biomass_Corn | T19: 0 | U19: 0.085342825 | V19: 3.104338 | W19: 1.0133975 | X19: 1.7588667 | Y19: 0.35768767 | Z19: 0.68601739 | AA19: 0.15290642 | AB19: 0.032434696 | AC19: 45179.42 | AD19: 201481.25 | AE19: -25.28 | AG19: 107.50256 | AH19: -47.666124 | AI19: 98.762212 | AJ19: 111.24126 | AK19: 88.010631 | AL19: 160 | AM19: 38.144019 | AN19: 30.118994 | AO19: 13.422023 | AQ19: =B19 -> SE_B-H2in | AR19: =C19 -> 0 | AS19: =SUM(AV19:BH19)+BJ19+BK19 -> 682.55073 | AT19: =SUM(AV19:BH19)+BM19+BN19 -> 682.55073 | AU19: =AS19-AT19 -> 0 | AV19: =F19/H19*AN19 -> 49.535404 | AW19: =G19/H19*AM19 -> 8.7708849 | AX19: =BR19 -> 14.884231 | AY19: =BQ19 -> 0 | AZ19: =BS19 -> 731.56501 | BA19: =I19/H19*AO19 -> 0 | BB19: =BT19 -> 62.191461 | BC19: =N19/H19/(0.9*8760) -> 11.843234 | BD19: =BU19 -> 26.20155 | BE19: =O19/H19/(0.9*8760) -> 11.386217 | BF19: =BV19 -> 116.84791 | BG19: =P19/H19 -> 1.5613297 | BH19: =BW19 -> -115.58727 | BI19: =SUM(CI19:CL19)-CD19 -> 0.84743172 | BJ19: =(AG19+AH19)*-1*(CJ19+CK19) -> -327.75032 | BK19: =BI19*AG19 -> 91.10108 | BL19: =CI19+CL19-CD19 -> -4.6300053 | BM19: =(CJ19+CK19)*AH19*-1 -> 261.08819 | BN19: =BL19*AG19 -> -497.73743 | BP19: =R19 -> Drymill CCS Fermentation Exhaust | BQ19: =T19/V19/H19*AM19*-1 -> 0 | BR19: =U19/V19/H19*AM19 -> 14.884231 | BS19: {=_xlfn.IFS(S19="Biomass_Corn", 1/V19/H19*AL19, S19="Biomass_Agri", 1/V19/H19*AK19, S19="Biomass_Wood", 1/V19/H19*AJ19, S19="Biomass_Herb", 1/V19/H19*AI19)} -> 731.56501 | BT19: =W19/V19/H19*AO19 -> 62.191461 | BU19: =AC19/V19/H19/(0.9*8760) -> 26.20155 | BV19: =AD19/V19/H19/(0.9*8760) -> 116.84791 | BW19: =AE19/V19/H19 -> -115.58727 | BY19: =22/7 -> 3.1428571 | BZ19: =X19 -> 1.7588667 | CA19: 0.18289084 | CB19: 0.23037491 | CD19: =BZ19/V19/H19 -> 8.0420332 | CE19: =IF(W19=0, 0, CA19*W19/V19/H19) -> 0.84743174 | CF19: =CB19/H19 -> 3.26992 | CG19: =IF(I19=0, 0, CA19*I19/H19) -> 0 | CI19: =(Z19+AB19)/V19/H19 -> 3.2849651 | CJ19: =(Y19+AA19)/V19/H19 -> 2.3345798 | CK19: =BY19 -> 3.1428571 | CL19: =(L19+M19)/H19 -> 0.12706283 | CN19: =CD19+CE19+CG19-SUM(CI19:CL19) -> 2.2441986e-08
B20: MIDAT_B-H2in | D20: 6 | F20: 0.11587061 | G20: 0.0162 | H20: 0.070452767 | I20: 0 | J20: 0 | K20: 0 | L20: 0.008951928 | M20: 0 | N20: 6578.32 | O20: 6324.47 | P20: 0.11 | R20: {=_xlfn.XLOOKUP(D20, CP:CP, CQ:DD)} -> Drymill CCS Fermentation Exhaust | S20: Biomass_Corn | T20: 0 | U20: 0.085342825 | V20: 3.104338 | W20: 1.0133975 | X20: 1.7588667 | Y20: 0.35768767 | Z20: 0.68601739 | AA20: 0.15290642 | AB20: 0.032434696 | AC20: 45179.42 | AD20: 201481.25 | AE20: -25.28 | AG20: 107.50256 | AH20: -49.879537 | AI20: 99.878528 | AJ20: 107.75134 | AK20: 88.568333 | AL20: 160 | AM20: 39.370157 | AN20: 31.385136 | AO20: 13.422023 | AQ20: =B20 -> MIDAT_B-H2in | AR20: =C20 -> 0 | AS20: =SUM(AV20:BH20)+BJ20+BK20 -> 697.51732 | AT20: =SUM(AV20:BH20)+BM20+BN20 -> 697.51732 | AU20: =AS20-AT20 -> 0 | AV20: =F20/H20*AN20 -> 51.617773 | AW20: =G20/H20*AM20 -> 9.0528246 | AX20: =BR20 -> 15.362684 | AY20: =BQ20 -> 0 | AZ20: =BS20 -> 731.56501 | BA20: =I20/H20*AO20 -> 0 | BB20: =BT20 -> 62.191461 | BC20: =N20/H20/(0.9*8760) -> 11.843234 | BD20: =BU20 -> 26.20155 | BE20: =O20/H20/(0.9*8760) -> 11.386217 | BF20: =BV20 -> 116.84791 | BG20: =P20/H20 -> 1.5613297 | BH20: =BW20 -> -115.58727 | BI20: =SUM(CI20:CL20)-CD20 -> 0.84743172 | BJ20: =(AG20+AH20)*-1*(CJ20+CK20) -> -315.62649 | BK20: =BI20*AG20 -> 91.10108 | BL20: =CI20+CL20-CD20 -> -4.6300053 | BM20: =(CJ20+CK20)*AH20*-1 -> 273.21202 | BN20: =BL20*AG20 -> -497.73743 | BP20: =R20 -> Drymill CCS Fermentation Exhaust | BQ20: =T20/V20/H20*AM20*-1 -> 0 | BR20: =U20/V20/H20*AM20 -> 15.362684 | BS20: {=_xlfn.IFS(S20="Biomass_Corn", 1/V20/H20*AL20, S20="Biomass_Agri", 1/V20/H20*AK20, S20="Biomass_Wood", 1/V20/H20*AJ20, S20="Biomass_Herb", 1/V20/H20*AI20)} -> 731.56501 | BT20: =W20/V20/H20*AO20 -> 62.191461 | BU20: =AC20/V20/H20/(0.9*8760) -> 26.20155 | BV20: =AD20/V20/H20/(0.9*8760) -> 116.84791 | BW20: =AE20/V20/H20 -> -115.58727 | BY20: =22/7 -> 3.1428571 | BZ20: =X20 -> 1.7588667 | CA20: 0.18289084 | CB20: 0.23037491 | CD20: =BZ20/V20/H20 -> 8.0420332 | CE20: =IF(W20=0, 0, CA20*W20/V20/H20) -> 0.84743174 | CF20: =CB20/H20 -> 3.26992 | CG20: =IF(I20=0, 0, CA20*I20/H20) -> 0 | CI20: =(Z20+AB20)/V20/H20 -> 3.2849651 | CJ20: =(Y20+AA20)/V20/H20 -> 2.3345798 | CK20: =BY20 -> 3.1428571 | CL20: =(L20+M20)/H20 -> 0.12706283 | CN20: =CD20+CE20+CG20-SUM(CI20:CL20) -> 2.2441986e-08
B21: NE_B-H2in | D21: 6 | F21: 0.11587061 | G21: 0.0162 | H21: 0.070452767 | I21: 0 | J21: 0 | K21: 0 | L21: 0.008951928 | M21: 0 | N21: 6578.32 | O21: 6324.47 | P21: 0.11 | R21: {=_xlfn.XLOOKUP(D21, CP:CP, CQ:DD)} -> Drymill CCS Fermentation Exhaust | S21: Biomass_Corn | T21: 0 | U21: 0.085342825 | V21: 3.104338 | W21: 1.0133975 | X21: 1.7588667 | Y21: 0.35768767 | Z21: 0.68601739 | AA21: 0.15290642 | AB21: 0.032434696 | AC21: 45179.42 | AD21: 201481.25 | AE21: -25.28 | AG21: 107.50256 | AH21: -59.252961 | AI21: 100.64964 | AJ21: 106.42207 | AK21: 90.784433 | AL21: 160 | AM21: 47.412137 | AN21: 33.344947 | AO21: 13.422023 | AQ21: =B21 -> NE_B-H2in | AR21: =C21 -> 0 | AS21: =SUM(AV21:BH21)+BJ21+BK21 -> 757.07013 | AT21: =SUM(AV21:BH21)+BM21+BN21 -> 757.07013 | AU21: =AS21-AT21 -> 0 | AV21: =F21/H21*AN21 -> 54.840989 | AW21: =G21/H21*AM21 -> 10.902008 | AX21: =BR21 -> 18.500757 | AY21: =BQ21 -> 0 | AZ21: =BS21 -> 731.56501 | BA21: =I21/H21*AO21 -> 0 | BB21: =BT21 -> 62.191461 | BC21: =N21/H21/(0.9*8760) -> 11.843234 | BD21: =BU21 -> 26.20155 | BE21: =O21/H21/(0.9*8760) -> 11.386217 | BF21: =BV21 -> 116.84791 | BG21: =P21/H21 -> 1.5613297 | BH21: =BW21 -> -115.58727 | BI21: =SUM(CI21:CL21)-CD21 -> 0.84743172 | BJ21: =(AG21+AH21)*-1*(CJ21+CK21) -> -264.28415 | BK21: =BI21*AG21 -> 91.10108 | BL21: =CI21+CL21-CD21 -> -4.6300053 | BM21: =(CJ21+CK21)*AH21*-1 -> 324.55436 | BN21: =BL21*AG21 -> -497.73743 | BP21: =R21 -> Drymill CCS Fermentation Exhaust | BQ21: =T21/V21/H21*AM21*-1 -> 0 | BR21: =U21/V21/H21*AM21 -> 18.500757 | BS21: {=_xlfn.IFS(S21="Biomass_Corn", 1/V21/H21*AL21, S21="Biomass_Agri", 1/V21/H21*AK21, S21="Biomass_Wood", 1/V21/H21*AJ21, S21="Biomass_Herb", 1/V21/H21*AI21)} -> 731.56501 | BT21: =W21/V21/H21*AO21 -> 62.191461 | BU21: =AC21/V21/H21/(0.9*8760) -> 26.20155 | BV21: =AD21/V21/H21/(0.9*8760) -> 116.84791 | BW21: =AE21/V21/H21 -> -115.58727 | BY21: =22/7 -> 3.1428571 | BZ21: =X21 -> 1.7588667 | CA21: 0.18289084 | CB21: 0.23037491 | CD21: =BZ21/V21/H21 -> 8.0420332 | CE21: =IF(W21=0, 0, CA21*W21/V21/H21) -> 0.84743174 | CF21: =CB21/H21 -> 3.26992 | CG21: =IF(I21=0, 0, CA21*I21/H21) -> 0 | CI21: =(Z21+AB21)/V21/H21 -> 3.2849651 | CJ21: =(Y21+AA21)/V21/H21 -> 2.3345798 | CK21: =BY21 -> 3.1428571 | CL21: =(L21+M21)/H21 -> 0.12706283 | CN21: =CD21+CE21+CG21-SUM(CI21:CL21) -> 2.2441986e-08
D22: 6 | R22: {=_xlfn.XLOOKUP(D22, CP:CP, CQ:DD)} -> Drymill CCS Fermentation Exhaust | S22: Biomass_Corn | T22: 0 | U22: 0.085342825 | V22: 3.104338 | W22: 1.0133975 | X22: 1.7588667 | Y22: 0.35768767 | Z22: 0.68601739 | AA22: 0.15290642 | AB22: 0.032434696 | AC22: 45179.42 | AD22: 201481.25 | AE22: -25.28 | AQ22: =B22 -> 0 | AR22: =C22 -> 0 | AS22: =SUM(AV22:BH22)+BJ22+BK22 -> #DIV/0! | AT22: =SUM(AV22:BH22)+BM22+BN22 -> #DIV/0! | AU22: =AS22-AT22 -> #DIV/0! | AV22: =F22/H22*AN22 -> #DIV/0! | AW22: =G22/H22*AM22 -> #DIV/0! | AX22: =BR22 -> #DIV/0! | AY22: =BQ22 -> #DIV/0! | AZ22: =BS22 -> #DIV/0! | BA22: =I22/H22*AO22 -> #DIV/0! | BB22: =BT22 -> #DIV/0! | BC22: =N22/H22/(0.9*8760) -> #DIV/0! | BD22: =BU22 -> #DIV/0! | BE22: =O22/H22/(0.9*8760) -> #DIV/0! | BF22: =BV22 -> #DIV/0! | BG22: =P22/H22 -> #DIV/0! | BH22: =BW22 -> #DIV/0! | BI22: =SUM(CI22:CL22)-CD22 -> #DIV/0! | BJ22: =(AG22+AH22)*-1*(CJ22+CK22) -> #DIV/0! | BK22: =BI22*AG22 -> #DIV/0! | BL22: =CI22+CL22-CD22 -> #DIV/0! | BM22: =(CJ22+CK22)*AH22*-1 -> #DIV/0! | BN22: =BL22*AG22 -> #DIV/0! | BP22: =R22 -> Drymill CCS Fermentation Exhaust | BQ22: =T22/V22/H22*AM22*-1 -> #DIV/0! | BR22: =U22/V22/H22*AM22 -> #DIV/0! | BS22: {=_xlfn.IFS(S22="Biomass_Corn", 1/V22/H22*AL22, S22="Biomass_Agri", 1/V22/H22*AK22, S22="Biomass_Wood", 1/V22/H22*AJ22, S22="Biomass_Herb", 1/V22/H22*AI22)} -> #DIV/0! | BT22: =W22/V22/H22*AO22 -> #DIV/0! | BU22: =AC22/V22/H22/(0.9*8760) -> #DIV/0! | BV22: =AD22/V22/H22/(0.9*8760) -> #DIV/0! | BW22: =AE22/V22/H22 -> #DIV/0! | BY22: =22/7 -> 3.1428571 | BZ22: =X22 -> 1.7588667 | CA22: 0.18289084 | CB22: 0.23037491 | CD22: =BZ22/V22/H22 -> #DIV/0! | CE22: =IF(W22=0, 0, CA22*W22/V22/H22) -> #DIV/0! | CF22: =CB22/H22 -> #DIV/0! | CG22: =IF(I22=0, 0, CA22*I22/H22) -> 0 | CI22: =(Z22+AB22)/V22/H22 -> #DIV/0! | CJ22: =(Y22+AA22)/V22/H22 -> #DIV/0! | CK22: =BY22 -> 3.1428571 | CL22: =(L22+M22)/H22 -> #DIV/0! | CN22: =CD22+CE22+CG22-SUM(CI22:CL22) -> #DIV/0!
D23: 6 | R23: {=_xlfn.XLOOKUP(D23, CP:CP, CQ:DD)} -> Drymill CCS Fermentation Exhaust | S23: Biomass_Corn | T23: 0 | U23: 0.085342825 | V23: 3.104338 | W23: 1.0133975 | X23: 1.7588667 | Y23: 0.35768767 | Z23: 0.68601739 | AA23: 0.15290642 | AB23: 0.032434696 | AC23: 45179.42 | AD23: 201481.25 | AE23: -25.28 | AQ23: =B23 -> 0 | AR23: =C23 -> 0 | AS23: =SUM(AV23:BH23)+BJ23+BK23 -> #DIV/0! | AT23: =SUM(AV23:BH23)+BM23+BN23 -> #DIV/0! | AU23: =AS23-AT23 -> #DIV/0! | AV23: =F23/H23*AN23 -> #DIV/0! | AW23: =G23/H23*AM23 -> #DIV/0! | AX23: =BR23 -> #DIV/0! | AY23: =BQ23 -> #DIV/0! | AZ23: =BS23 -> #DIV/0! | BA23: =I23/H23*AO23 -> #DIV/0! | BB23: =BT23 -> #DIV/0! | BC23: =N23/H23/(0.9*8760) -> #DIV/0! | BD23: =BU23 -> #DIV/0! | BE23: =O23/H23/(0.9*8760) -> #DIV/0! | BF23: =BV23 -> #DIV/0! | BG23: =P23/H23 -> #DIV/0! | BH23: =BW23 -> #DIV/0! | BI23: =SUM(CI23:CL23)-CD23 -> #DIV/0! | BJ23: =(AG23+AH23)*-1*(CJ23+CK23) -> #DIV/0! | BK23: =BI23*AG23 -> #DIV/0! | BL23: =CI23+CL23-CD23 -> #DIV/0! | BM23: =(CJ23+CK23)*AH23*-1 -> #DIV/0! | BN23: =BL23*AG23 -> #DIV/0! | BP23: =R23 -> Drymill CCS Fermentation Exhaust | BQ23: =T23/V23/H23*AM23*-1 -> #DIV/0! | BR23: =U23/V23/H23*AM23 -> #DIV/0! | BS23: {=_xlfn.IFS(S23="Biomass_Corn", 1/V23/H23*AL23, S23="Biomass_Agri", 1/V23/H23*AK23, S23="Biomass_Wood", 1/V23/H23*AJ23, S23="Biomass_Herb", 1/V23/H23*AI23)} -> #DIV/0! | BT23: =W23/V23/H23*AO23 -> #DIV/0! | BU23: =AC23/V23/H23/(0.9*8760) -> #DIV/0! | BV23: =AD23/V23/H23/(0.9*8760) -> #DIV/0! | BW23: =AE23/V23/H23 -> #DIV/0! | BY23: =22/7 -> 3.1428571 | BZ23: =X23 -> 1.7588667 | CA23: 0.18289084 | CB23: 0.23037491 | CD23: =BZ23/V23/H23 -> #DIV/0! | CE23: =IF(W23=0, 0, CA23*W23/V23/H23) -> #DIV/0! | CF23: =CB23/H23 -> #DIV/0! | CG23: =IF(I23=0, 0, CA23*I23/H23) -> 0 | CI23: =(Z23+AB23)/V23/H23 -> #DIV/0! | CJ23: =(Y23+AA23)/V23/H23 -> #DIV/0! | CK23: =BY23 -> 3.1428571 | CL23: =(L23+M23)/H23 -> #DIV/0! | CN23: =CD23+CE23+CG23-SUM(CI23:CL23) -> #DIV/0!
D24: 6 | R24: {=_xlfn.XLOOKUP(D24, CP:CP, CQ:DD)} -> Drymill CCS Fermentation Exhaust | S24: Biomass_Corn | T24: 0 | U24: 0.085342825 | V24: 3.104338 | W24: 1.0133975 | X24: 1.7588667 | Y24: 0.35768767 | Z24: 0.68601739 | AA24: 0.15290642 | AB24: 0.032434696 | AC24: 45179.42 | AD24: 201481.25 | AE24: -25.28 | AQ24: =B24 -> 0 | AR24: =C24 -> 0 | AS24: =SUM(AV24:BH24)+BJ24+BK24 -> #DIV/0! | AT24: =SUM(AV24:BH24)+BM24+BN24 -> #DIV/0! | AU24: =AS24-AT24 -> #DIV/0! | AV24: =F24/H24*AN24 -> #DIV/0! | AW24: =G24/H24*AM24 -> #DIV/0! | AX24: =BR24 -> #DIV/0! | AY24: =BQ24 -> #DIV/0! | AZ24: =BS24 -> #DIV/0! | BA24: =I24/H24*AO24 -> #DIV/0! | BB24: =BT24 -> #DIV/0! | BC24: =N24/H24/(0.9*8760) -> #DIV/0! | BD24: =BU24 -> #DIV/0! | BE24: =O24/H24/(0.9*8760) -> #DIV/0! | BF24: =BV24 -> #DIV/0! | BG24: =P24/H24 -> #DIV/0! | BH24: =BW24 -> #DIV/0! | BI24: =SUM(CI24:CL24)-CD24 -> #DIV/0! | BJ24: =(AG24+AH24)*-1*(CJ24+CK24) -> #DIV/0! | BK24: =BI24*AG24 -> #DIV/0! | BL24: =CI24+CL24-CD24 -> #DIV/0! | BM24: =(CJ24+CK24)*AH24*-1 -> #DIV/0! | BN24: =BL24*AG24 -> #DIV/0! | BP24: =R24 -> Drymill CCS Fermentation Exhaust | BQ24: =T24/V24/H24*AM24*-1 -> #DIV/0! | BR24: =U24/V24/H24*AM24 -> #DIV/0! | BS24: {=_xlfn.IFS(S24="Biomass_Corn", 1/V24/H24*AL24, S24="Biomass_Agri", 1/V24/H24*AK24, S24="Biomass_Wood", 1/V24/H24*AJ24, S24="Biomass_Herb", 1/V24/H24*AI24)} -> #DIV/0! | BT24: =W24/V24/H24*AO24 -> #DIV/0! | BU24: =AC24/V24/H24/(0.9*8760) -> #DIV/0! | BV24: =AD24/V24/H24/(0.9*8760) -> #DIV/0! | BW24: =AE24/V24/H24 -> #DIV/0! | BY24: =22/7 -> 3.1428571 | BZ24: =X24 -> 1.7588667 | CA24: 0.18289084 | CB24: 0.23037491 | CD24: =BZ24/V24/H24 -> #DIV/0! | CE24: =IF(W24=0, 0, CA24*W24/V24/H24) -> #DIV/0! | CF24: =CB24/H24 -> #DIV/0! | CG24: =IF(I24=0, 0, CA24*I24/H24) -> 0 | CI24: =(Z24+AB24)/V24/H24 -> #DIV/0! | CJ24: =(Y24+AA24)/V24/H24 -> #DIV/0! | CK24: =BY24 -> 3.1428571 | CL24: =(L24+M24)/H24 -> #DIV/0! | CN24: =CD24+CE24+CG24-SUM(CI24:CL24) -> #DIV/0!
D25: 6 | R25: {=_xlfn.XLOOKUP(D25, CP:CP, CQ:DD)} -> Drymill CCS Fermentation Exhaust | S25: Biomass_Corn | T25: 0 | U25: 0.085342825 | V25: 3.104338 | W25: 1.0133975 | X25: 1.7588667 | Y25: 0.35768767 | Z25: 0.68601739 | AA25: 0.15290642 | AB25: 0.032434696 | AC25: 45179.42 | AD25: 201481.25 | AE25: -25.28 | AQ25: =B25 -> 0 | AR25: =C25 -> 0 | AS25: =SUM(AV25:BH25)+BJ25+BK25 -> #DIV/0! | AT25: =SUM(AV25:BH25)+BM25+BN25 -> #DIV/0! | AU25: =AS25-AT25 -> #DIV/0! | AV25: =F25/H25*AN25 -> #DIV/0! | AW25: =G25/H25*AM25 -> #DIV/0! | AX25: =BR25 -> #DIV/0! | AY25: =BQ25 -> #DIV/0! | AZ25: =BS25 -> #DIV/0! | BA25: =I25/H25*AO25 -> #DIV/0! | BB25: =BT25 -> #DIV/0! | BC25: =N25/H25/(0.9*8760) -> #DIV/0! | BD25: =BU25 -> #DIV/0! | BE25: =O25/H25/(0.9*8760) -> #DIV/0! | BF25: =BV25 -> #DIV/0! | BG25: =P25/H25 -> #DIV/0! | BH25: =BW25 -> #DIV/0! | BI25: =SUM(CI25:CL25)-CD25 -> #DIV/0! | BJ25: =(AG25+AH25)*-1*(CJ25+CK25) -> #DIV/0! | BK25: =BI25*AG25 -> #DIV/0! | BL25: =CI25+CL25-CD25 -> #DIV/0! | BM25: =(CJ25+CK25)*AH25*-1 -> #DIV/0! | BN25: =BL25*AG25 -> #DIV/0! | BP25: =R25 -> Drymill CCS Fermentation Exhaust | BQ25: =T25/V25/H25*AM25*-1 -> #DIV/0! | BR25: =U25/V25/H25*AM25 -> #DIV/0! | BS25: {=_xlfn.IFS(S25="Biomass_Corn", 1/V25/H25*AL25, S25="Biomass_Agri", 1/V25/H25*AK25, S25="Biomass_Wood", 1/V25/H25*AJ25, S25="Biomass_Herb", 1/V25/H25*AI25)} -> #DIV/0! | BT25: =W25/V25/H25*AO25 -> #DIV/0! | BU25: =AC25/V25/H25/(0.9*8760) -> #DIV/0! | BV25: =AD25/V25/H25/(0.9*8760) -> #DIV/0! | BW25: =AE25/V25/H25 -> #DIV/0! | BY25: =22/7 -> 3.1428571 | BZ25: =X25 -> 1.7588667 | CA25: 0.18289084 | CB25: 0.23037491 | CD25: =BZ25/V25/H25 -> #DIV/0! | CE25: =IF(W25=0, 0, CA25*W25/V25/H25) -> #DIV/0! | CF25: =CB25/H25 -> #DIV/0! | CG25: =IF(I25=0, 0, CA25*I25/H25) -> 0 | CI25: =(Z25+AB25)/V25/H25 -> #DIV/0! | CJ25: =(Y25+AA25)/V25/H25 -> #DIV/0! | CK25: =BY25 -> 3.1428571 | CL25: =(L25+M25)/H25 -> #DIV/0! | CN25: =CD25+CE25+CG25-SUM(CI25:CL25) -> #DIV/0!
D26: 6 | R26: {=_xlfn.XLOOKUP(D26, CP:CP, CQ:DD)} -> Drymill CCS Fermentation Exhaust | S26: Biomass_Corn | T26: 0 | U26: 0.085342825 | V26: 3.104338 | W26: 1.0133975 | X26: 1.7588667 | Y26: 0.35768767 | Z26: 0.68601739 | AA26: 0.15290642 | AB26: 0.032434696 | AC26: 45179.42 | AD26: 201481.25 | AE26: -25.28 | AQ26: =B26 -> 0 | AR26: =C26 -> 0 | AS26: =SUM(AV26:BH26)+BJ26+BK26 -> #DIV/0! | AT26: =SUM(AV26:BH26)+BM26+BN26 -> #DIV/0! | AU26: =AS26-AT26 -> #DIV/0! | AV26: =F26/H26*AN26 -> #DIV/0! | AW26: =G26/H26*AM26 -> #DIV/0! | AX26: =BR26 -> #DIV/0! | AY26: =BQ26 -> #DIV/0! | AZ26: =BS26 -> #DIV/0! | BA26: =I26/H26*AO26 -> #DIV/0! | BB26: =BT26 -> #DIV/0! | BC26: =N26/H26/(0.9*8760) -> #DIV/0! | BD26: =BU26 -> #DIV/0! | BE26: =O26/H26/(0.9*8760) -> #DIV/0! | BF26: =BV26 -> #DIV/0! | BG26: =P26/H26 -> #DIV/0! | BH26: =BW26 -> #DIV/0! | BI26: =SUM(CI26:CL26)-CD26 -> #DIV/0! | BJ26: =(AG26+AH26)*-1*(CJ26+CK26) -> #DIV/0! | BK26: =BI26*AG26 -> #DIV/0! | BL26: =CI26+CL26-CD26 -> #DIV/0! | BM26: =(CJ26+CK26)*AH26*-1 -> #DIV/0! | BN26: =BL26*AG26 -> #DIV/0! | BP26: =R26 -> Drymill CCS Fermentation Exhaust | BQ26: =T26/V26/H26*AM26*-1 -> #DIV/0! | BR26: =U26/V26/H26*AM26 -> #DIV/0! | BS26: {=_xlfn.IFS(S26="Biomass_Corn", 1/V26/H26*AL26, S26="Biomass_Agri", 1/V26/H26*AK26, S26="Biomass_Wood", 1/V26/H26*AJ26, S26="Biomass_Herb", 1/V26/H26*AI26)} -> #DIV/0! | BT26: =W26/V26/H26*AO26 -> #DIV/0! | BU26: =AC26/V26/H26/(0.9*8760) -> #DIV/0! | BV26: =AD26/V26/H26/(0.9*8760) -> #DIV/0! | BW26: =AE26/V26/H26 -> #DIV/0! | BY26: =22/7 -> 3.1428571 | BZ26: =X26 -> 1.7588667 | CA26: 0.18289084 | CB26: 0.23037491 | CD26: =BZ26/V26/H26 -> #DIV/0! | CE26: =IF(W26=0, 0, CA26*W26/V26/H26) -> #DIV/0! | CF26: =CB26/H26 -> #DIV/0! | CG26: =IF(I26=0, 0, CA26*I26/H26) -> 0 | CI26: =(Z26+AB26)/V26/H26 -> #DIV/0! | CJ26: =(Y26+AA26)/V26/H26 -> #DIV/0! | CK26: =BY26 -> 3.1428571 | CL26: =(L26+M26)/H26 -> #DIV/0! | CN26: =CD26+CE26+CG26-SUM(CI26:CL26) -> #DIV/0!
D27: 6 | R27: {=_xlfn.XLOOKUP(D27, CP:CP, CQ:DD)} -> Drymill CCS Fermentation Exhaust | S27: Biomass_Corn | T27: 0 | U27: 0.085342825 | V27: 3.104338 | W27: 1.0133975 | X27: 1.7588667 | Y27: 0.35768767 | Z27: 0.68601739 | AA27: 0.15290642 | AB27: 0.032434696 | AC27: 45179.42 | AD27: 201481.25 | AE27: -25.28 | AQ27: =B27 -> 0 | AR27: =C27 -> 0 | AS27: =SUM(AV27:BH27)+BJ27+BK27 -> #DIV/0! | AT27: =SUM(AV27:BH27)+BM27+BN27 -> #DIV/0! | AU27: =AS27-AT27 -> #DIV/0! | AV27: =F27/H27*AN27 -> #DIV/0! | AW27: =G27/H27*AM27 -> #DIV/0! | AX27: =BR27 -> #DIV/0! | AY27: =BQ27 -> #DIV/0! | AZ27: =BS27 -> #DIV/0! | BA27: =I27/H27*AO27 -> #DIV/0! | BB27: =BT27 -> #DIV/0! | BC27: =N27/H27/(0.9*8760) -> #DIV/0! | BD27: =BU27 -> #DIV/0! | BE27: =O27/H27/(0.9*8760) -> #DIV/0! | BF27: =BV27 -> #DIV/0! | BG27: =P27/H27 -> #DIV/0! | BH27: =BW27 -> #DIV/0! | BI27: =SUM(CI27:CL27)-CD27 -> #DIV/0! | BJ27: =(AG27+AH27)*-1*(CJ27+CK27) -> #DIV/0! | BK27: =BI27*AG27 -> #DIV/0! | BL27: =CI27+CL27-CD27 -> #DIV/0! | BM27: =(CJ27+CK27)*AH27*-1 -> #DIV/0! | BN27: =BL27*AG27 -> #DIV/0! | BP27: =R27 -> Drymill CCS Fermentation Exhaust | BQ27: =T27/V27/H27*AM27*-1 -> #DIV/0! | BR27: =U27/V27/H27*AM27 -> #DIV/0! | BS27: {=_xlfn.IFS(S27="Biomass_Corn", 1/V27/H27*AL27, S27="Biomass_Agri", 1/V27/H27*AK27, S27="Biomass_Wood", 1/V27/H27*AJ27, S27="Biomass_Herb", 1/V27/H27*AI27)} -> #DIV/0! | BT27: =W27/V27/H27*AO27 -> #DIV/0! | BU27: =AC27/V27/H27/(0.9*8760) -> #DIV/0! | BV27: =AD27/V27/H27/(0.9*8760) -> #DIV/0! | BW27: =AE27/V27/H27 -> #DIV/0! | BY27: =22/7 -> 3.1428571 | BZ27: =X27 -> 1.7588667 | CA27: 0.18289084 | CB27: 0.23037491 | CD27: =BZ27/V27/H27 -> #DIV/0! | CE27: =IF(W27=0, 0, CA27*W27/V27/H27) -> #DIV/0! | CF27: =CB27/H27 -> #DIV/0! | CG27: =IF(I27=0, 0, CA27*I27/H27) -> 0 | CI27: =(Z27+AB27)/V27/H27 -> #DIV/0! | CJ27: =(Y27+AA27)/V27/H27 -> #DIV/0! | CK27: =BY27 -> 3.1428571 | CL27: =(L27+M27)/H27 -> #DIV/0! | CN27: =CD27+CE27+CG27-SUM(CI27:CL27) -> #DIV/0!
D28: 6 | R28: {=_xlfn.XLOOKUP(D28, CP:CP, CQ:DD)} -> Drymill CCS Fermentation Exhaust | S28: Biomass_Corn | T28: 0 | U28: 0.085342825 | V28: 3.104338 | W28: 1.0133975 | X28: 1.7588667 | Y28: 0.35768767 | Z28: 0.68601739 | AA28: 0.15290642 | AB28: 0.032434696 | AC28: 45179.42 | AD28: 201481.25 | AE28: -25.28 | AQ28: =B28 -> 0 | AR28: =C28 -> 0 | AS28: =SUM(AV28:BH28)+BJ28+BK28 -> #DIV/0! | AT28: =SUM(AV28:BH28)+BM28+BN28 -> #DIV/0! | AU28: =AS28-AT28 -> #DIV/0! | AV28: =F28/H28*AN28 -> #DIV/0! | AW28: =G28/H28*AM28 -> #DIV/0! | AX28: =BR28 -> #DIV/0! | AY28: =BQ28 -> #DIV/0! | AZ28: =BS28 -> #DIV/0! | BA28: =I28/H28*AO28 -> #DIV/0! | BB28: =BT28 -> #DIV/0! | BC28: =N28/H28/(0.9*8760) -> #DIV/0! | BD28: =BU28 -> #DIV/0! | BE28: =O28/H28/(0.9*8760) -> #DIV/0! | BF28: =BV28 -> #DIV/0! | BG28: =P28/H28 -> #DIV/0! | BH28: =BW28 -> #DIV/0! | BI28: =SUM(CI28:CL28)-CD28 -> #DIV/0! | BJ28: =(AG28+AH28)*-1*(CJ28+CK28) -> #DIV/0! | BK28: =BI28*AG28 -> #DIV/0! | BL28: =CI28+CL28-CD28 -> #DIV/0! | BM28: =(CJ28+CK28)*AH28*-1 -> #DIV/0! | BN28: =BL28*AG28 -> #DIV/0! | BP28: =R28 -> Drymill CCS Fermentation Exhaust | BQ28: =T28/V28/H28*AM28*-1 -> #DIV/0! | BR28: =U28/V28/H28*AM28 -> #DIV/0! | BS28: {=_xlfn.IFS(S28="Biomass_Corn", 1/V28/H28*AL28, S28="Biomass_Agri", 1/V28/H28*AK28, S28="Biomass_Wood", 1/V28/H28*AJ28, S28="Biomass_Herb", 1/V28/H28*AI28)} -> #DIV/0! | BT28: =W28/V28/H28*AO28 -> #DIV/0! | BU28: =AC28/V28/H28/(0.9*8760) -> #DIV/0! | BV28: =AD28/V28/H28/(0.9*8760) -> #DIV/0! | BW28: =AE28/V28/H28 -> #DIV/0! | BY28: =22/7 -> 3.1428571 | BZ28: =X28 -> 1.7588667 | CA28: 0.18289084 | CB28: 0.23037491 | CD28: =BZ28/V28/H28 -> #DIV/0! | CE28: =IF(W28=0, 0, CA28*W28/V28/H28) -> #DIV/0! | CF28: =CB28/H28 -> #DIV/0! | CG28: =IF(I28=0, 0, CA28*I28/H28) -> 0 | CI28: =(Z28+AB28)/V28/H28 -> #DIV/0! | CJ28: =(Y28+AA28)/V28/H28 -> #DIV/0! | CK28: =BY28 -> 3.1428571 | CL28: =(L28+M28)/H28 -> #DIV/0! | CN28: =CD28+CE28+CG28-SUM(CI28:CL28) -> #DIV/0!
D29: 6 | R29: {=_xlfn.XLOOKUP(D29, CP:CP, CQ:DD)} -> Drymill CCS Fermentation Exhaust | S29: Biomass_Corn | T29: 0 | U29: 0.085342825 | V29: 3.104338 | W29: 1.0133975 | X29: 1.7588667 | Y29: 0.35768767 | Z29: 0.68601739 | AA29: 0.15290642 | AB29: 0.032434696 | AC29: 45179.42 | AD29: 201481.25 | AE29: -25.28 | AQ29: =B29 -> 0 | AR29: =C29 -> 0 | AS29: =SUM(AV29:BH29)+BJ29+BK29 -> #DIV/0! | AT29: =SUM(AV29:BH29)+BM29+BN29 -> #DIV/0! | AU29: =AS29-AT29 -> #DIV/0! | AV29: =F29/H29*AN29 -> #DIV/0! | AW29: =G29/H29*AM29 -> #DIV/0! | AX29: =BR29 -> #DIV/0! | AY29: =BQ29 -> #DIV/0! | AZ29: =BS29 -> #DIV/0! | BA29: =I29/H29*AO29 -> #DIV/0! | BB29: =BT29 -> #DIV/0! | BC29: =N29/H29/(0.9*8760) -> #DIV/0! | BD29: =BU29 -> #DIV/0! | BE29: =O29/H29/(0.9*8760) -> #DIV/0! | BF29: =BV29 -> #DIV/0! | BG29: =P29/H29 -> #DIV/0! | BH29: =BW29 -> #DIV/0! | BI29: =SUM(CI29:CL29)-CD29 -> #DIV/0! | BJ29: =(AG29+AH29)*-1*(CJ29+CK29) -> #DIV/0! | BK29: =BI29*AG29 -> #DIV/0! | BL29: =CI29+CL29-CD29 -> #DIV/0! | BM29: =(CJ29+CK29)*AH29*-1 -> #DIV/0! | BN29: =BL29*AG29 -> #DIV/0! | BP29: =R29 -> Drymill CCS Fermentation Exhaust | BQ29: =T29/V29/H29*AM29*-1 -> #DIV/0! | BR29: =U29/V29/H29*AM29 -> #DIV/0! | BS29: {=_xlfn.IFS(S29="Biomass_Corn", 1/V29/H29*AL29, S29="Biomass_Agri", 1/V29/H29*AK29, S29="Biomass_Wood", 1/V29/H29*AJ29, S29="Biomass_Herb", 1/V29/H29*AI29)} -> #DIV/0! | BT29: =W29/V29/H29*AO29 -> #DIV/0! | BU29: =AC29/V29/H29/(0.9*8760) -> #DIV/0! | BV29: =AD29/V29/H29/(0.9*8760) -> #DIV/0! | BW29: =AE29/V29/H29 -> #DIV/0! | BY29: =22/7 -> 3.1428571 | BZ29: =X29 -> 1.7588667 | CA29: 0.18289084 | CB29: 0.23037491 | CD29: =BZ29/V29/H29 -> #DIV/0! | CE29: =IF(W29=0, 0, CA29*W29/V29/H29) -> #DIV/0! | CF29: =CB29/H29 -> #DIV/0! | CG29: =IF(I29=0, 0, CA29*I29/H29) -> 0 | CI29: =(Z29+AB29)/V29/H29 -> #DIV/0! | CJ29: =(Y29+AA29)/V29/H29 -> #DIV/0! | CK29: =BY29 -> 3.1428571 | CL29: =(L29+M29)/H29 -> #DIV/0! | CN29: =CD29+CE29+CG29-SUM(CI29:CL29) -> #DIV/0!
D30: 6 | R30: {=_xlfn.XLOOKUP(D30, CP:CP, CQ:DD)} -> Drymill CCS Fermentation Exhaust | S30: Biomass_Corn | T30: 0 | U30: 0.085342825 | V30: 3.104338 | W30: 1.0133975 | X30: 1.7588667 | Y30: 0.35768767 | Z30: 0.68601739 | AA30: 0.15290642 | AB30: 0.032434696 | AC30: 45179.42 | AD30: 201481.25 | AE30: -25.28 | AQ30: =B30 -> 0 | AR30: =C30 -> 0 | AS30: =SUM(AV30:BH30)+BJ30+BK30 -> #DIV/0! | AT30: =SUM(AV30:BH30)+BM30+BN30 -> #DIV/0! | AU30: =AS30-AT30 -> #DIV/0! | AV30: =F30/H30*AN30 -> #DIV/0! | AW30: =G30/H30*AM30 -> #DIV/0! | AX30: =BR30 -> #DIV/0! | AY30: =BQ30 -> #DIV/0! | AZ30: =BS30 -> #DIV/0! | BA30: =I30/H30*AO30 -> #DIV/0! | BB30: =BT30 -> #DIV/0! | BC30: =N30/H30/(0.9*8760) -> #DIV/0! | BD30: =BU30 -> #DIV/0! | BE30: =O30/H30/(0.9*8760) -> #DIV/0! | BF30: =BV30 -> #DIV/0! | BG30: =P30/H30 -> #DIV/0! | BH30: =BW30 -> #DIV/0! | BI30: =SUM(CI30:CL30)-CD30 -> #DIV/0! | BJ30: =(AG30+AH30)*-1*(CJ30+CK30) -> #DIV/0! | BK30: =BI30*AG30 -> #DIV/0! | BL30: =CI30+CL30-CD30 -> #DIV/0! | BM30: =(CJ30+CK30)*AH30*-1 -> #DIV/0! | BN30: =BL30*AG30 -> #DIV/0! | BP30: =R30 -> Drymill CCS Fermentation Exhaust | BQ30: =T30/V30/H30*AM30*-1 -> #DIV/0! | BR30: =U30/V30/H30*AM30 -> #DIV/0! | BS30: {=_xlfn.IFS(S30="Biomass_Corn", 1/V30/H30*AL30, S30="Biomass_Agri", 1/V30/H30*AK30, S30="Biomass_Wood", 1/V30/H30*AJ30, S30="Biomass_Herb", 1/V30/H30*AI30)} -> #DIV/0! | BT30: =W30/V30/H30*AO30 -> #DIV/0! | BU30: =AC30/V30/H30/(0.9*8760) -> #DIV/0! | BV30: =AD30/V30/H30/(0.9*8760) -> #DIV/0! | BW30: =AE30/V30/H30 -> #DIV/0! | BY30: =22/7 -> 3.1428571 | BZ30: =X30 -> 1.7588667 | CA30: 0.18289084 | CB30: 0.23037491 | CD30: =BZ30/V30/H30 -> #DIV/0! | CE30: =IF(W30=0, 0, CA30*W30/V30/H30) -> #DIV/0! | CF30: =CB30/H30 -> #DIV/0! | CG30: =IF(I30=0, 0, CA30*I30/H30) -> 0 | CI30: =(Z30+AB30)/V30/H30 -> #DIV/0! | CJ30: =(Y30+AA30)/V30/H30 -> #DIV/0! | CK30: =BY30 -> 3.1428571 | CL30: =(L30+M30)/H30 -> #DIV/0! | CN30: =CD30+CE30+CG30-SUM(CI30:CL30) -> #DIV/0!
D31: 6 | R31: {=_xlfn.XLOOKUP(D31, CP:CP, CQ:DD)} -> Drymill CCS Fermentation Exhaust | S31: Biomass_Corn | T31: 0 | U31: 0.085342825 | V31: 3.104338 | W31: 1.0133975 | X31: 1.7588667 | Y31: 0.35768767 | Z31: 0.68601739 | AA31: 0.15290642 | AB31: 0.032434696 | AC31: 45179.42 | AD31: 201481.25 | AE31: -25.28 | AQ31: =B31 -> 0 | AR31: =C31 -> 0 | AS31: =SUM(AV31:BH31)+BJ31+BK31 -> #DIV/0! | AT31: =SUM(AV31:BH31)+BM31+BN31 -> #DIV/0! | AU31: =AS31-AT31 -> #DIV/0! | AV31: =F31/H31*AN31 -> #DIV/0! | AW31: =G31/H31*AM31 -> #DIV/0! | AX31: =BR31 -> #DIV/0! | AY31: =BQ31 -> #DIV/0! | AZ31: =BS31 -> #DIV/0! | BA31: =I31/H31*AO31 -> #DIV/0! | BB31: =BT31 -> #DIV/0! | BC31: =N31/H31/(0.9*8760) -> #DIV/0! | BD31: =BU31 -> #DIV/0! | BE31: =O31/H31/(0.9*8760) -> #DIV/0! | BF31: =BV31 -> #DIV/0! | BG31: =P31/H31 -> #DIV/0! | BH31: =BW31 -> #DIV/0! | BI31: =SUM(CI31:CL31)-CD31 -> #DIV/0! | BJ31: =(AG31+AH31)*-1*(CJ31+CK31) -> #DIV/0! | BK31: =BI31*AG31 -> #DIV/0! | BL31: =CI31+CL31-CD31 -> #DIV/0! | BM31: =(CJ31+CK31)*AH31*-1 -> #DIV/0! | BN31: =BL31*AG31 -> #DIV/0! | BP31: =R31 -> Drymill CCS Fermentation Exhaust | BQ31: =T31/V31/H31*AM31*-1 -> #DIV/0! | BR31: =U31/V31/H31*AM31 -> #DIV/0! | BS31: {=_xlfn.IFS(S31="Biomass_Corn", 1/V31/H31*AL31, S31="Biomass_Agri", 1/V31/H31*AK31, S31="Biomass_Wood", 1/V31/H31*AJ31, S31="Biomass_Herb", 1/V31/H31*AI31)} -> #DIV/0! | BT31: =W31/V31/H31*AO31 -> #DIV/0! | BU31: =AC31/V31/H31/(0.9*8760) -> #DIV/0! | BV31: =AD31/V31/H31/(0.9*8760) -> #DIV/0! | BW31: =AE31/V31/H31 -> #DIV/0! | BY31: =22/7 -> 3.1428571 | BZ31: =X31 -> 1.7588667 | CA31: 0.18289084 | CB31: 0.23037491 | CD31: =BZ31/V31/H31 -> #DIV/0! | CE31: =IF(W31=0, 0, CA31*W31/V31/H31) -> #DIV/0! | CF31: =CB31/H31 -> #DIV/0! | CG31: =IF(I31=0, 0, CA31*I31/H31) -> 0 | CI31: =(Z31+AB31)/V31/H31 -> #DIV/0! | CJ31: =(Y31+AA31)/V31/H31 -> #DIV/0! | CK31: =BY31 -> 3.1428571 | CL31: =(L31+M31)/H31 -> #DIV/0! | CN31: =CD31+CE31+CG31-SUM(CI31:CL31) -> #DIV/0!
D32: 6 | R32: {=_xlfn.XLOOKUP(D32, CP:CP, CQ:DD)} -> Drymill CCS Fermentation Exhaust | S32: Biomass_Corn | T32: 0 | U32: 0.085342825 | V32: 3.104338 | W32: 1.0133975 | X32: 1.7588667 | Y32: 0.35768767 | Z32: 0.68601739 | AA32: 0.15290642 | AB32: 0.032434696 | AC32: 45179.42 | AD32: 201481.25 | AE32: -25.28 | AQ32: =B32 -> 0 | AR32: =C32 -> 0 | AS32: =SUM(AV32:BH32)+BJ32+BK32 -> #DIV/0! | AT32: =SUM(AV32:BH32)+BM32+BN32 -> #DIV/0! | AU32: =AS32-AT32 -> #DIV/0! | AV32: =F32/H32*AN32 -> #DIV/0! | AW32: =G32/H32*AM32 -> #DIV/0! | AX32: =BR32 -> #DIV/0! | AY32: =BQ32 -> #DIV/0! | AZ32: =BS32 -> #DIV/0! | BA32: =I32/H32*AO32 -> #DIV/0! | BB32: =BT32 -> #DIV/0! | BC32: =N32/H32/(0.9*8760) -> #DIV/0! | BD32: =BU32 -> #DIV/0! | BE32: =O32/H32/(0.9*8760) -> #DIV/0! | BF32: =BV32 -> #DIV/0! | BG32: =P32/H32 -> #DIV/0! | BH32: =BW32 -> #DIV/0! | BI32: =SUM(CI32:CL32)-CD32 -> #DIV/0! | BJ32: =(AG32+AH32)*-1*(CJ32+CK32) -> #DIV/0! | BK32: =BI32*AG32 -> #DIV/0! | BL32: =CI32+CL32-CD32 -> #DIV/0! | BM32: =(CJ32+CK32)*AH32*-1 -> #DIV/0! | BN32: =BL32*AG32 -> #DIV/0! | BP32: =R32 -> Drymill CCS Fermentation Exhaust | BQ32: =T32/V32/H32*AM32*-1 -> #DIV/0! | BR32: =U32/V32/H32*AM32 -> #DIV/0! | BS32: {=_xlfn.IFS(S32="Biomass_Corn", 1/V32/H32*AL32, S32="Biomass_Agri", 1/V32/H32*AK32, S32="Biomass_Wood", 1/V32/H32*AJ32, S32="Biomass_Herb", 1/V32/H32*AI32)} -> #DIV/0! | BT32: =W32/V32/H32*AO32 -> #DIV/0! | BU32: =AC32/V32/H32/(0.9*8760) -> #DIV/0! | BV32: =AD32/V32/H32/(0.9*8760) -> #DIV/0! | BW32: =AE32/V32/H32 -> #DIV/0! | BY32: =22/7 -> 3.1428571 | BZ32: =X32 -> 1.7588667 | CA32: 0.18289084 | CB32: 0.23037491 | CD32: =BZ32/V32/H32 -> #DIV/0! | CE32: =IF(W32=0, 0, CA32*W32/V32/H32) -> #DIV/0! | CF32: =CB32/H32 -> #DIV/0! | CG32: =IF(I32=0, 0, CA32*I32/H32) -> 0 | CI32: =(Z32+AB32)/V32/H32 -> #DIV/0! | CJ32: =(Y32+AA32)/V32/H32 -> #DIV/0! | CK32: =BY32 -> 3.1428571 | CL32: =(L32+M32)/H32 -> #DIV/0! | CN32: =CD32+CE32+CG32-SUM(CI32:CL32) -> #DIV/0!
D33: 6 | R33: {=_xlfn.XLOOKUP(D33, CP:CP, CQ:DD)} -> Drymill CCS Fermentation Exhaust | S33: Biomass_Corn | T33: 0 | U33: 0.085342825 | V33: 3.104338 | W33: 1.0133975 | X33: 1.7588667 | Y33: 0.35768767 | Z33: 0.68601739 | AA33: 0.15290642 | AB33: 0.032434696 | AC33: 45179.42 | AD33: 201481.25 | AE33: -25.28 | AQ33: =B33 -> 0 | AR33: =C33 -> 0 | AS33: =SUM(AV33:BH33)+BJ33+BK33 -> #DIV/0! | AT33: =SUM(AV33:BH33)+BM33+BN33 -> #DIV/0! | AU33: =AS33-AT33 -> #DIV/0! | AV33: =F33/H33*AN33 -> #DIV/0! | AW33: =G33/H33*AM33 -> #DIV/0! | AX33: =BR33 -> #DIV/0! | AY33: =BQ33 -> #DIV/0! | AZ33: =BS33 -> #DIV/0! | BA33: =I33/H33*AO33 -> #DIV/0! | BB33: =BT33 -> #DIV/0! | BC33: =N33/H33/(0.9*8760) -> #DIV/0! | BD33: =BU33 -> #DIV/0! | BE33: =O33/H33/(0.9*8760) -> #DIV/0! | BF33: =BV33 -> #DIV/0! | BG33: =P33/H33 -> #DIV/0! | BH33: =BW33 -> #DIV/0! | BI33: =SUM(CI33:CL33)-CD33 -> #DIV/0! | BJ33: =(AG33+AH33)*-1*(CJ33+CK33) -> #DIV/0! | BK33: =BI33*AG33 -> #DIV/0! | BL33: =CI33+CL33-CD33 -> #DIV/0! | BM33: =(CJ33+CK33)*AH33*-1 -> #DIV/0! | BN33: =BL33*AG33 -> #DIV/0! | BP33: =R33 -> Drymill CCS Fermentation Exhaust | BQ33: =T33/V33/H33*AM33*-1 -> #DIV/0! | BR33: =U33/V33/H33*AM33 -> #DIV/0! | BS33: {=_xlfn.IFS(S33="Biomass_Corn", 1/V33/H33*AL33, S33="Biomass_Agri", 1/V33/H33*AK33, S33="Biomass_Wood", 1/V33/H33*AJ33, S33="Biomass_Herb", 1/V33/H33*AI33)} -> #DIV/0! | BT33: =W33/V33/H33*AO33 -> #DIV/0! | BU33: =AC33/V33/H33/(0.9*8760) -> #DIV/0! | BV33: =AD33/V33/H33/(0.9*8760) -> #DIV/0! | BW33: =AE33/V33/H33 -> #DIV/0! | BY33: =22/7 -> 3.1428571 | BZ33: =X33 -> 1.7588667 | CA33: 0.18289084 | CB33: 0.23037491 | CD33: =BZ33/V33/H33 -> #DIV/0! | CE33: =IF(W33=0, 0, CA33*W33/V33/H33) -> #DIV/0! | CF33: =CB33/H33 -> #DIV/0! | CG33: =IF(I33=0, 0, CA33*I33/H33) -> 0 | CI33: =(Z33+AB33)/V33/H33 -> #DIV/0! | CJ33: =(Y33+AA33)/V33/H33 -> #DIV/0! | CK33: =BY33 -> 3.1428571 | CL33: =(L33+M33)/H33 -> #DIV/0! | CN33: =CD33+CE33+CG33-SUM(CI33:CL33) -> #DIV/0!
... D66: 6 | R66: {=_xlfn.XLOOKUP(D66, CP:CP, CQ:DD)} -> Drymill CCS Fermentation Exhaust | S66: Biomass_Corn | T66: 0 | U66: 0.085342825 | V66: 3.104338 | W66: 1.0133975 | X66: 1.7588667 | Y66: 0.35768767 | Z66: 0.68601739 | AA66: 0.15290642 | AB66: 0.032434696 | AC66: 45179.42 | AD66: 201481.25 | AE66: -25.28 | AQ66: =B66 -> 0 | AR66: =C66 -> 0 | AS66: =SUM(AV66:BH66)+BJ66+BK66 -> #DIV/0! | AT66: =SUM(AV66:BH66)+BM66+BN66 -> #DIV/0! | AU66: =AS66-AT66 -> #DIV/0! | AV66: =F66/H66*AN66 -> #DIV/0! | AW66: =G66/H66*AM66 -> #DIV/0! | AX66: =BR66 -> #DIV/0! | AY66: =BQ66 -> #DIV/0! | AZ66: =BS66 -> #DIV/0! | BA66: =I66/H66*AO66 -> #DIV/0! | BB66: =BT66 -> #DIV/0! | BC66: =N66/H66/(0.9*8760) -> #DIV/0! | BD66: =BU66 -> #DIV/0! | BE66: =O66/H66/(0.9*8760) -> #DIV/0! | BF66: =BV66 -> #DIV/0! | BG66: =P66/H66 -> #DIV/0! | BH66: =BW66 -> #DIV/0! | BI66: =SUM(CI66:CL66)-CD66 -> #DIV/0! | BJ66: =(AG66+AH66)*-1*(CJ66+CK66) -> #DIV/0! | BK66: =BI66*AG66 -> #DIV/0! | BL66: =CI66+CL66-CD66 -> #DIV/0! | BM66: =(CJ66+CK66)*AH66*-1 -> #DIV/0! | BN66: =BL66*AG66 -> #DIV/0! | BP66: =R66 -> Drymill CCS Fermentation Exhaust | BQ66: =T66/V66/H66*AM66*-1 -> #DIV/0! | BR66: =U66/V66/H66*AM66 -> #DIV/0! | BS66: {=_xlfn.IFS(S66="Biomass_Corn", 1/V66/H66*AL66, S66="Biomass_Agri", 1/V66/H66*AK66, S66="Biomass_Wood", 1/V66/H66*AJ66, S66="Biomass_Herb", 1/V66/H66*AI66)} -> #DIV/0! | BT66: =W66/V66/H66*AO66 -> #DIV/0! | BU66: =AC66/V66/H66/(0.9*8760) -> #DIV/0! | BV66: =AD66/V66/H66/(0.9*8760) -> #DIV/0! | BW66: =AE66/V66/H66 -> #DIV/0! | BY66: =22/7 -> 3.1428571 | BZ66: =X66 -> 1.7588667 | CA66: 0.18289084 | CB66: 0.23037491 | CD66: =BZ66/V66/H66 -> #DIV/0! | CE66: =IF(W66=0, 0, CA66*W66/V66/H66) -> #DIV/0! | CF66: =CB66/H66 -> #DIV/0! | CG66: =IF(I66=0, 0, CA66*I66/H66) -> 0 | CI66: =(Z66+AB66)/V66/H66 -> #DIV/0! | CJ66: =(Y66+AA66)/V66/H66 -> #DIV/0! | CK66: =BY66 -> 3.1428571 | CL66: =(L66+M66)/H66 -> #DIV/0! | CN66: =CD66+CE66+CG66-SUM(CI66:CL66) -> #DIV/0!

Sheet lc_summary
A1: Levelized cost for Bioethylene Production - $/GJ-ethylene - chemicals CO2 sequestration
A2: id_LC | B2: h2_consumption | C2: elec_consumption | D2: elec_consumption - ethanol prod. | E2: elec_production - ethanol prod. | F2: biomass_consumption - ethanol prod. | G2: natgas_consumption | H2: natgas_consumption - ethanol prod. | I2: investment_cost | J2: investment_cost - ethanol prod. | K2: fixed_om_cost | L2: fixed_om_cost - ethanol prod. | M2: variable_om_cost | N2: variable_om_cost - ethanol prod. | O2: modified capture cost | P2: modified emissions cost | Q2: LCOE ($/t-ethylene)
A3: =lc_detailed!AQ4 -> CA_B-NGin | B3: =lc_detailed!AV4 -> 0 | C3: =lc_detailed!AW4 -> 8.3994214 | D3: =lc_detailed!AX4 -> 14.253856 | E3: =lc_detailed!AY4 -> 0 | F3: =lc_detailed!AZ4 -> 731.56501 | G3: =lc_detailed!BA4 -> 22.532117 | H3: =lc_detailed!BB4 -> 63.464285 | I3: =lc_detailed!BC4 -> 11.843234 | ... N3: =lc_detailed!BH4 -> -115.58727 | O3: =lc_detailed!BJ4 -> -553.23517 | P3: =lc_detailed!BK4 -> 123.43785 | Q3: =lc_detailed!AS4 -> 462.67035
A4: =lc_detailed!AQ5 -> NW_B-NGin | B4: =lc_detailed!AV5 -> 0 | C4: =lc_detailed!AW5 -> 6.1619046 | D4: =lc_detailed!AX5 -> 10.45678 | E4: =lc_detailed!AY5 -> 0 | F4: =lc_detailed!AZ5 -> 731.56501 | G4: =lc_detailed!BA5 -> 22.532117 | H4: =lc_detailed!BB5 -> 63.464285 | I4: =lc_detailed!BC5 -> 11.843234 | ... N4: =lc_detailed!BH5 -> -115.58727 | O4: =lc_detailed!BJ5 -> -548.30548 | P4: =lc_detailed!BK5 -> 123.43785 | Q4: =lc_detailed!AS5 -> 461.56545
A5: =lc_detailed!AQ6 -> SW_B-NGin | B5: =lc_detailed!AV6 -> 0 | C5: =lc_detailed!AW6 -> 6.434273 | D5: =lc_detailed!AX6 -> 10.91899 | E5: =lc_detailed!AY6 -> 0 | F5: =lc_detailed!AZ6 -> 731.56501 | G5: =lc_detailed!BA6 -> 22.532117 | H5: =lc_detailed!BB6 -> 63.464285 | I5: =lc_detailed!BC6 -> 11.843234 | ... N5: =lc_detailed!BH6 -> -115.58727 | O5: =lc_detailed!BJ6 -> -498.68563 | P5: =lc_detailed!BK6 -> 123.43785 | Q5: =lc_detailed!AS6 -> 511.91987
A6: =lc_detailed!AQ7 -> TX_B-NGin | B6: =lc_detailed!AV7 -> 0 | C6: =lc_detailed!AW7 -> 4.6437793 | D6: =lc_detailed!AX7 -> 7.8805144 | E6: =lc_detailed!AY7 -> 0 | F6: =lc_detailed!AZ7 -> 731.56501 | G6: =lc_detailed!BA7 -> 21.922436 | H6: =lc_detailed!BB7 -> 61.747049 | I6: =lc_detailed!BC7 -> 11.843234 | ... N6: =lc_detailed!BH7 -> -115.58727 | O6: =lc_detailed!BJ7 -> -471.85068 | P6: =lc_detailed!BK7 -> 123.43785 | Q6: =lc_detailed!AS7 -> 531.59893
A7: =lc_detailed!AQ8 -> NCEN_B-NGin | B7: =lc_detailed!AV8 -> 0 | C7: =lc_detailed!AW8 -> 7.0709977 | D7: =lc_detailed!AX8 -> 11.999515 | E7: =lc_detailed!AY8 -> 0 | F7: =lc_detailed!AZ8 -> 731.56501 | G7: =lc_detailed!BA8 -> 22.080218 | H7: =lc_detailed!BB8 -> 62.191461 | I7: =lc_detailed!BC8 -> 11.843234 | ... N7: =lc_detailed!BH8 -> -115.58727 | O7: =lc_detailed!BJ8 -> -361.08484 | P7: =lc_detailed!BK8 -> 123.43785 | Q7: =lc_detailed!AS8 -> 649.51319
A8: =lc_detailed!AQ9 -> CEN_B-NGin | B8: =lc_detailed!AV9 -> 0 | C8: =lc_detailed!AW9 -> 5.7823499 | D8: =lc_detailed!AX9 -> 9.8126739 | E8: =lc_detailed!AY9 -> 0 | F8: =lc_detailed!AZ9 -> 731.56501 | G8: =lc_detailed!BA9 -> 22.080218 | H8: =lc_detailed!BB9 -> 62.191461 | I8: =lc_detailed!BC9 -> 11.843234 | ... N8: =lc_detailed!BH9 -> -115.58727 | O8: =lc_detailed!BJ9 -> -415.94739 | P8: =lc_detailed!BK9 -> 123.43785 | Q8: =lc_detailed!AS9 -> 591.17515
A9: =lc_detailed!AQ10 -> SE_B-NGin | B9: =lc_detailed!AV10 -> 0 | C9: =lc_detailed!AW10 -> 8.7708849 | D9: =lc_detailed!AX10 -> 14.884231 | E9: =lc_detailed!AY10 -> 0 | F9: =lc_detailed!AZ10 -> 731.56501 | G9: =lc_detailed!BA10 -> 22.080218 | H9: =lc_detailed!BB10 -> 62.191461 | I9: =lc_detailed!BC10 -> 11.843234 | ... N9: =lc_detailed!BH10 -> -115.58727 | O9: =lc_detailed!BJ10 -> -327.75032 | P9: =lc_detailed!BK10 -> 123.43785 | Q9: =lc_detailed!AS10 -> 687.43231
A10: =lc_detailed!AQ11 -> MIDAT_B-NGin | B10: =lc_detailed!AV11 -> 0 | C10: =lc_detailed!AW11 -> 9.0528246 | D10: =lc_detailed!AX11 -> 15.362684 | E10: =lc_detailed!AY11 -> 0 | F10: =lc_detailed!AZ11 -> 731.56501 | G10: =lc_detailed!BA11 -> 22.080218 | H10: =lc_detailed!BB11 -> 62.191461 | I10: =lc_detailed!BC11 -> 11.843234 | ... N10: =lc_detailed!BH11 -> -115.58727 | O10: =lc_detailed!BJ11 -> -315.62649 | P10: =lc_detailed!BK11 -> 123.43785 | Q10: =lc_detailed!AS11 -> 700.31654
A11: =lc_detailed!AQ12 -> NE_B-NGin | B11: =lc_detailed!AV12 -> 0 | C11: =lc_detailed!AW12 -> 10.902008 | D11: =lc_detailed!AX12 -> 18.500757 | E11: =lc_detailed!AY12 -> 0 | F11: =lc_detailed!AZ12 -> 731.56501 | G11: =lc_detailed!BA12 -> 22.080218 | H11: =lc_detailed!BB12 -> 62.191461 | I11: =lc_detailed!BC12 -> 11.843234 | ... N11: =lc_detailed!BH12 -> -115.58727 | O11: =lc_detailed!BJ12 -> -264.28415 | P11: =lc_detailed!BK12 -> 123.43785 | Q11: =lc_detailed!AS12 -> 756.64613
A12: =lc_detailed!AQ13 -> CA_B-H2in | B12: =lc_detailed!AV13 -> 48.965151 | C12: =lc_detailed!AW13 -> 8.3994214 | D12: =lc_detailed!AX13 -> 14.253856 | E12: =lc_detailed!AY13 -> 0 | F12: =lc_detailed!AZ13 -> 731.56501 | G12: =lc_detailed!BA13 -> 0 | H12: =lc_detailed!BB13 -> 63.464285 | I12: =lc_detailed!BC13 -> 11.843234 | ... N12: =lc_detailed!BH13 -> -115.58727 | O12: =lc_detailed!BJ13 -> -553.23517 | P12: =lc_detailed!BK13 -> 91.10108 | Q12: =lc_detailed!AS13 -> 456.76661
A13: =lc_detailed!AQ14 -> NW_B-H2in | B13: =lc_detailed!AV14 -> 45.858615 | C13: =lc_detailed!AW14 -> 6.1619046 | D13: =lc_detailed!AX14 -> 10.45678 | E13: =lc_detailed!AY14 -> 0 | F13: =lc_detailed!AZ14 -> 731.56501 | G13: =lc_detailed!BA14 -> 0 | H13: =lc_detailed!BB14 -> 63.464285 | I13: =lc_detailed!BC14 -> 11.843234 | ... N13: =lc_detailed!BH14 -> -115.58727 | O13: =lc_detailed!BJ14 -> -548.30548 | P13: =lc_detailed!BK14 -> 91.10108 | Q13: =lc_detailed!AS14 -> 452.55518
A14: =lc_detailed!AQ15 -> SW_B-H2in | B14: =lc_detailed!AV15 -> 43.445561 | C14: =lc_detailed!AW15 -> 6.434273 | D14: =lc_detailed!AX15 -> 10.91899 | E14: =lc_detailed!AY15 -> 0 | F14: =lc_detailed!AZ15 -> 731.56501 | G14: =lc_detailed!BA15 -> 0 | H14: =lc_detailed!BB15 -> 63.464285 | I14: =lc_detailed!BC15 -> 11.843234 | ... N14: =lc_detailed!BH15 -> -115.58727 | O14: =lc_detailed!BJ15 -> -498.68563 | P14: =lc_detailed!BK15 -> 91.10108 | Q14: =lc_detailed!AS15 -> 500.49654
... A63: =lc_detailed!AQ64 -> 0 | B63: =lc_detailed!AV64 -> #DIV/0! | C63: =lc_detailed!AW64 -> #DIV/0! | D63: =lc_detailed!AX64 -> #DIV/0! | E63: =lc_detailed!AY64 -> #DIV/0! | F63: =lc_detailed!AZ64 -> #DIV/0! | G63: =lc_detailed!BA64 -> #DIV/0! | H63: =lc_detailed!BB64 -> #DIV/0! | I63: =lc_detailed!BC64 -> #DIV/0! | ... N63: =lc_detailed!BH64 -> #DIV/0! | O63: =lc_detailed!BJ64 -> #DIV/0! | P63: =lc_detailed!BK64 -> #DIV/0! | Q63: =lc_detailed!AS64 -> #DIV/0!
