Workbook

Sheet lc_detailed
B1: Ethanol Upgrade Asset Parameters (normalized by MWh ethanol) | D1: Ethanol feedstock asset | Q1: Ethanol Production Asset Parameters (normalized by commodity feedstock) | AD1: Duals | AZ1: LCOE for assets with ethane capacity ($/t-ethylene) | BB1: SEQ - CI | BC1: SEQ - CREDIT | BE1: NO SEQ - CI | BF1: NO SEQ - CREDIT | BU1: CHEM SEQUESTRATION - CARBON INTENSITY | BX1: CHEM SEQUESTRATION - CREDIT | CA1: NO CHEM SEQUESTRATION - CARBON INTENSITY | CD1: NO CHEM SEQUESTRATION - CREDIT | CH1: Ethanol Production LCOE parameters ($/t-ethylene) | CQ1: Carbon Content | CV1: Carbon Inputs - Ethanol Production | CX1: Carbon Inputs - Ethanol Dehydration | DB1: Carbon Outputs - Ethanol Production | DD1: Carbon Outputs - Ethanol Dehydration | DH1: Sanity Checks | DJ1: Asset Parameters (normalized by commodity feedstock)
B2: id | C2: commodity | D2: production_asset | E2: id_name | F2: h2_consumption (MWh/MWh-ethanol) | G2: elec_consumption (MWh/MWh-ethanol) | H2: ethylene_production (t-ethylene/MWh-ethanol) | I2: natgas_consumption (MWh/MWh-ethanol) | J2: capture_rate (t-CO2/MWh-ethanol) | K2: emission_rate (t-CO2/MWh-ethanol) | L2: calculated_emission_rate (t-CO2/MWh-ethanol) | M2: investment_cost ($/yr per MW ethanol) | N2: fixed_om_cost ($/yr per MW ethanol) | O2: variable_om_cost ($/MWh-ethanol) | Q2: id_bioethanol | R2: commodity_bioethanol | S2: elec_production (MWh/t-bio) | T2: elec_consumption (MWh/t-bio) | U2: ethanol_production (MWh-ethanol/t-bio) | V2: natgas_consumption (MWh/t-bio) | W2: co2_biomass_content (t-CO2/t-bio) | X2: capture_rate (t-CO2/t-bio) | Y2: emission_rate (t-CO2/t-bio) | Z2: investment_cost ($/yr per t-bio/hr) | AA2: fixed_om_cost ($/yr per t-bio/hr) | AB2: variable_om_cost ($/t-bio) | AD2: co2_sink ($/t) | AE2: co2_captured ($/t) | AF2: bioherb_supply ($/t) | AG2: biowood_supply ($/t) | AH2: bioagri_supply ($/t) | AI2: biocorn_supply ($/t) | AJ2: ethanol_balance ($/MWh) | AK2: ethanol_demand ($/MWh) | AL2: elec_demand ($/MWh) | AM2: h2_balance ($/MWh) | AN2: h2_demand ($/MWh) | AO2: gasoline_balance ($/MWh) | AP2: gasoline_demand ($/MWh) | AQ2: diesel_balance ($/MWh) | AR2: diesel_demand ($/MWh) | AS2: jetfuel_balance ($/MWh) | AT2: jetfuel_demand ($/MWh) | AU2: ng_balance ($/MWh) | AV2: ng_demand ($/MWh) | AW2: ethylene_balance ($/t) | AX2: ethylene_demand ($/t) | AZ2: id_LC | BA2: commodity_LC | BB2: LCOE ($/t-ethylene) | BC2: LCOE ($/t-ethylene) | BD2: Diff. Between Methods | BE2: LCOE ($/t-ethylene) | BF2: LCOE ($/t-ethylene) | BG2: Diff. Between Methods | BH2: h2_consumption | BI2: elec_consumption | BJ2: elec_consumption - ethanol | BK2: elec_production - ethanol | BL2: biomass_consumption - ethanol | BM2: natgas_consumption | BN2: natgas_consumption - ethanol | BO2: investment_cost | BP2: investment_cost - ethanol | BQ2: fixed_om_cost | BR2: fixed_om_cost - ethanol | BS2: variable_om_cost | BT2: variable_om_cost - ethanol | BU2: CI | BV2: modified capture cost | BW2: modified emissions cost | BX2: CI | BY2: modified capture cost | BZ2: modified emissions cost | CA2: CI | CB2: modified capture cost | CC2: modified emissions cost | CD2: CI | CE2: modified capture cost | CF2: modified emissions cost | CH2: id_LC_ethanol | CI2: elec_production | CJ2: elec_consumption | CK2: biomass_consumption | CL2: natgas_consumption | CM2: investment_cost | CN2: fixed_om_cost | CO2: variable_om_cost | CQ2: Ethylene (t-CO2/t-ethylene) | CR2: Biomass CO2 content (t-CO2/t-bio) | CS2: NG (t-CO2/MWh-NG) | CT2: Ethanol (t-CO2/MWh-ethanol) | CV2: Biomass (t-CO2/t-ethylene) | CW2: NG (t-CO2//t-ethylene) | CX2: Ethanol (t-CO2//t-ethylene) | CY2: NG (t-CO2//t-ethylene) | CZ2: Total input (t-CO2/t-ethylene) | DB2: Emissions (t-CO2/t-ethylene) | DC2: Captured (t-CO2/t-ethylene) | DD2: Ethylene (t-CO2/t-ethylene) | DE2: Emissions (t-CO2/t-ethylene) | DF2: Total Output (t-CO2/t-ethylene) | DH2: CARBON INPUT - OUTPUT | DJ2: ethanol_production_asset | DK2: id_ethanol_prod_ref | DL2: commodity_ethanol_prod_ref | DM2: elec_production (MWh/t-bio) | DN2: elec_consumption (MWh/t-bio) | DO2: ethanol_production (MWh-ethanol/t-bio) | DP2: natgas_consumption (MWh/t-bio) | DQ2: co2_biomass_content (t-CO2/t-bio) | DR2: capture_rate (t-CO2/t-bio) | DS2: emission_rate (t-CO2/t-bio) | DT2: investment_cost ($/yr per t-bio/hr) | DU2: fixed_om_cost ($/yr per t-bio/hr) | DV2: variable_om_cost ($/t-bio)
B3: NCEN_Ethanol_Dehydration_NGfuel | C3: Ethanol | D3: 5 | E3: =Q3 -> Drymill CCS 90 | F3: 0 | G3: 0.016231455 | H3: 0.070449025 | I3: 0.11456845 | J3: 0 | K3: 1.6218958 | L3: =(CY3+(CX3-DD3))*H3 -> 1.7128149 | M3: 6577.9713 | N3: 6324.1329 | O3: 0.11130946 | Q3: {=_xlfn.XLOOKUP(D3, DJ:DJ, DK:DV)} -> Drymill CCS 90 | R3: Biomass_Corn | S3: 0 | T3: 0.4049 | U3: 3.2587 | V3: 0.7507 | W3: 1.65 | X3: 0.66452746 | Y3: 0.07384 | Z3: 36112.15 | AA3: 173741.51 | AB3: 80.28 | AD3: 73.71884 | AE3: -6.097314 | AF3: 61.343403 | AG3: 33.004971 | AH3: 42.19561 | AI3: 155 | AJ3: 51.423576 | AL3: 22.90669 | AM3: 13.197062 | AO3: -129.52898 | AP3: -129.52898 | AU3: 14.953878 | AV3: 0 | AW3: 822.26752 | AX3: 822.26752 | AZ3: =B3 -> NCEN_Ethanol_Dehydration_NGfuel | BA3: =C3 -> Ethanol | BB3: =SUM(BH3:BT3)+BV3+BW3 -> 857.29655 | BC3: =SUM(BH3:BT3)+BY3+BZ3 -> 857.29655 | BD3: =BB3-BC3 -> 0 | BE3: =SUM(BH3:BT3)+CB3+CC3 -> 1088.7737 | BF3: =SUM(BH3:BT3)+CE3+CF3 -> 1088.7737 | BG3: =BE3-BF3 -> 0 | BH3: =F3/H3*AM3 -> 0 | BI3: =G3/H3*AL3 -> 5.2777014 | BJ3: =CJ3 -> 40.400873 | BK3: =CI3 -> 0 | BL3: =CK3 -> 675.16875 | BM3: =I3/H3*AU3 -> 24.318897 | BN3: =CL3 -> 48.899102 | BO3: =M3/H3/(0.9*8760) -> 11.843236 | BP3: =CM3 -> 19.952043 | BQ3: =N3/H3/(0.9*8760) -> 11.386215 | BR3: =CN3 -> 95.992568 | BS3: =O3/H3 -> 1.58 | BT3: =CO3 -> 349.69385 | BU3: =CZ3-DF3-DD3 -> -3.14 | BV3: =(AD3+AE3)*-1*DC3 -> -195.73953 | BW3: =BU3*AD3 -> -231.47716 | BX3: =CZ3-DF3-DC3-DD3 -> -6.0346334 | BY3: =DC3*AE3*-1 -> 17.649489 | BZ3: =BX3*AD3 -> -444.86617 | CA3: =CZ3-DF3 -> 0 | CB3: =(AD3+AE3)*-1*DC3 -> -195.73953 | CC3: =CA3*AD3 -> 0 | CD3: =CZ3-DF3-DC3 -> -2.8946334 | CE3: =DC3*AE3*-1 -> 17.649489 | CF3: =CD3*AD3 -> -213.38902 | CH3: =Q3 -> Drymill CCS 90 | CI3: =S3/U3/H3*AL3*-1 -> 0 | CJ3: =T3/U3/H3*AL3 -> 40.400873 | CK3: {=_xlfn.IFS(R3="Biomass_Corn", 1/U3/H3*AI3, R3="Biomass_Agri", 1/U3/H3*AH3, R3="Biomass_Wood", 1/U3/H3*AG3, R3="Biomass_Herb", 1/U3/H3*AF3)} -> 675.16875 | CL3: =V3/U3/H3*AU3 -> 48.899102 | CM3: =Z3/U3/H3/(0.9*8760) -> 19.952043 | CN3: =AA3/U3/H3/(0.9*8760) -> 95.992568 | CO3: =AB3/U3/H3 -> 349.69385 | CQ3: 3.14 | CR3: =W3 -> 1.65 | CS3: 0.18104824 | CT3: =(CV3+CW3-DB3-DC3)*H3 -> 0.35376226 | CV3: =CR3/U3/H3 -> 7.1872802 | CW3: =IF(V3=0, 0, CS3/V3/U3/H3) -> 1.0505301 | CX3: =CT3/H3 -> 5.0215353 | CY3: =IF(I3=0, 0, CS3/I3/H3) -> 22.431291 | CZ3: =CV3+CW3+CY3 -> 30.669102 | DB3: =Y3/U3/H3 -> 0.32164168 | DC3: =X3/U3/H3 -> 2.8946334 | DD3: =CQ3 -> 3.14 | DE3: =L3/H3 -> 24.312827 | DF3: =SUM(DB3:DE3) -> 30.669102 | DH3: =CZ3-DF3 -> 0 | DJ3: 1 | DK3: SE_DryMill_Existing_Non_CCS | DL3: Biomass_Corn | DM3: 0 | DN3: 0.06 | DO3: 3.26 | DP3: 0.75 | DQ3: 1.65 | DR3: 0 | DS3: 1.034529 | DT3: 0 | DU3: 154043.63 | DV3: 79.65
B4: NCEN_Ethanol_Dehydration_H2fuel | C4: Ethanol | D4: 5 | E4: =Q4 -> Drymill CCS 90 | F4: 0.11233878 | G4: 0.016231455 | H4: 0.070449025 | I4: 0 | J4: 0 | K4: 0.041633218 | L4: =(CY4+(CX4-DD4))*H4 -> 0.13255233 | M4: 6577.9713 | N4: 6324.1329 | O4: 0.11130946 | Q4: {=_xlfn.XLOOKUP(D4, DJ:DJ, DK:DV)} -> Drymill CCS 90 | R4: Biomass_Corn | S4: 0 | T4: 0.4049 | U4: 3.2587 | V4: 0.7507 | W4: 1.65 | X4: 0.66452746 | Y4: 0.07384 | Z4: 36112.15 | AA4: 173741.51 | AB4: 80.28 | AD4: 73.71884 | AE4: -6.097314 | AF4: 61.343403 | AG4: 33.004971 | AH4: 42.19561 | AI4: 155 | AJ4: 51.423576 | AL4: 22.90669 | AM4: 13.197062 | AO4: -129.52898 | AP4: -129.52898 | AU4: 14.953878 | AV4: 0 | AW4: 822.26752 | AX4: 822.26752 | AZ4: =B4 -> NCEN_Ethanol_Dehydration_H2fuel | BA4: =C4 -> Ethanol | BB4: =SUM(BH4:BT4)+BV4+BW4 -> 854.02183 | BC4: =SUM(BH4:BT4)+BY4+BZ4 -> 854.02183 | BD4: =BB4-BC4 -> 0 | BE4: =SUM(BH4:BT4)+CB4+CC4 -> 1085.499 | BF4: =SUM(BH4:BT4)+CE4+CF4 -> 1085.499 | BG4: =BE4-BF4 -> 0 | BH4: =F4/H4*AM4 -> 21.044179 | BI4: =G4/H4*AL4 -> 5.2777014 | BJ4: =CJ4 -> 40.400873 | BK4: =CI4 -> 0 | BL4: =CK4 -> 675.16875 | BM4: =I4/H4*AU4 -> 0 | BN4: =CL4 -> 48.899102 | BO4: =M4/H4/(0.9*8760) -> 11.843236 | BP4: =CM4 -> 19.952043 | BQ4: =N4/H4/(0.9*8760) -> 11.386215 | BR4: =CN4 -> 95.992568 | BS4: =O4/H4 -> 1.58 | BT4: =CO4 -> 349.69385 | BU4: =CZ4-DF4-DD4 -> -3.14 | BV4: =(AD4+AE4)*-1*DC4 -> -195.73953 | BW4: =BU4*AD4 -> -231.47716 | BX4: =CZ4-DF4-DC4-DD4 -> -6.0346334 | BY4: =DC4*AE4*-1 -> 17.649489 | BZ4: =BX4*AD4 -> -444.86617 | CA4: =CZ4-DF4 -> 0 | CB4: =(AD4+AE4)*-1*DC4 -> -195.73953 | CC4: =CA4*AD4 -> 0 | CD4: =CZ4-DF4-DC4 -> -2.8946334 | CE4: =DC4*AE4*-1 -> 17.649489 | CF4: =CD4*AD4 -> -213.38902 | CH4: =Q4 -> Drymill CCS 90 | CI4: =S4/U4/H4*AL4*-1 -> 0 | CJ4: =T4/U4/H4*AL4 -> 40.400873 | CK4: {=_xlfn.IFS(R4="Biomass_Corn", 1/U4/H4*AI4, R4="Biomass_Agri", 1/U4/H4*AH4, R4="Biomass_Wood", 1/U4/H4*AG4, R4="Biomass_Herb", 1/U4/H4*AF4)} -> 675.16875 | CL4: =V4/U4/H4*AU4 -> 48.899102 | CM4: =Z4/U4/H4/(0.9*8760) -> 19.952043 | CN4: =AA4/U4/H4/(0.9*8760) -> 95.992568 | CO4: =AB4/U4/H4 -> 349.69385 | CQ4: 3.14 | CR4: =W4 -> 1.65 | CS4: 0.18104824 | CT4: =(CV4+CW4-DB4-DC4)*H4 -> 0.35376226 | CV4: =CR4/U4/H4 -> 7.1872802 | CW4: =IF(V4=0, 0, CS4/V4/U4/H4) -> 1.0505301 | CX4: =CT4/H4 -> 5.0215353 | CY4: =IF(I4=0, 0, CS4/I4/H4) -> 0 | CZ4: =CV4+CW4+CY4 -> 8.2378103 | DB4: =Y4/U4/H4 -> 0.32164168 | DC4: =X4/U4/H4 -> 2.8946334 | DD4: =CQ4 -> 3.14 | DE4: =L4/H4 -> 1.8815353 | DF4: =SUM(DB4:DE4) -> 8.2378103 | DH4: =CZ4-DF4 -> 0 | DJ4: 2 | DK4: SE_Biochemical_Non_CCS | DL4: Biomass_Agri | DM4: 0.1227 | DN4: 0 | DO4: 1.5509 | DP4: 0 | DQ4: 1.32 | DR4: 0 | DS4: 0.96259975 | DT4: 656536.27 | DU4: 194987.35 | DV4: 55.68
B5: CEN_Ethanol_Dehydration_NGfuel | C5: Ethanol | D5: 5 | E5: =Q5 -> Drymill CCS 90 | F5: 0 | G5: 0.016231455 | H5: 0.070449025 | I5: 0.11456845 | J5: 0 | K5: 1.6218958 | L5: =(CY5+(CX5-DD5))*H5 -> 1.7128149 | M5: 6577.9713 | N5: 6324.1329 | O5: 0.11130946 | Q5: {=_xlfn.XLOOKUP(D5, DJ:DJ, DK:DV)} -> Drymill CCS 90 | R5: Biomass_Corn | S5: 0 | T5: 0.4049 | U5: 3.2587 | V5: 0.7507 | W5: 1.65 | X5: 0.66452746 | Y5: 0.07384 | Z5: 36112.15 | AA5: 173741.51 | AB5: 80.28 | AD5: 73.71884 | AE5: -6.199254 | AF5: 65.59151 | AG5: 31.821489 | AH5: 37.986239 | AI5: 155 | AJ5: 51.417555 | AL5: 22.465142 | AM5: 13.285634 | AO5: -129.68145 | AP5: -129.68145 | AU5: 15.046749 | AV5: 0 | AW5: 822.26752 | AX5: 822.26752 | AZ5: =B5 -> CEN_Ethanol_Dehydration_NGfuel | BA5: =C5 -> Ethanol | BB5: =SUM(BH5:BT5)+BV5+BW5 -> 857.16585 | BC5: =SUM(BH5:BT5)+BY5+BZ5 -> 857.16585 | BD5: =BB5-BC5 -> 0 | BE5: =SUM(BH5:BT5)+CB5+CC5 -> 1088.643 | BF5: =SUM(BH5:BT5)+CE5+CF5 -> 1088.643 | BG5: =BE5-BF5 -> 0 | BH5: =F5/H5*AM5 -> 0 | BI5: =G5/H5*AL5 -> 5.1759687 | BJ5: =CJ5 -> 39.622108 | BK5: =CI5 -> 0 | BL5: =CK5 -> 675.16875 | BM5: =I5/H5*AU5 -> 24.46993 | BN5: =CL5 -> 49.20279 | BO5: =M5/H5/(0.9*8760) -> 11.843236 | BP5: =CM5 -> 19.952043 | BQ5: =N5/H5/(0.9*8760) -> 11.386215 | BR5: =CN5 -> 95.992568 | BS5: =O5/H5 -> 1.58 | BT5: =CO5 -> 349.69385 | BU5: =CZ5-DF5-DD5 -> -3.14 | BV5: =(AD5+AE5)*-1*DC5 -> -195.44445 | BW5: =BU5*AD5 -> -231.47716 | BX5: =CZ5-DF5-DC5-DD5 -> -6.0346334 | BY5: =DC5*AE5*-1 -> 17.944568 | BZ5: =BX5*AD5 -> -444.86617 | CA5: =CZ5-DF5 -> 0 | CB5: =(AD5+AE5)*-1*DC5 -> -195.44445 | CC5: =CA5*AD5 -> 0 | CD5: =CZ5-DF5-DC5 -> -2.8946334 | CE5: =DC5*AE5*-1 -> 17.944568 | CF5: =CD5*AD5 -> -213.38902 | CH5: =Q5 -> Drymill CCS 90 | CI5: =S5/U5/H5*AL5*-1 -> 0 | CJ5: =T5/U5/H5*AL5 -> 39.622108 | CK5: {=_xlfn.IFS(R5="Biomass_Corn", 1/U5/H5*AI5, R5="Biomass_Agri", 1/U5/H5*AH5, R5="Biomass_Wood", 1/U5/H5*AG5, R5="Biomass_Herb", 1/U5/H5*AF5)} -> 675.16875 | CL5: =V5/U5/H5*AU5 -> 49.20279 | CM5: =Z5/U5/H5/(0.9*8760) -> 19.952043 | CN5: =AA5/U5/H5/(0.9*8760) -> 95.992568 | CO5: =AB5/U5/H5 -> 349.69385 | CQ5: 3.14 | CR5: =W5 -> 1.65 | CS5: 0.18104824 | CT5: =(CV5+CW5-DB5-DC5)*H5 -> 0.35376226 | CV5: =CR5/U5/H5 -> 7.1872802 | CW5: =IF(V5=0, 0, CS5/V5/U5/H5) -> 1.0505301 | CX5: =CT5/H5 -> 5.0215353 | CY5: =IF(I5=0, 0, CS5/I5/H5) -> 22.431291 | CZ5: =CV5+CW5+CY5 -> 30.669102 | DB5: =Y5/U5/H5 -> 0.32164168 | DC5: =X5/U5/H5 -> 2.8946334 | DD5: =CQ5 -> 3.14 | DE5: =L5/H5 -> 24.312827 | DF5: =SUM(DB5:DE5) -> 30.669102 | DH5: =CZ5-DF5 -> 0 | DJ5: 3 | DK5: SE_Biochemical_CCS_20 | DL5: Biomass_Agri | DM5: 0.1227 | DN5: 0 | DO5: 1.5509 | DP5: 0 | DQ5: 1.32 | DR5: 0.19 | DS5: 0.77259975 | DT5: 658128.84 | DU5: 195838.97 | DV5: 55.71
B6: CEN_Ethanol_Dehydration_H2fuel | C6: Ethanol | D6: 5 | E6: =Q6 -> Drymill CCS 90 | F6: 0.11233878 | G6: 0.016231455 | H6: 0.070449025 | I6: 0 | J6: 0 | K6: 0.041633218 | L6: =(CY6+(CX6-DD6))*H6 -> 0.13255233 | M6: 6577.9713 | N6: 6324.1329 | O6: 0.11130946 | Q6: {=_xlfn.XLOOKUP(D6, DJ:DJ, DK:DV)} -> Drymill CCS 90 | R6: Biomass_Corn | S6: 0 | T6: 0.4049 | U6: 3.2587 | V6: 0.7507 | W6: 1.65 | X6: 0.66452746 | Y6: 0.07384 | Z6: 36112.15 | AA6: 173741.51 | AB6: 80.28 | AD6: 73.71884 | AE6: -6.199254 | AF6: 65.59151 | AG6: 31.821489 | AH6: 37.986239 | AI6: 155 | AJ6: 51.417555 | AL6: 22.465142 | AM6: 13.285634 | AO6: -129.68145 | AP6: -129.68145 | AU6: 15.046749 | AV6: 0 | AW6: 822.26752 | AX6: 822.26752 | AZ6: =B6 -> CEN_Ethanol_Dehydration_H2fuel | BA6: =C6 -> Ethanol | BB6: =SUM(BH6:BT6)+BV6+BW6 -> 853.88134 | BC6: =SUM(BH6:BT6)+BY6+BZ6 -> 853.88134 | BD6: =BB6-BC6 -> 0 | BE6: =SUM(BH6:BT6)+CB6+CC6 -> 1085.3585 | BF6: =SUM(BH6:BT6)+CE6+CF6 -> 1085.3585 | BG6: =BE6-BF6 -> 0 | BH6: =F6/H6*AM6 -> 21.185417 | BI6: =G6/H6*AL6 -> 5.1759687 | BJ6: =CJ6 -> 39.622108 | BK6: =CI6 -> 0 | BL6: =CK6 -> 675.16875 | BM6: =I6/H6*AU6 -> 0 | BN6: =CL6 -> 49.20279 | BO6: =M6/H6/(0.9*8760) -> 11.843236 | BP6: =CM6 -> 19.952043 | BQ6: =N6/H6/(0.9*8760) -> 11.386215 | BR6: =CN6 -> 95.992568 | BS6: =O6/H6 -> 1.58 | BT6: =CO6 -> 349.69385 | BU6: =CZ6-DF6-DD6 -> -3.14 | BV6: =(AD6+AE6)*-1*DC6 -> -195.44445 | BW6: =BU6*AD6 -> -231.47716 | BX6: =CZ6-DF6-DC6-DD6 -> -6.0346334 | BY6: =DC6*AE6*-1 -> 17.944568 | BZ6: =BX6*AD6 -> -444.86617 | CA6: =CZ6-DF6 -> 0 | CB6: =(AD6+AE6)*-1*DC6 -> -195.44445 | CC6: =CA6*AD6 -> 0 | CD6: =CZ6-DF6-DC6 -> -2.8946334 | CE6: =DC6*AE6*-1 -> 17.944568 | CF6: =CD6*AD6 -> -213.38902 | CH6: =Q6 -> Drymill CCS 90 | CI6: =S6/U6/H6*AL6*-1 -> 0 | CJ6: =T6/U6/H6*AL6 -> 39.622108 | CK6: {=_xlfn.IFS(R6="Biomass_Corn", 1/U6/H6*AI6, R6="Biomass_Agri", 1/U6/H6*AH6, R6="Biomass_Wood", 1/U6/H6*AG6, R6="Biomass_Herb", 1/U6/H6*AF6)} -> 675.16875 | CL6: =V6/U6/H6*AU6 -> 49.20279 | CM6: =Z6/U6/H6/(0.9*8760) -> 19.952043 | CN6: =AA6/U6/H6/(0.9*8760) -> 95.992568 | CO6: =AB6/U6/H6 -> 349.69385 | CQ6: 3.14 | CR6: =W6 -> 1.65 | CS6: 0.18104824 | CT6: =(CV6+CW6-DB6-DC6)*H6 -> 0.35376226 | CV6: =CR6/U6/H6 -> 7.1872802 | CW6: =IF(V6=0, 0, CS6/V6/U6/H6) -> 1.0505301 | CX6: =CT6/H6 -> 5.0215353 | CY6: =IF(I6=0, 0, CS6/I6/H6) -> 0 | CZ6: =CV6+CW6+CY6 -> 8.2378103 | DB6: =Y6/U6/H6 -> 0.32164168 | DC6: =X6/U6/H6 -> 2.8946334 | DD6: =CQ6 -> 3.14 | DE6: =L6/H6 -> 1.8815353 | DF6: =SUM(DB6:DE6) -> 8.2378103 | DH6: =CZ6-DF6 -> 0 | DJ6: 4 | DK6: SE_Biochemical_CCS_86 | DL6: Biomass_Agri | DM6: 0.1227 | DN6: 0.26 | DO6: 1.5509 | DP6: 0 | DQ6: 1.32 | DR6: 0.83 | DS6: 0.13259975 | DT6: 727064.6 | DU6: 233553.61 | DV6: 56.9
DJ7: 5 | DK7: Drymill CCS 90 | DL7: Biomass_Corn | DM7: 0 | DN7: 0.4049 | DO7: 3.2587 | DP7: 0.7507 | DQ7: 1.65 | DR7: 0.66452746 | DS7: 0.07384 | DT7: 36112.15 | DU7: 173741.51 | DV7: 80.28

Sheet lc_summary_noseq
A1: Levelized cost for Bioethylene Production - $/GJ-ethylene - no chemicals CO2 sequestration | V1: Assumptions | Z1: Levelized cost for Bioethylene Production - $/GJ-ethylene - no chemicals CO2 sequestration - SORTED
A2: id_LC | B2: h2_consumption | C2: elec_consumption | D2: elec_consumption - ethanol | E2: elec_production - ethanol | F2: biomass_consumption - ethanol | G2: natgas_consumption | H2: natgas_consumption - ethanol | I2: investment_cost | J2: investment_cost - ethanol | K2: fixed_om_cost | L2: fixed_om_cost - ethanol | M2: variable_om_cost | N2: variable_om_cost - ethanol | O2: modified capture cost | P2: modified emissions cost | Q2: CI | R2: LCOE ($/t-ethylene) | S2: LCOE ($/GJ-ethylene) | T2: CHECK LCOE ($/GJ-ethylene) | V2: Ethylene LHV | W2: 45.6 | X2: GJ/t-ethylene | Z2: id_LC | AA2: h2_consumption | AB2: elec_consumption | AC2: elec_consumption - ethanol | AD2: elec_production - ethanol | AE2: biomass_consumption - ethanol | AF2: natgas_consumption | AG2: natgas_consumption - ethanol | AH2: investment_cost | AI2: investment_cost - ethanol | AJ2: fixed_om_cost | AK2: fixed_om_cost - ethanol | AL2: variable_om_cost | AM2: variable_om_cost - ethanol | AN2: modified capture cost | AO2: modified emissions cost | AP2: CI | AQ2: LCOE ($/t-ethylene) | AR2: LCOE ($/GJ-ethylene) | AS2: CHECK LCOE ($/GJ-ethylene)
A3: =lc_detailed!AZ3 -> NCEN_Ethanol_Dehydration_NGfuel | B3: =lc_detailed!BH3/$W$2 -> 0 | C3: =lc_detailed!BI3/$W$2 -> 0.11573907 | D3: =lc_detailed!BJ3/$W$2 -> 0.88598405 | E3: =lc_detailed!BK3/$W$2 -> 0 | F3: =lc_detailed!BL3/$W$2 -> 14.806332 | G3: =lc_detailed!BM3/$W$2 -> 0.53330916 | H3: =lc_detailed!BN3/$W$2 -> 1.0723487 | I3: =lc_detailed!BO3/$W$2 -> 0.25972008 | ... N3: =lc_detailed!BT3/$W$2 -> 7.6687248 | O3: =lc_detailed!CB3/$W$2 -> -4.2925335 | P3: =lc_detailed!CC3/$W$2 -> 0 | Q3: =lc_detailed!CA3 -> 0 | R3: =lc_detailed!BE3 -> 1088.7737 | S3: =R3/$W$2 -> 23.876616 | T3: =SUM(B3:P3) -> 23.876616 | Z3: {=_xlfn._xlws.SORT(A3:T34, 18, 1)} -> 0 | AA3: 0 | AB3: 0 | AC3: 0 | AD3: 0 | AE3: 0 | AF3: 0 | AG3: 0 | AH3: 0 | AI3: 0 | AJ3: 0 | AK3: 0 | AL3: 0 | AM3: 0 | AN3: 0 | AO3: 0 | AP3: 0 | AQ3: 0 | AR3: 0 | AS3: 0
A4: =lc_detailed!AZ4 -> NCEN_Ethanol_Dehydration_H2fuel | B4: =lc_detailed!BH4/$W$2 -> 0.46149516 | C4: =lc_detailed!BI4/$W$2 -> 0.11573907 | D4: =lc_detailed!BJ4/$W$2 -> 0.88598405 | E4: =lc_detailed!BK4/$W$2 -> 0 | F4: =lc_detailed!BL4/$W$2 -> 14.806332 | G4: =lc_detailed!BM4/$W$2 -> 0 | H4: =lc_detailed!BN4/$W$2 -> 1.0723487 | I4: =lc_detailed!BO4/$W$2 -> 0.25972008 | ... N4: =lc_detailed!BT4/$W$2 -> 7.6687248 | O4: =lc_detailed!CB4/$W$2 -> -4.2925335 | P4: =lc_detailed!CC4/$W$2 -> 0 | Q4: =lc_detailed!CA4 -> 0 | R4: =lc_detailed!BE4 -> 1085.499 | S4: =R4/$W$2 -> 23.804802 | T4: =SUM(B4:P4) -> 23.804802 | Z4: 0 | AA4: 0 | AB4: 0 | AC4: 0 | AD4: 0 | AE4: 0 | AF4: 0 | AG4: 0 | AH4: 0 | AI4: 0 | AJ4: 0 | AK4: 0 | AL4: 0 | AM4: 0 | AN4: 0 | AO4: 0 | AP4: 0 | AQ4: 0 | AR4: 0 | AS4: 0
A5: =lc_detailed!AZ5 -> CEN_Ethanol_Dehydration_NGfuel | B5: =lc_detailed!BH5/$W$2 -> 0 | C5: =lc_detailed!BI5/$W$2 -> 0.11350809 | D5: =lc_detailed!BJ5/$W$2 -> 0.86890588 | E5: =lc_detailed!BK5/$W$2 -> 0 | F5: =lc_detailed!BL5/$W$2 -> 14.806332 | G5: =lc_detailed!BM5/$W$2 -> 0.53662127 | H5: =lc_detailed!BN5/$W$2 -> 1.0790085 | I5: =lc_detailed!BO5/$W$2 -> 0.25972008 | ... N5: =lc_detailed!BT5/$W$2 -> 7.6687248 | O5: =lc_detailed!CB5/$W$2 -> -4.2860624 | P5: =lc_detailed!CC5/$W$2 -> 0 | Q5: =lc_detailed!CA5 -> 0 | R5: =lc_detailed!BE5 -> 1088.643 | S5: =R5/$W$2 -> 23.87375 | T5: =SUM(B5:P5) -> 23.87375 | Z5: 0 | AA5: 0 | AB5: 0 | AC5: 0 | AD5: 0 | AE5: 0 | AF5: 0 | AG5: 0 | AH5: 0 | AI5: 0 | AJ5: 0 | AK5: 0 | AL5: 0 | AM5: 0 | AN5: 0 | AO5: 0 | AP5: 0 | AQ5: 0 | AR5: 0 | AS5: 0
A6: =lc_detailed!AZ6 -> CEN_Ethanol_Dehydration_H2fuel | B6: =lc_detailed!BH6/$W$2 -> 0.46459248 | C6: =lc_detailed!BI6/$W$2 -> 0.11350809 | D6: =lc_detailed!BJ6/$W$2 -> 0.86890588 | E6: =lc_detailed!BK6/$W$2 -> 0 | F6: =lc_detailed!BL6/$W$2 -> 14.806332 | G6: =lc_detailed!BM6/$W$2 -> 0 | H6: =lc_detailed!BN6/$W$2 -> 1.0790085 | I6: =lc_detailed!BO6/$W$2 -> 0.25972008 | ... N6: =lc_detailed!BT6/$W$2 -> 7.6687248 | O6: =lc_detailed!CB6/$W$2 -> -4.2860624 | P6: =lc_detailed!CC6/$W$2 -> 0 | Q6: =lc_detailed!CA6 -> 0 | R6: =lc_detailed!BE6 -> 1085.3585 | S6: =R6/$W$2 -> 23.801721 | T6: =SUM(B6:P6) -> 23.801721 | Z6: 0 | AA6: 0 | AB6: 0 | AC6: 0 | AD6: 0 | AE6: 0 | AF6: 0 | AG6: 0 | AH6: 0 | AI6: 0 | AJ6: 0 | AK6: 0 | AL6: 0 | AM6: 0 | AN6: 0 | AO6: 0 | AP6: 0 | AQ6: 0 | AR6: 0 | AS6: 0
A7: =lc_detailed!AZ7 -> 0 | B7: =lc_detailed!BH7/$W$2 -> 0 | C7: =lc_detailed!BI7/$W$2 -> 0 | D7: =lc_detailed!BJ7/$W$2 -> 0 | E7: =lc_detailed!BK7/$W$2 -> 0 | F7: =lc_detailed!BL7/$W$2 -> 0 | G7: =lc_detailed!BM7/$W$2 -> 0 | H7: =lc_detailed!BN7/$W$2 -> 0 | I7: =lc_detailed!BO7/$W$2 -> 0 | ... N7: =lc_detailed!BT7/$W$2 -> 0 | O7: =lc_detailed!CB7/$W$2 -> 0 | P7: =lc_detailed!CC7/$W$2 -> 0 | Q7: =lc_detailed!CA7 -> 0 | R7: =lc_detailed!BE7 -> 0 | S7: =R7/$W$2 -> 0 | T7: =SUM(B7:P7) -> 0 | Z7: CEN_Ethanol_Dehydration_H2fuel | AA7: 0.46459248 | AB7: 0.11350809 | AC7: 0.86890588 | AD7: 0 | AE7: 14.806332 | AF7: 0 | AG7: 1.0790085 | AH7: 0.25972008 | AI7: 0.43754479 | AJ7: 0.2496977 | AK7: 2.1051002 | AL7: 0.034649123 | AM7: 7.6687248 | AN7: -4.2860624 | AO7: 0 | AP7: 0 | AQ7: 1085.3585 | AR7: 23.801721 | AS7: 23.801721
A8: =lc_detailed!AZ8 -> 0 | B8: =lc_detailed!BH8/$W$2 -> 0 | C8: =lc_detailed!BI8/$W$2 -> 0 | D8: =lc_detailed!BJ8/$W$2 -> 0 | E8: =lc_detailed!BK8/$W$2 -> 0 | F8: =lc_detailed!BL8/$W$2 -> 0 | G8: =lc_detailed!BM8/$W$2 -> 0 | H8: =lc_detailed!BN8/$W$2 -> 0 | I8: =lc_detailed!BO8/$W$2 -> 0 | ... N8: =lc_detailed!BT8/$W$2 -> 0 | O8: =lc_detailed!CB8/$W$2 -> 0 | P8: =lc_detailed!CC8/$W$2 -> 0 | Q8: =lc_detailed!CA8 -> 0 | R8: =lc_detailed!BE8 -> 0 | S8: =R8/$W$2 -> 0 | T8: =SUM(B8:P8) -> 0 | Z8: NCEN_Ethanol_Dehydration_H2fuel | AA8: 0.46149516 | AB8: 0.11573907 | AC8: 0.88598405 | AD8: 0 | AE8: 14.806332 | AF8: 0 | AG8: 1.0723487 | AH8: 0.25972008 | AI8: 0.43754479 | AJ8: 0.2496977 | AK8: 2.1051002 | AL8: 0.034649123 | AM8: 7.6687248 | AN8: -4.2925335 | AO8: 0 | AP8: 0 | AQ8: 1085.499 | AR8: 23.804802 | AS8: 23.804802
A9: =lc_detailed!AZ9 -> 0 | B9: =lc_detailed!BH9/$W$2 -> 0 | C9: =lc_detailed!BI9/$W$2 -> 0 | D9: =lc_detailed!BJ9/$W$2 -> 0 | E9: =lc_detailed!BK9/$W$2 -> 0 | F9: =lc_detailed!BL9/$W$2 -> 0 | G9: =lc_detailed!BM9/$W$2 -> 0 | H9: =lc_detailed!BN9/$W$2 -> 0 | I9: =lc_detailed!BO9/$W$2 -> 0 | ... N9: =lc_detailed!BT9/$W$2 -> 0 | O9: =lc_detailed!CB9/$W$2 -> 0 | P9: =lc_detailed!CC9/$W$2 -> 0 | Q9: =lc_detailed!CA9 -> 0 | R9: =lc_detailed!BE9 -> 0 | S9: =R9/$W$2 -> 0 | T9: =SUM(B9:P9) -> 0 | Z9: CEN_Ethanol_Dehydration_NGfuel | AA9: 0 | AB9: 0.11350809 | AC9: 0.86890588 | AD9: 0 | AE9: 14.806332 | AF9: 0.53662127 | AG9: 1.0790085 | AH9: 0.25972008 | AI9: 0.43754479 | AJ9: 0.2496977 | AK9: 2.1051002 | AL9: 0.034649123 | AM9: 7.6687248 | AN9: -4.2860624 | AO9: 0 | AP9: 0 | AQ9: 1088.643 | AR9: 23.87375 | AS9: 23.87375
A10: =lc_detailed!AZ10 -> 0 | B10: =lc_detailed!BH10/$W$2 -> 0 | C10: =lc_detailed!BI10/$W$2 -> 0 | D10: =lc_detailed!BJ10/$W$2 -> 0 | E10: =lc_detailed!BK10/$W$2 -> 0 | F10: =lc_detailed!BL10/$W$2 -> 0 | G10: =lc_detailed!BM10/$W$2 -> 0 | H10: =lc_detailed!BN10/$W$2 -> 0 | I10: =lc_detailed!BO10/$W$2 -> 0 | ... N10: =lc_detailed!BT10/$W$2 -> 0 | O10: =lc_detailed!CB10/$W$2 -> 0 | P10: =lc_detailed!CC10/$W$2 -> 0 | Q10: =lc_detailed!CA10 -> 0 | R10: =lc_detailed!BE10 -> 0 | S10: =R10/$W$2 -> 0 | T10: =SUM(B10:P10) -> 0 | Z10: NCEN_Ethanol_Dehydration_NGfuel | AA10: 0 | AB10: 0.11573907 | AC10: 0.88598405 | AD10: 0 | AE10: 14.806332 | AF10: 0.53330916 | AG10: 1.0723487 | AH10: 0.25972008 | AI10: 0.43754479 | AJ10: 0.2496977 | AK10: 2.1051002 | AL10: 0.034649123 | AM10: 7.6687248 | AN10: -4.2925335 | AO10: 0 | AP10: 0 | AQ10: 1088.7737 | AR10: 23.876616 | AS10: 23.876616
Z11: 0 | AA11: 0 | AB11: 0 | AC11: 0 | AD11: 0 | AE11: 0 | AF11: 0 | AG11: 0 | AH11: 0 | AI11: 0 | AJ11: 0 | AK11: 0 | AL11: 0 | AM11: 0 | AN11: 0 | AO11: 0 | AP11: 0 | AQ11: 0 | AR11: 0 | AS11: 0
Z12: 0 | AA12: 0 | AB12: 0 | AC12: 0 | AD12: 0 | AE12: 0 | AF12: 0 | AG12: 0 | AH12: 0 | AI12: 0 | AJ12: 0 | AK12: 0 | AL12: 0 | AM12: 0 | AN12: 0 | AO12: 0 | AP12: 0 | AQ12: 0 | AR12: 0 | AS12: 0
Z13: 0 | AA13: 0 | AB13: 0 | AC13: 0 | AD13: 0 | AE13: 0 | AF13: 0 | AG13: 0 | AH13: 0 | AI13: 0 | AJ13: 0 | AK13: 0 | AL13: 0 | AM13: 0 | AN13: 0 | AO13: 0 | AP13: 0 | AQ13: 0 | AR13: 0 | AS13: 0
Z14: 0 | AA14: 0 | AB14: 0 | AC14: 0 | AD14: 0 | AE14: 0 | AF14: 0 | AG14: 0 | AH14: 0 | AI14: 0 | AJ14: 0 | AK14: 0 | AL14: 0 | AM14: 0 | AN14: 0 | AO14: 0 | AP14: 0 | AQ14: 0 | AR14: 0 | AS14: 0
Z15: 0 | AA15: 0 | AB15: 0 | AC15: 0 | AD15: 0 | AE15: 0 | AF15: 0 | AG15: 0 | AH15: 0 | AI15: 0 | AJ15: 0 | AK15: 0 | AL15: 0 | AM15: 0 | AN15: 0 | AO15: 0 | AP15: 0 | AQ15: 0 | AR15: 0 | AS15: 0
Z16: 0 | AA16: 0 | AB16: 0 | AC16: 0 | AD16: 0 | AE16: 0 | AF16: 0 | AG16: 0 | AH16: 0 | AI16: 0 | AJ16: 0 | AK16: 0 | AL16: 0 | AM16: 0 | AN16: 0 | AO16: 0 | AP16: 0 | AQ16: 0 | AR16: 0 | AS16: 0
Z17: 0 | AA17: 0 | AB17: 0 | AC17: 0 | AD17: 0 | AE17: 0 | AF17: 0 | AG17: 0 | AH17: 0 | AI17: 0 | AJ17: 0 | AK17: 0 | AL17: 0 | AM17: 0 | AN17: 0 | AO17: 0 | AP17: 0 | AQ17: 0 | AR17: 0 | AS17: 0
Z18: 0 | AA18: 0 | AB18: 0 | AC18: 0 | AD18: 0 | AE18: 0 | AF18: 0 | AG18: 0 | AH18: 0 | AI18: 0 | AJ18: 0 | AK18: 0 | AL18: 0 | AM18: 0 | AN18: 0 | AO18: 0 | AP18: 0 | AQ18: 0 | AR18: 0 | AS18: 0
Z19: 0 | AA19: 0 | AB19: 0 | AC19: 0 | AD19: 0 | AE19: 0 | AF19: 0 | AG19: 0 | AH19: 0 | AI19: 0 | AJ19: 0 | AK19: 0 | AL19: 0 | AM19: 0 | AN19: 0 | AO19: 0 | AP19: 0 | AQ19: 0 | AR19: 0 | AS19: 0
Z20: 0 | AA20: 0 | AB20: 0 | AC20: 0 | AD20: 0 | AE20: 0 | AF20: 0 | AG20: 0 | AH20: 0 | AI20: 0 | AJ20: 0 | AK20: 0 | AL20: 0 | AM20: 0 | AN20: 0 | AO20: 0 | AP20: 0 | AQ20: 0 | AR20: 0 | AS20: 0
Z21: 0 | AA21: 0 | AB21: 0 | AC21: 0 | AD21: 0 | AE21: 0 | AF21: 0 | AG21: 0 | AH21: 0 | AI21: 0 | AJ21: 0 | AK21: 0 | AL21: 0 | AM21: 0 | AN21: 0 | AO21: 0 | AP21: 0 | AQ21: 0 | AR21: 0 | AS21: 0
Z22: 0 | AA22: 0 | AB22: 0 | AC22: 0 | AD22: 0 | AE22: 0 | AF22: 0 | AG22: 0 | AH22: 0 | AI22: 0 | AJ22: 0 | AK22: 0 | AL22: 0 | AM22: 0 | AN22: 0 | AO22: 0 | AP22: 0 | AQ22: 0 | AR22: 0 | AS22: 0
... Z34: 0 | AA34: 0 | AB34: 0 | AC34: 0 | AD34: 0 | AE34: 0 | AF34: 0 | AG34: 0 | AH34: 0 | AI34: 0 | AJ34: 0 | AK34: 0 | AL34: 0 | AM34: 0 | AN34: 0 | AO34: 0 | AP34: 0 | AQ34: 0 | AR34: 0 | AS34: 0

Sheet lc_summary_seq
A1: Levelized cost for Bioethylene Production - $/GJ-ethylene - chemicals CO2 sequestration | V1: Assumptions | Z1: Levelized cost for Bioethylene Production - $/GJ-ethylene - chemicals CO2 sequestration - SORTED
A2: id_LC | B2: h2_consumption | C2: elec_consumption | D2: elec_consumption - ethanol | E2: elec_production - ethanol | F2: biomass_consumption - ethanol | G2: natgas_consumption | H2: natgas_consumption - ethanol | I2: investment_cost | J2: investment_cost - ethanol | K2: fixed_om_cost | L2: fixed_om_cost - ethanol | M2: variable_om_cost | N2: variable_om_cost - ethanol | O2: modified capture cost | P2: modified emissions cost | Q2: CI | R2: LCOE ($/t-ethylene) | S2: LCOE ($/GJ-ethylene) | T2: CHECK LCOE ($/GJ-ethylene) | V2: Ethylene LHV | W2: 45.6 | X2: GJ/t-ethylene | Z2: id_LC | AA2: h2_consumption | AB2: elec_consumption | AC2: elec_consumption - ethanol | AD2: elec_production - ethanol | AE2: biomass_consumption - ethanol | AF2: natgas_consumption | AG2: natgas_consumption - ethanol | AH2: investment_cost | AI2: investment_cost - ethanol | AJ2: fixed_om_cost | AK2: fixed_om_cost - ethanol | AL2: variable_om_cost | AM2: variable_om_cost - ethanol | AN2: modified capture cost | AO2: modified emissions cost | AP2: CI | AQ2: LCOE ($/t-ethylene) | AR2: LCOE ($/GJ-ethylene) | AS2: CHECK LCOE ($/GJ-ethylene)
A3: =lc_detailed!AZ3 -> NCEN_Ethanol_Dehydration_NGfuel | B3: =lc_detailed!BH3/$W$2 -> 0 | C3: =lc_detailed!BI3/$W$2 -> 0.11573907 | D3: =lc_detailed!BJ3/$W$2 -> 0.88598405 | E3: =lc_detailed!BK3/$W$2 -> 0 | F3: =lc_detailed!BL3/$W$2 -> 14.806332 | G3: =lc_detailed!BM3/$W$2 -> 0.53330916 | H3: =lc_detailed!BN3/$W$2 -> 1.0723487 | I3: =lc_detailed!BO3/$W$2 -> 0.25972008 | ... N3: =lc_detailed!BT3/$W$2 -> 7.6687248 | O3: =lc_detailed!BV3/$W$2 -> -4.2925335 | P3: =lc_detailed!BW3/$W$2 -> -5.0762535 | Q3: =lc_detailed!BU3 -> -3.14 | R3: =lc_detailed!BB3 -> 857.29655 | S3: =R3/$W$2 -> 18.800363 | T3: =SUM(B3:P3) -> 18.800363 | Z3: {=_xlfn._xlws.SORT(A3:T34, 18, 1)} -> 0 | AA3: 0 | AB3: 0 | AC3: 0 | AD3: 0 | AE3: 0 | AF3: 0 | AG3: 0 | AH3: 0 | AI3: 0 | AJ3: 0 | AK3: 0 | AL3: 0 | AM3: 0 | AN3: 0 | AO3: 0 | AP3: 0 | AQ3: 0 | AR3: 0 | AS3: 0
A4: =lc_detailed!AZ4 -> NCEN_Ethanol_Dehydration_H2fuel | B4: =lc_detailed!BH4/$W$2 -> 0.46149516 | C4: =lc_detailed!BI4/$W$2 -> 0.11573907 | D4: =lc_detailed!BJ4/$W$2 -> 0.88598405 | E4: =lc_detailed!BK4/$W$2 -> 0 | F4: =lc_detailed!BL4/$W$2 -> 14.806332 | G4: =lc_detailed!BM4/$W$2 -> 0 | H4: =lc_detailed!BN4/$W$2 -> 1.0723487 | I4: =lc_detailed!BO4/$W$2 -> 0.25972008 | ... N4: =lc_detailed!BT4/$W$2 -> 7.6687248 | O4: =lc_detailed!BV4/$W$2 -> -4.2925335 | P4: =lc_detailed!BW4/$W$2 -> -5.0762535 | Q4: =lc_detailed!BU4 -> -3.14 | R4: =lc_detailed!BB4 -> 854.02183 | S4: =R4/$W$2 -> 18.728549 | T4: =SUM(B4:P4) -> 18.728549 | Z4: 0 | AA4: 0 | AB4: 0 | AC4: 0 | AD4: 0 | AE4: 0 | AF4: 0 | AG4: 0 | AH4: 0 | AI4: 0 | AJ4: 0 | AK4: 0 | AL4: 0 | AM4: 0 | AN4: 0 | AO4: 0 | AP4: 0 | AQ4: 0 | AR4: 0 | AS4: 0
A5: =lc_detailed!AZ5 -> CEN_Ethanol_Dehydration_NGfuel | B5: =lc_detailed!BH5/$W$2 -> 0 | C5: =lc_detailed!BI5/$W$2 -> 0.11350809 | D5: =lc_detailed!BJ5/$W$2 -> 0.86890588 | E5: =lc_detailed!BK5/$W$2 -> 0 | F5: =lc_detailed!BL5/$W$2 -> 14.806332 | G5: =lc_detailed!BM5/$W$2 -> 0.53662127 | H5: =lc_detailed!BN5/$W$2 -> 1.0790085 | I5: =lc_detailed!BO5/$W$2 -> 0.25972008 | ... N5: =lc_detailed!BT5/$W$2 -> 7.6687248 | O5: =lc_detailed!BV5/$W$2 -> -4.2860624 | P5: =lc_detailed!BW5/$W$2 -> -5.0762535 | Q5: =lc_detailed!BU5 -> -3.14 | R5: =lc_detailed!BB5 -> 857.16585 | S5: =R5/$W$2 -> 18.797497 | T5: =SUM(B5:P5) -> 18.797497 | Z5: 0 | AA5: 0 | AB5: 0 | AC5: 0 | AD5: 0 | AE5: 0 | AF5: 0 | AG5: 0 | AH5: 0 | AI5: 0 | AJ5: 0 | AK5: 0 | AL5: 0 | AM5: 0 | AN5: 0 | AO5: 0 | AP5: 0 | AQ5: 0 | AR5: 0 | AS5: 0
A6: =lc_detailed!AZ6 -> CEN_Ethanol_Dehydration_H2fuel | B6: =lc_detailed!BH6/$W$2 -> 0.46459248 | C6: =lc_detailed!BI6/$W$2 -> 0.11350809 | D6: =lc_detailed!BJ6/$W$2 -> 0.86890588 | E6: =lc_detailed!BK6/$W$2 -> 0 | F6: =lc_detailed!BL6/$W$2 -> 14.806332 | G6: =lc_detailed!BM6/$W$2 -> 0 | H6: =lc_detailed!BN6/$W$2 -> 1.0790085 | I6: =lc_detailed!BO6/$W$2 -> 0.25972008 | ... N6: =lc_detailed!BT6/$W$2 -> 7.6687248 | O6: =lc_detailed!BV6/$W$2 -> -4.2860624 | P6: =lc_detailed!BW6/$W$2 -> -5.0762535 | Q6: =lc_detailed!BU6 -> -3.14 | R6: =lc_detailed!BB6 -> 853.88134 | S6: =R6/$W$2 -> 18.725468 | T6: =SUM(B6:P6) -> 18.725468 | Z6: 0 | AA6: 0 | AB6: 0 | AC6: 0 | AD6: 0 | AE6: 0 | AF6: 0 | AG6: 0 | AH6: 0 | AI6: 0 | AJ6: 0 | AK6: 0 | AL6: 0 | AM6: 0 | AN6: 0 | AO6: 0 | AP6: 0 | AQ6: 0 | AR6: 0 | AS6: 0
A7: =lc_detailed!AZ7 -> 0 | B7: =lc_detailed!BH7/$W$2 -> 0 | C7: =lc_detailed!BI7/$W$2 -> 0 | D7: =lc_detailed!BJ7/$W$2 -> 0 | E7: =lc_detailed!BK7/$W$2 -> 0 | F7: =lc_detailed!BL7/$W$2 -> 0 | G7: =lc_detailed!BM7/$W$2 -> 0 | H7: =lc_detailed!BN7/$W$2 -> 0 | I7: =lc_detailed!BO7/$W$2 -> 0 | ... N7: =lc_detailed!BT7/$W$2 -> 0 | O7: =lc_detailed!BV7/$W$2 -> 0 | P7: =lc_detailed!BW7/$W$2 -> 0 | Q7: =lc_detailed!BU7 -> 0 | R7: =lc_detailed!BB7 -> 0 | S7: =R7/$W$2 -> 0 | T7: =SUM(B7:P7) -> 0 | Z7: CEN_Ethanol_Dehydration_H2fuel | AA7: 0.46459248 | AB7: 0.11350809 | AC7: 0.86890588 | AD7: 0 | AE7: 14.806332 | AF7: 0 | AG7: 1.0790085 | AH7: 0.25972008 | AI7: 0.43754479 | AJ7: 0.2496977 | AK7: 2.1051002 | AL7: 0.034649123 | AM7: 7.6687248 | AN7: -4.2860624 | AO7: -5.0762535 | AP7: -3.14 | AQ7: 853.88134 | AR7: 18.725468 | AS7: 18.725468
A8: =lc_detailed!AZ8 -> 0 | B8: =lc_detailed!BH8/$W$2 -> 0 | C8: =lc_detailed!BI8/$W$2 -> 0 | D8: =lc_detailed!BJ8/$W$2 -> 0 | E8: =lc_detailed!BK8/$W$2 -> 0 | F8: =lc_detailed!BL8/$W$2 -> 0 | G8: =lc_detailed!BM8/$W$2 -> 0 | H8: =lc_detailed!BN8/$W$2 -> 0 | I8: =lc_detailed!BO8/$W$2 -> 0 | ... N8: =lc_detailed!BT8/$W$2 -> 0 | O8: =lc_detailed!BV8/$W$2 -> 0 | P8: =lc_detailed!BW8/$W$2 -> 0 | Q8: =lc_detailed!BU8 -> 0 | R8: =lc_detailed!BB8 -> 0 | S8: =R8/$W$2 -> 0 | T8: =SUM(B8:P8) -> 0 | Z8: NCEN_Ethanol_Dehydration_H2fuel | AA8: 0.46149516 | AB8: 0.11573907 | AC8: 0.88598405 | AD8: 0 | AE8: 14.806332 | AF8: 0 | AG8: 1.0723487 | AH8: 0.25972008 | AI8: 0.43754479 | AJ8: 0.2496977 | AK8: 2.1051002 | AL8: 0.034649123 | AM8: 7.6687248 | AN8: -4.2925335 | AO8: -5.0762535 | AP8: -3.14 | AQ8: 854.02183 | AR8: 18.728549 | AS8: 18.728549
A9: =lc_detailed!AZ9 -> 0 | B9: =lc_detailed!BH9/$W$2 -> 0 | C9: =lc_detailed!BI9/$W$2 -> 0 | D9: =lc_detailed!BJ9/$W$2 -> 0 | E9: =lc_detailed!BK9/$W$2 -> 0 | F9: =lc_detailed!BL9/$W$2 -> 0 | G9: =lc_detailed!BM9/$W$2 -> 0 | H9: =lc_detailed!BN9/$W$2 -> 0 | I9: =lc_detailed!BO9/$W$2 -> 0 | ... N9: =lc_detailed!BT9/$W$2 -> 0 | O9: =lc_detailed!BV9/$W$2 -> 0 | P9: =lc_detailed!BW9/$W$2 -> 0 | Q9: =lc_detailed!BU9 -> 0 | R9: =lc_detailed!BB9 -> 0 | S9: =R9/$W$2 -> 0 | T9: =SUM(B9:P9) -> 0 | Z9: CEN_Ethanol_Dehydration_NGfuel | AA9: 0 | AB9: 0.11350809 | AC9: 0.86890588 | AD9: 0 | AE9: 14.806332 | AF9: 0.53662127 | AG9: 1.0790085 | AH9: 0.25972008 | AI9: 0.43754479 | AJ9: 0.2496977 | AK9: 2.1051002 | AL9: 0.034649123 | AM9: 7.6687248 | AN9: -4.2860624 | AO9: -5.0762535 | AP9: -3.14 | AQ9: 857.16585 | AR9: 18.797497 | AS9: 18.797497
A10: =lc_detailed!AZ10 -> 0 | B10: =lc_detailed!BH10/$W$2 -> 0 | C10: =lc_detailed!BI10/$W$2 -> 0 | D10: =lc_detailed!BJ10/$W$2 -> 0 | E10: =lc_detailed!BK10/$W$2 -> 0 | F10: =lc_detailed!BL10/$W$2 -> 0 | G10: =lc_detailed!BM10/$W$2 -> 0 | H10: =lc_detailed!BN10/$W$2 -> 0 | I10: =lc_detailed!BO10/$W$2 -> 0 | ... N10: =lc_detailed!BT10/$W$2 -> 0 | O10: =lc_detailed!BV10/$W$2 -> 0 | P10: =lc_detailed!BW10/$W$2 -> 0 | Q10: =lc_detailed!BU10 -> 0 | R10: =lc_detailed!BB10 -> 0 | S10: =R10/$W$2 -> 0 | T10: =SUM(B10:P10) -> 0 | Z10: NCEN_Ethanol_Dehydration_NGfuel | AA10: 0 | AB10: 0.11573907 | AC10: 0.88598405 | AD10: 0 | AE10: 14.806332 | AF10: 0.53330916 | AG10: 1.0723487 | AH10: 0.25972008 | AI10: 0.43754479 | AJ10: 0.2496977 | AK10: 2.1051002 | AL10: 0.034649123 | AM10: 7.6687248 | AN10: -4.2925335 | AO10: -5.0762535 | AP10: -3.14 | AQ10: 857.29655 | AR10: 18.800363 | AS10: 18.800363
Z11: 0 | AA11: 0 | AB11: 0 | AC11: 0 | AD11: 0 | AE11: 0 | AF11: 0 | AG11: 0 | AH11: 0 | AI11: 0 | AJ11: 0 | AK11: 0 | AL11: 0 | AM11: 0 | AN11: 0 | AO11: 0 | AP11: 0 | AQ11: 0 | AR11: 0 | AS11: 0
Z12: 0 | AA12: 0 | AB12: 0 | AC12: 0 | AD12: 0 | AE12: 0 | AF12: 0 | AG12: 0 | AH12: 0 | AI12: 0 | AJ12: 0 | AK12: 0 | AL12: 0 | AM12: 0 | AN12: 0 | AO12: 0 | AP12: 0 | AQ12: 0 | AR12: 0 | AS12: 0
Z13: 0 | AA13: 0 | AB13: 0 | AC13: 0 | AD13: 0 | AE13: 0 | AF13: 0 | AG13: 0 | AH13: 0 | AI13: 0 | AJ13: 0 | AK13: 0 | AL13: 0 | AM13: 0 | AN13: 0 | AO13: 0 | AP13: 0 | AQ13: 0 | AR13: 0 | AS13: 0
Z14: 0 | AA14: 0 | AB14: 0 | AC14: 0 | AD14: 0 | AE14: 0 | AF14: 0 | AG14: 0 | AH14: 0 | AI14: 0 | AJ14: 0 | AK14: 0 | AL14: 0 | AM14: 0 | AN14: 0 | AO14: 0 | AP14: 0 | AQ14: 0 | AR14: 0 | AS14: 0
Z15: 0 | AA15: 0 | AB15: 0 | AC15: 0 | AD15: 0 | AE15: 0 | AF15: 0 | AG15: 0 | AH15: 0 | AI15: 0 | AJ15: 0 | AK15: 0 | AL15: 0 | AM15: 0 | AN15: 0 | AO15: 0 | AP15: 0 | AQ15: 0 | AR15: 0 | AS15: 0
Z16: 0 | AA16: 0 | AB16: 0 | AC16: 0 | AD16: 0 | AE16: 0 | AF16: 0 | AG16: 0 | AH16: 0 | AI16: 0 | AJ16: 0 | AK16: 0 | AL16: 0 | AM16: 0 | AN16: 0 | AO16: 0 | AP16: 0 | AQ16: 0 | AR16: 0 | AS16: 0
Z17: 0 | AA17: 0 | AB17: 0 | AC17: 0 | AD17: 0 | AE17: 0 | AF17: 0 | AG17: 0 | AH17: 0 | AI17: 0 | AJ17: 0 | AK17: 0 | AL17: 0 | AM17: 0 | AN17: 0 | AO17: 0 | AP17: 0 | AQ17: 0 | AR17: 0 | AS17: 0
Z18: 0 | AA18: 0 | AB18: 0 | AC18: 0 | AD18: 0 | AE18: 0 | AF18: 0 | AG18: 0 | AH18: 0 | AI18: 0 | AJ18: 0 | AK18: 0 | AL18: 0 | AM18: 0 | AN18: 0 | AO18: 0 | AP18: 0 | AQ18: 0 | AR18: 0 | AS18: 0
Z19: 0 | AA19: 0 | AB19: 0 | AC19: 0 | AD19: 0 | AE19: 0 | AF19: 0 | AG19: 0 | AH19: 0 | AI19: 0 | AJ19: 0 | AK19: 0 | AL19: 0 | AM19: 0 | AN19: 0 | AO19: 0 | AP19: 0 | AQ19: 0 | AR19: 0 | AS19: 0
Z20: 0 | AA20: 0 | AB20: 0 | AC20: 0 | AD20: 0 | AE20: 0 | AF20: 0 | AG20: 0 | AH20: 0 | AI20: 0 | AJ20: 0 | AK20: 0 | AL20: 0 | AM20: 0 | AN20: 0 | AO20: 0 | AP20: 0 | AQ20: 0 | AR20: 0 | AS20: 0
Z21: 0 | AA21: 0 | AB21: 0 | AC21: 0 | AD21: 0 | AE21: 0 | AF21: 0 | AG21: 0 | AH21: 0 | AI21: 0 | AJ21: 0 | AK21: 0 | AL21: 0 | AM21: 0 | AN21: 0 | AO21: 0 | AP21: 0 | AQ21: 0 | AR21: 0 | AS21: 0
Z22: 0 | AA22: 0 | AB22: 0 | AC22: 0 | AD22: 0 | AE22: 0 | AF22: 0 | AG22: 0 | AH22: 0 | AI22: 0 | AJ22: 0 | AK22: 0 | AL22: 0 | AM22: 0 | AN22: 0 | AO22: 0 | AP22: 0 | AQ22: 0 | AR22: 0 | AS22: 0
... Z34: 0 | AA34: 0 | AB34: 0 | AC34: 0 | AD34: 0 | AE34: 0 | AF34: 0 | AG34: 0 | AH34: 0 | AI34: 0 | AJ34: 0 | AK34: 0 | AL34: 0 | AM34: 0 | AN34: 0 | AO34: 0 | AP34: 0 | AQ34: 0 | AR34: 0 | AS34: 0
