Workbook

Sheet lc_detailed
B2: Asset Parameters (normalized by commodity feedstock) | S2: Duals | AA2: LCOE for assets with ethane capacity ($/t-ethylene) | AC2: CI | AD2: CREDIT | AO2: CARBON INTENSITY | AR2: CREDIT | AV2: Carbon Content | AZ2: Carbon Inputs | BD2: Carbon Outputs | BJ2: Sanity Checks
B3: id | C3: commodity | D3: CCS | E3: h2_consumption (MWh/MWh-ethane) | F3: h2_production (MWh/MWh-ethane) | G3: elec_consumption (MWh/MWh-ethane) | H3: ethylene_production (t-ethylene/MWh-ethane) | I3: natgas_consumption (MWh/MWh-ethane) | J3: natgas_production (MWh/MWh-ethane) | K3: process_capture_rate (t-CO2/MWh-ethane) | L3: process_emission_rate (t-CO2/MWh-ethane) | M3: fuel_capture_rate (t-CO2/MWh-ethane) | N3: fuel_emission_rate (t-CO2/MWh-ethane) | O3: investment_cost ($/yr per MW ethane) | P3: fixed_om_cost ($/yr per MW ethane) | Q3: variable_om_cost ($/MWh-ethane) | S3: co2_sink ($/t) | T3: co2_captured ($/t) | U3: ethane_supply ($/MWh) | V3: elec_demand ($/MWh) | W3: h2_balance ($/MWh) | X3: gasoline_balance ($/MWh) | Y3: ng_balance ($/MWh) | AA3: id_LC | AB3: commodity_LC | AC3: LCOE ($/t-ethylene) | AD3: LCOE ($/t-ethylene) | AE3: Diff. Between Methods | AF3: h2_consumption | AG3: h2_production | AH3: elec_consumption | AI3: ethane_consumption | AJ3: natgas_consumption | AK3: natgas_production | AL3: investment_cost | AM3: fixed_om_cost | AN3: variable_om_cost | AO3: CI | AP3: modified capture cost | AQ3: modified emissions cost | AR3: CI | AS3: modified capture cost | AT3: modified emissions cost | AV3: Ethylene (t-CO2/t-ethylene) | AW3: Ethane (t-CO2/MWh-ethane) | AX3: NG (t-CO2/MWh-NG) | AZ3: Ethane (t-CO2/t-ethylene) | BA3: NG (t-CO2/t-ethylene) | BB3: Total input (t-CO2/t-ethylene) | BD3: Ethylene (t-CO2/t-ethylene) | BE3: Methane (t-CO2/t-ethylene) | BF3: Emissions (t-CO2/t-ethylene) | BG3: Captured (t-CO2/t-ethylene) | BH3: Total Output (t-CO2/t-ethylene) | BJ3: Diff. Between Input and Output CO2 (t-CO2/t-ethylene)
B4: CA_F-NGin-H2out | C4: Ethane | D4: 0 | E4: 0 | F4: 0.155559 | G4: 0 | H4: 0.048583519 | I4: 0.16812274 | J4: 0 | K4: 0 | L4: 0.01967126 | M4: 0 | N4: 0.030748108 | O4: 90689.949 | P4: 49635.759 | Q4: -2.393333 | S4: 73.71884 | T4: -4.302149 | U4: 21.986353 | V4: 21.021514 | W4: 9.044068 | X4: -126.2252 | Y4: 10.321106 | AA4: =B4 -> CA_F-NGin-H2out | AB4: =C4 -> Ethane | AC4: =SUM(AF4:AN4)+AP4+AQ4 -> 852.9024 | AD4: =SUM(AF4:AN4)+AS4+AT4 -> 852.9024 | AE4: =AC4-AD4 -> 0 | AF4: =E4/H4*W4 -> 0 | AG4: =F4/H4*W4*-1 -> -28.958095 | AH4: =G4/H4*V4 -> 0 | AI4: =1/H4*U4 -> 452.54756 | AJ4: =I4/H4*Y4 -> 35.716075 | AK4: =J4/H4*Y4*-1 -> 0 | AL4: =O4/H4/(0.9*8760) -> 236.76831 | AM4: =P4/H4/(0.9*8760) -> 129.5863 | AN4: =Q4/H4 -> -49.26224 | AO4: =BE4+BF4+BG4 -> 1.0377875 | AP4: =(S4+T4)*-1*(K4+M4)/H4 -> 0 | AQ4: =AO4*S4 -> 76.50449 | AR4: =BE4+BF4 -> 1.0377875 | AS4: =T4*(K4+M4)*-1/H4 -> 0 | AT4: =AR4*S4 -> 76.50449 | AV4: =22/7 -> 3.1428571 | AW4: 0.20320575 | AX4: 0.18289084 | AZ4: =1/H4*AW4 -> 4.1826066 | BA4: =I4/H4*AX4 -> 0.63289175 | BB4: =AZ4+BA4 -> 4.8154984 | BD4: =AV4 -> 3.1428571 | BE4: =J4/H4*AX4 -> 0 | BF4: =(L4+N4)/H4 -> 1.0377875 | BG4: =(K4+M4)/H4 -> 0 | BH4: =SUM(BD4:BG4) -> 4.1806446 | BJ4: =BB4-BH4 -> 0.63485377
B5: NW_F-NGin-H2out | C5: Ethane | D5: 0 | E5: 0 | F5: 0.155559 | G5: 0 | H5: 0.048583519 | I5: 0.16812274 | J5: 0 | K5: 0 | L5: 0.01967126 | M5: 0 | N5: 0.030748108 | O5: 90689.949 | P5: 49635.759 | Q5: -2.393333 | S5: 73.71884 | T5: -5.000084 | U5: 21.986353 | V5: 21.357777 | W5: 7.54831 | X5: -126.78287 | Y5: 8.60172 | AA5: =B5 -> NW_F-NGin-H2out | AB5: =C5 -> Ethane | AC5: =SUM(AF5:AN5)+AP5+AQ5 -> 851.74173 | AD5: =SUM(AF5:AN5)+AS5+AT5 -> 851.74173 | AE5: =AC5-AD5 -> 0 | AF5: =E5/H5*W5 -> 0 | AG5: =F5/H5*W5*-1 -> -24.168845 | AH5: =G5/H5*V5 -> 0 | AI5: =1/H5*U5 -> 452.54756 | AJ5: =I5/H5*Y5 -> 29.766159 | AK5: =J5/H5*Y5*-1 -> 0 | AL5: =O5/H5/(0.9*8760) -> 236.76831 | AM5: =P5/H5/(0.9*8760) -> 129.5863 | AN5: =Q5/H5 -> -49.26224 | AO5: =BE5+BF5+BG5 -> 1.0377875 | AP5: =(S5+T5)*-1*(K5+M5)/H5 -> 0 | AQ5: =AO5*S5 -> 76.50449 | AR5: =BE5+BF5 -> 1.0377875 | AS5: =T5*(K5+M5)*-1/H5 -> 0 | AT5: =AR5*S5 -> 76.50449 | AV5: =22/7 -> 3.1428571 | AW5: 0.20320575 | AX5: 0.18289084 | AZ5: =1/H5*AW5 -> 4.1826066 | BA5: =I5/H5*AX5 -> 0.63289175 | BB5: =AZ5+BA5 -> 4.8154984 | BD5: =AV5 -> 3.1428571 | BE5: =J5/H5*AX5 -> 0 | BF5: =(L5+N5)/H5 -> 1.0377875 | BG5: =(K5+M5)/H5 -> 0 | BH5: =SUM(BD5:BG5) -> 4.1806446 | BJ5: =BB5-BH5 -> 0.63485377
B6: SW_F-NGin-H2out | C6: Ethane | D6: 0 | E6: 0 | F6: 0.155559 | G6: 0 | H6: 0.048583519 | I6: 0.16812274 | J6: 0 | K6: 0 | L6: 0.01967126 | M6: 0 | N6: 0.030748108 | O6: 90689.949 | P6: 49635.759 | Q6: -2.393333 | S6: 73.71884 | T6: -6.097314 | U6: 21.986353 | V6: 22.90669 | W6: 13.197062 | X6: -129.52898 | Y6: 14.953878 | AA6: =B6 -> SW_F-NGin-H2out | AB6: =C6 -> Ethane | AC6: =SUM(AF6:AN6)+AP6+AQ6 -> 855.63663 | AD6: =SUM(AF6:AN6)+AS6+AT6 -> 855.63663 | AE6: =AC6-AD6 -> 0 | AF6: =E6/H6*W6 -> 0 | AG6: =F6/H6*W6*-1 -> -42.255518 | AH6: =G6/H6*V6 -> 0 | AI6: =1/H6*U6 -> 452.54756 | AJ6: =I6/H6*Y6 -> 51.747732 | AK6: =J6/H6*Y6*-1 -> 0 | AL6: =O6/H6/(0.9*8760) -> 236.76831 | AM6: =P6/H6/(0.9*8760) -> 129.5863 | AN6: =Q6/H6 -> -49.26224 | AO6: =BE6+BF6+BG6 -> 1.0377875 | AP6: =(S6+T6)*-1*(K6+M6)/H6 -> 0 | AQ6: =AO6*S6 -> 76.50449 | AR6: =BE6+BF6 -> 1.0377875 | AS6: =T6*(K6+M6)*-1/H6 -> 0 | AT6: =AR6*S6 -> 76.50449 | AV6: =22/7 -> 3.1428571 | AW6: 0.20320575 | AX6: 0.18289084 | AZ6: =1/H6*AW6 -> 4.1826066 | BA6: =I6/H6*AX6 -> 0.63289175 | BB6: =AZ6+BA6 -> 4.8154984 | BD6: =AV6 -> 3.1428571 | BE6: =J6/H6*AX6 -> 0 | BF6: =(L6+N6)/H6 -> 1.0377875 | BG6: =(K6+M6)/H6 -> 0 | BH6: =SUM(BD6:BG6) -> 4.1806446 | BJ6: =BB6-BH6 -> 0.63485377
B7: TX_F-NGin-H2out | C7: Ethane | D7: 0 | E7: 0 | F7: 0.155559 | G7: 0 | H7: 0.048583519 | I7: 0.16812274 | J7: 0 | K7: 0 | L7: 0.01967126 | M7: 0 | N7: 0.030748108 | O7: 90689.949 | P7: 49635.759 | Q7: -2.393333 | S7: 73.71884 | T7: -6.199254 | U7: 21.986353 | V7: 22.465142 | W7: 13.285634 | X7: -129.68145 | Y7: 15.046749 | AA7: =B7 -> TX_F-NGin-H2out | AB7: =C7 -> Ethane | AC7: =SUM(AF7:AN7)+AP7+AQ7 -> 855.67441 | AD7: =SUM(AF7:AN7)+AS7+AT7 -> 855.67441 | AE7: =AC7-AD7 -> 0 | AF7: =E7/H7*W7 -> 0 | AG7: =F7/H7*W7*-1 -> -42.539115 | AH7: =G7/H7*V7 -> 0 | AI7: =1/H7*U7 -> 452.54756 | AJ7: =I7/H7*Y7 -> 52.069111 | AK7: =J7/H7*Y7*-1 -> 0 | AL7: =O7/H7/(0.9*8760) -> 236.76831 | AM7: =P7/H7/(0.9*8760) -> 129.5863 | AN7: =Q7/H7 -> -49.26224 | AO7: =BE7+BF7+BG7 -> 1.0377875 | AP7: =(S7+T7)*-1*(K7+M7)/H7 -> 0 | AQ7: =AO7*S7 -> 76.50449 | AR7: =BE7+BF7 -> 1.0377875 | AS7: =T7*(K7+M7)*-1/H7 -> 0 | AT7: =AR7*S7 -> 76.50449 | AV7: =22/7 -> 3.1428571 | AW7: 0.20320575 | AX7: 0.18289084 | AZ7: =1/H7*AW7 -> 4.1826066 | BA7: =I7/H7*AX7 -> 0.63289175 | BB7: =AZ7+BA7 -> 4.8154984 | BD7: =AV7 -> 3.1428571 | BE7: =J7/H7*AX7 -> 0 | BF7: =(L7+N7)/H7 -> 1.0377875 | BG7: =(K7+M7)/H7 -> 0 | BH7: =SUM(BD7:BG7) -> 4.1806446 | BJ7: =BB7-BH7 -> 0.63485377
B8: NCEN_F-NGin-H2out | C8: Ethane | D8: 0 | E8: 0 | F8: 0.155559 | G8: 0 | H8: 0.048583519 | I8: 0.16812274 | J8: 0 | K8: 0 | L8: 0.01967126 | M8: 0 | N8: 0.030748108 | O8: 90689.949 | P8: 49635.759 | Q8: -2.393333 | S8: 73.71884 | T8: -6.091002 | U8: 21.986353 | V8: 21.266241 | W8: 7.267779 | X8: -128.07763 | Y8: 7.96358 | AA8: =B8 -> NCEN_F-NGin-H2out | AB8: =C8 -> Ethane | AC8: =SUM(AF8:AN8)+AP8+AQ8 -> 850.43168 | AD8: =SUM(AF8:AN8)+AS8+AT8 -> 850.43168 | AE8: =AC8-AD8 -> 0 | AF8: =E8/H8*W8 -> 0 | AG8: =F8/H8*W8*-1 -> -23.270616 | AH8: =G8/H8*V8 -> 0 | AI8: =1/H8*U8 -> 452.54756 | AJ8: =I8/H8*Y8 -> 27.557882 | AK8: =J8/H8*Y8*-1 -> 0 | AL8: =O8/H8/(0.9*8760) -> 236.76831 | AM8: =P8/H8/(0.9*8760) -> 129.5863 | AN8: =Q8/H8 -> -49.26224 | AO8: =BE8+BF8+BG8 -> 1.0377875 | AP8: =(S8+T8)*-1*(K8+M8)/H8 -> 0 | AQ8: =AO8*S8 -> 76.50449 | AR8: =BE8+BF8 -> 1.0377875 | AS8: =T8*(K8+M8)*-1/H8 -> 0 | AT8: =AR8*S8 -> 76.50449 | AV8: =22/7 -> 3.1428571 | AW8: 0.20320575 | AX8: 0.18289084 | AZ8: =1/H8*AW8 -> 4.1826066 | BA8: =I8/H8*AX8 -> 0.63289175 | BB8: =AZ8+BA8 -> 4.8154984 | BD8: =AV8 -> 3.1428571 | BE8: =J8/H8*AX8 -> 0 | BF8: =(L8+N8)/H8 -> 1.0377875 | BG8: =(K8+M8)/H8 -> 0 | BH8: =SUM(BD8:BG8) -> 4.1806446 | BJ8: =BB8-BH8 -> 0.63485377
B9: CEN_F-NGin-H2out | C9: Ethane | D9: 0 | E9: 0 | F9: 0.155559 | G9: 0 | H9: 0.048583519 | I9: 0.16812274 | J9: 0 | K9: 0 | L9: 0.01967126 | M9: 0 | N9: 0.030748108 | O9: 90689.949 | P9: 49635.759 | Q9: -2.393333 | S9: 73.71884 | T9: -16.179128 | U9: 21.986353 | V9: 21.500722 | W9: 7.532437 | X9: -140.74133 | Y9: 5.407672 | AA9: =B9 -> CEN_F-NGin-H2out | AB9: =C9 -> Ethane | AC9: =SUM(AF9:AN9)+AP9+AQ9 -> 840.73959 | AD9: =SUM(AF9:AN9)+AS9+AT9 -> 840.73959 | AE9: =AC9-AD9 -> 0 | AF9: =E9/H9*W9 -> 0 | AG9: =F9/H9*W9*-1 -> -24.118021 | AH9: =G9/H9*V9 -> 0 | AI9: =1/H9*U9 -> 452.54756 | AJ9: =I9/H9*Y9 -> 18.71319 | AK9: =J9/H9*Y9*-1 -> 0 | AL9: =O9/H9/(0.9*8760) -> 236.76831 | AM9: =P9/H9/(0.9*8760) -> 129.5863 | AN9: =Q9/H9 -> -49.26224 | AO9: =BE9+BF9+BG9 -> 1.0377875 | AP9: =(S9+T9)*-1*(K9+M9)/H9 -> 0 | AQ9: =AO9*S9 -> 76.50449 | AR9: =BE9+BF9 -> 1.0377875 | AS9: =T9*(K9+M9)*-1/H9 -> 0 | AT9: =AR9*S9 -> 76.50449 | AV9: =22/7 -> 3.1428571 | AW9: 0.20320575 | AX9: 0.18289084 | AZ9: =1/H9*AW9 -> 4.1826066 | BA9: =I9/H9*AX9 -> 0.63289175 | BB9: =AZ9+BA9 -> 4.8154984 | BD9: =AV9 -> 3.1428571 | BE9: =J9/H9*AX9 -> 0 | BF9: =(L9+N9)/H9 -> 1.0377875 | BG9: =(K9+M9)/H9 -> 0 | BH9: =SUM(BD9:BG9) -> 4.1806446 | BJ9: =BB9-BH9 -> 0.63485377
B10: SE_F-NGin-H2out | C10: Ethane | D10: 0 | E10: 0 | F10: 0.155559 | G10: 0 | H10: 0.048583519 | I10: 0.16812274 | J10: 0 | K10: 0 | L10: 0.01967126 | M10: 0 | N10: 0.030748108 | O10: 90689.949 | P10: 49635.759 | Q10: -2.393333 | S10: 73.71884 | T10: -23.276809 | U10: 21.986353 | V10: 20.789991 | W10: 9.19598 | X10: -150.75579 | Y10: 8.960454 | AA10: =B10 -> SE_F-NGin-H2out | AB10: =C10 -> Ethane | AC10: =SUM(AF10:AN10)+AP10+AQ10 -> 847.70747 | AD10: =SUM(AF10:AN10)+AS10+AT10 -> 847.70747 | AE10: =AC10-AD10 -> 0 | AF10: =E10/H10*W10 -> 0 | AG10: =F10/H10*W10*-1 -> -29.4445 | AH10: =G10/H10*V10 -> 0 | AI10: =1/H10*U10 -> 452.54756 | AJ10: =I10/H10*Y10 -> 31.007554 | AK10: =J10/H10*Y10*-1 -> 0 | AL10: =O10/H10/(0.9*8760) -> 236.76831 | AM10: =P10/H10/(0.9*8760) -> 129.5863 | AN10: =Q10/H10 -> -49.26224 | AO10: =BE10+BF10+BG10 -> 1.0377875 | AP10: =(S10+T10)*-1*(K10+M10)/H10 -> 0 | AQ10: =AO10*S10 -> 76.50449 | AR10: =BE10+BF10 -> 1.0377875 | AS10: =T10*(K10+M10)*-1/H10 -> 0 | AT10: =AR10*S10 -> 76.50449 | AV10: =22/7 -> 3.1428571 | AW10: 0.20320575 | AX10: 0.18289084 | AZ10: =1/H10*AW10 -> 4.1826066 | BA10: =I10/H10*AX10 -> 0.63289175 | BB10: =AZ10+BA10 -> 4.8154984 | BD10: =AV10 -> 3.1428571 | BE10: =J10/H10*AX10 -> 0 | BF10: =(L10+N10)/H10 -> 1.0377875 | BG10: =(K10+M10)/H10 -> 0 | BH10: =SUM(BD10:BG10) -> 4.1806446 | BJ10: =BB10-BH10 -> 0.63485377
B11: MIDAT_F-NGin-H2out | C11: Ethane | D11: 0.9 | E11: 0 | F11: 0.155559 | G11: 0 | H11: 0.048583519 | I11: 0.16812274 | J11: 0 | K11: 0 | L11: 0.01967126 | M11: 0 | N11: 0.030748108 | O11: 90689.949 | P11: 49635.759 | Q11: -2.393333 | S11: 73.71884 | T11: -4.302149 | U11: 21.986353 | V11: 21.021514 | W11: 9.044068 | X11: -126.2252 | Y11: 10.321106 | AA11: =B11 -> MIDAT_F-NGin-H2out | AB11: =C11 -> Ethane | AC11: =SUM(AF11:AN11)+AP11+AQ11 -> 852.9024 | AD11: =SUM(AF11:AN11)+AS11+AT11 -> 852.9024 | AE11: =AC11-AD11 -> 0 | AF11: =E11/H11*W11 -> 0 | AG11: =F11/H11*W11*-1 -> -28.958095 | AH11: =G11/H11*V11 -> 0 | AI11: =1/H11*U11 -> 452.54756 | AJ11: =I11/H11*Y11 -> 35.716075 | AK11: =J11/H11*Y11*-1 -> 0 | AL11: =O11/H11/(0.9*8760) -> 236.76831 | AM11: =P11/H11/(0.9*8760) -> 129.5863 | AN11: =Q11/H11 -> -49.26224 | AO11: =BE11+BF11+BG11 -> 1.0377875 | AP11: =(S11+T11)*-1*(K11+M11)/H11 -> 0 | AQ11: =AO11*S11 -> 76.50449 | AR11: =BE11+BF11 -> 1.0377875 | AS11: =T11*(K11+M11)*-1/H11 -> 0 | AT11: =AR11*S11 -> 76.50449 | AV11: =22/7 -> 3.1428571 | AW11: 0.20320575 | AX11: 0.18289084 | AZ11: =1/H11*AW11 -> 4.1826066 | BA11: =I11/H11*AX11 -> 0.63289175 | BB11: =AZ11+BA11 -> 4.8154984 | BD11: =AV11 -> 3.1428571 | BE11: =J11/H11*AX11 -> 0 | BF11: =(L11+N11)/H11 -> 1.0377875 | BG11: =(K11+M11)/H11 -> 0 | BH11: =SUM(BD11:BG11) -> 4.1806446 | BJ11: =BB11-BH11 -> 0.63485377
B12: NE_F-NGin-H2out | C12: Ethane | D12: 0 | E12: 0 | F12: 0.155559 | G12: 0 | H12: 0.048583519 | I12: 0.16812274 | J12: 0 | K12: 0 | L12: 0.01967126 | M12: 0 | N12: 0.030748108 | O12: 90689.949 | P12: 49635.759 | Q12: -2.393333 | S12: 73.71884 | T12: -4.302149 | U12: 21.986353 | V12: 21.021514 | W12: 9.044068 | X12: -126.2252 | Y12: 10.321106 | AA12: =B12 -> NE_F-NGin-H2out | AB12: =C12 -> Ethane | AC12: =SUM(AF12:AN12)+AP12+AQ12 -> 852.9024 | AD12: =SUM(AF12:AN12)+AS12+AT12 -> 852.9024 | AE12: =AC12-AD12 -> 0 | AF12: =E12/H12*W12 -> 0 | AG12: =F12/H12*W12*-1 -> -28.958095 | AH12: =G12/H12*V12 -> 0 | AI12: =1/H12*U12 -> 452.54756 | AJ12: =I12/H12*Y12 -> 35.716075 | AK12: =J12/H12*Y12*-1 -> 0 | AL12: =O12/H12/(0.9*8760) -> 236.76831 | AM12: =P12/H12/(0.9*8760) -> 129.5863 | AN12: =Q12/H12 -> -49.26224 | AO12: =BE12+BF12+BG12 -> 1.0377875 | AP12: =(S12+T12)*-1*(K12+M12)/H12 -> 0 | AQ12: =AO12*S12 -> 76.50449 | AR12: =BE12+BF12 -> 1.0377875 | AS12: =T12*(K12+M12)*-1/H12 -> 0 | AT12: =AR12*S12 -> 76.50449 | AV12: =22/7 -> 3.1428571 | AW12: 0.20320575 | AX12: 0.18289084 | AZ12: =1/H12*AW12 -> 4.1826066 | BA12: =I12/H12*AX12 -> 0.63289175 | BB12: =AZ12+BA12 -> 4.8154984 | BD12: =AV12 -> 3.1428571 | BE12: =J12/H12*AX12 -> 0 | BF12: =(L12+N12)/H12 -> 1.0377875 | BG12: =(K12+M12)/H12 -> 0 | BH12: =SUM(BD12:BG12) -> 4.1806446 | BJ12: =BB12-BH12 -> 0.63485377
B13: CA_F-NGin | C13: Ethane | D13: 0.9 | E13: 0 | F13: 0 | G13: 0 | H13: 0.048583519 | I13: 0.012144678 | J13: 0 | K13: 0 | L13: 0.01967126 | M13: 0 | N13: 0.0022211503 | O13: 90689.948 | P13: 49635.759 | Q13: -2.3930916 | S13: 73.71884 | T13: -4.302149 | U13: 21.986353 | V13: 21.021514 | W13: 9.044068 | X13: -126.2252 | Y13: 10.321106 | AA13: =B13 -> CA_F-NGin | AB13: =C13 -> Ethane | AC13: =SUM(AF13:AN13)+AP13+AQ13 -> 805.44365 | AD13: =SUM(AF13:AN13)+AS13+AT13 -> 805.44365 | AE13: =AC13-AD13 -> 0 | AF13: =E13/H13*W13 -> 0 | AG13: =F13/H13*W13*-1 -> 0 | AH13: =G13/H13*V13 -> 0 | AI13: =1/H13*U13 -> 452.54756 | AJ13: =I13/H13*Y13 -> 2.5800212 | AK13: =J13/H13*Y13*-1 -> 0 | AL13: =O13/H13/(0.9*8760) -> 236.76831 | AM13: =P13/H13/(0.9*8760) -> 129.5863 | AN13: =Q13/H13 -> -49.257271 | AO13: =BE13+BF13+BG13 -> 0.45061393 | AP13: =(S13+T13)*-1*(K13+M13)/H13 -> 0 | AQ13: =AO13*S13 -> 33.218736 | AR13: =BE13+BF13 -> 0.45061393 | AS13: =T13*(K13+M13)*-1/H13 -> 0 | AT13: =AR13*S13 -> 33.218736 | AV13: =22/7 -> 3.1428571 | AW13: 0.20320575 | AX13: 0.18289084 | AZ13: =1/H13*AW13 -> 4.1826066 | BA13: =I13/H13*AX13 -> 0.045718185 | BB13: =AZ13+BA13 -> 4.2283248 | BD13: =AV13 -> 3.1428571 | BE13: =J13/H13*AX13 -> 0 | BF13: =(L13+N13)/H13 -> 0.45061393 | BG13: =(K13+M13)/H13 -> 0 | BH13: =SUM(BD13:BG13) -> 3.5934711 | BJ13: =BB13-BH13 -> 0.63485377
B14: NW_F-NGin | C14: Ethane | D14: 0 | E14: 0 | F14: 0 | G14: 0 | H14: 0.048583519 | I14: 0.012144678 | J14: 0 | K14: 0 | L14: 0.01967126 | M14: 0 | N14: 0.0022211503 | O14: 90689.948 | P14: 49635.759 | Q14: -2.3930916 | S14: 73.71884 | T14: -4.302149 | U14: 21.986353 | V14: 21.021514 | W14: 9.044068 | X14: -126.2252 | Y14: 10.321106 | AA14: =B14 -> NW_F-NGin | AB14: =C14 -> Ethane | AC14: =SUM(AF14:AN14)+AP14+AQ14 -> 805.44365 | AD14: =SUM(AF14:AN14)+AS14+AT14 -> 805.44365 | AE14: =AC14-AD14 -> 0 | AF14: =E14/H14*W14 -> 0 | AG14: =F14/H14*W14*-1 -> 0 | AH14: =G14/H14*V14 -> 0 | AI14: =1/H14*U14 -> 452.54756 | AJ14: =I14/H14*Y14 -> 2.5800212 | AK14: =J14/H14*Y14*-1 -> 0 | AL14: =O14/H14/(0.9*8760) -> 236.76831 | AM14: =P14/H14/(0.9*8760) -> 129.5863 | AN14: =Q14/H14 -> -49.257271 | AO14: =BE14+BF14+BG14 -> 0.45061393 | AP14: =(S14+T14)*-1*(K14+M14)/H14 -> 0 | AQ14: =AO14*S14 -> 33.218736 | AR14: =BE14+BF14 -> 0.45061393 | AS14: =T14*(K14+M14)*-1/H14 -> 0 | AT14: =AR14*S14 -> 33.218736 | AV14: =22/7 -> 3.1428571 | AW14: 0.20320575 | AX14: 0.18289084 | AZ14: =1/H14*AW14 -> 4.1826066 | BA14: =I14/H14*AX14 -> 0.045718185 | BB14: =AZ14+BA14 -> 4.2283248 | BD14: =AV14 -> 3.1428571 | BE14: =J14/H14*AX14 -> 0 | BF14: =(L14+N14)/H14 -> 0.45061393 | BG14: =(K14+M14)/H14 -> 0 | BH14: =SUM(BD14:BG14) -> 3.5934711 | BJ14: =BB14-BH14 -> 0.63485377
B15: SW_F-NGin | C15: Ethane | D15: 0 | E15: 0 | F15: 0 | G15: 0 | H15: 0.048583519 | I15: 0.012144678 | J15: 0 | K15: 0 | L15: 0.01967126 | M15: 0 | N15: 0.0022211503 | O15: 90689.948 | P15: 49635.759 | Q15: -2.3930916 | S15: 73.71884 | T15: -4.302149 | U15: 21.986353 | V15: 21.021514 | W15: 9.044068 | X15: -126.2252 | Y15: 10.321106 | AA15: =B15 -> SW_F-NGin | AB15: =C15 -> Ethane | AC15: =SUM(AF15:AN15)+AP15+AQ15 -> 805.44365 | AD15: =SUM(AF15:AN15)+AS15+AT15 -> 805.44365 | AE15: =AC15-AD15 -> 0 | AF15: =E15/H15*W15 -> 0 | AG15: =F15/H15*W15*-1 -> 0 | AH15: =G15/H15*V15 -> 0 | AI15: =1/H15*U15 -> 452.54756 | AJ15: =I15/H15*Y15 -> 2.5800212 | AK15: =J15/H15*Y15*-1 -> 0 | AL15: =O15/H15/(0.9*8760) -> 236.76831 | AM15: =P15/H15/(0.9*8760) -> 129.5863 | AN15: =Q15/H15 -> -49.257271 | AO15: =BE15+BF15+BG15 -> 0.45061393 | AP15: =(S15+T15)*-1*(K15+M15)/H15 -> 0 | AQ15: =AO15*S15 -> 33.218736 | AR15: =BE15+BF15 -> 0.45061393 | AS15: =T15*(K15+M15)*-1/H15 -> 0 | AT15: =AR15*S15 -> 33.218736 | AV15: =22/7 -> 3.1428571 | AW15: 0.20320575 | AX15: 0.18289084 | AZ15: =1/H15*AW15 -> 4.1826066 | BA15: =I15/H15*AX15 -> 0.045718185 | BB15: =AZ15+BA15 -> 4.2283248 | BD15: =AV15 -> 3.1428571 | BE15: =J15/H15*AX15 -> 0 | BF15: =(L15+N15)/H15 -> 0.45061393 | BG15: =(K15+M15)/H15 -> 0 | BH15: =SUM(BD15:BG15) -> 3.5934711 | BJ15: =BB15-BH15 -> 0.63485377
... B52: TX_F-H2in-CH4out | C52: Ethane | D52: 0 | E52: 0.11859412 | F52: 0 | G52: 0 | H52: 0.048583519 | I52: 0 | J52: 0.10750343 | K52: 0 | L52: 9.8671813e-06 | M52: 0 | N52: 0 | O52: 90689.948 | P52: 49635.759 | Q52: -2.3930916 | S52: 73.71884 | T52: -23.276809 | U52: 21.986353 | V52: 20.789991 | W52: 9.19598 | X52: -150.75579 | Y52: 8.960454 | AA52: =B52 -> TX_F-H2in-CH4out | AB52: =C52 -> Ethane | AC52: =SUM(AF52:AN52)+AP52+AQ52 -> 802.11377 | AD52: =SUM(AF52:AN52)+AS52+AT52 -> 802.11377 | AE52: =AC52-AD52 -> 0 | AF52: =E52/H52*W52 -> 22.447718 | AG52: =F52/H52*W52*-1 -> 0 | AH52: =G52/H52*V52 -> 0 | AI52: =1/H52*U52 -> 452.54756 | AJ52: =I52/H52*Y52 -> 0 | AK52: =J52/H52*Y52*-1 -> -19.827291 | AL52: =O52/H52/(0.9*8760) -> 236.76831 | AM52: =P52/H52/(0.9*8760) -> 129.5863 | AN52: =Q52/H52 -> -49.257271 | AO52: =BE52+BF52+BG52 -> 0.40489574 | AP52: =(S52+T52)*-1*(K52+M52)/H52 -> 0 | AQ52: =AO52*S52 -> 29.848444 | AR52: =BE52+BF52 -> 0.40489574 | AS52: =T52*(K52+M52)*-1/H52 -> 0 | AT52: =AR52*S52 -> 29.848444 | AV52: =22/7 -> 3.1428571 | AW52: 0.20320575 | AX52: 0.18289084 | AZ52: =1/H52*AW52 -> 4.1826066 | BA52: =I52/H52*AX52 -> 0 | BB52: =AZ52+BA52 -> 4.1826066 | BD52: =AV52 -> 3.1428571 | BE52: =J52/H52*AX52 -> 0.40469264 | BF52: =(L52+N52)/H52 -> 0.00020309729 | BG52: =(K52+M52)/H52 -> 0 | BH52: =SUM(BD52:BG52) -> 3.5477529 | BJ52: =BB52-BH52 -> 0.63485377
B53: NCEN_F-H2in-CH4out | C53: Ethane | E53: 0.11859412 | F53: 0 | G53: 0 | H53: 0.048583519 | I53: 0 | J53: 0.10750343 | K53: 0 | L53: 9.8671813e-06 | M53: 0 | N53: 0 | O53: 90689.948 | P53: 49635.759 | Q53: -2.3930916 | S53: 73.71884 | T53: -23.276809 | U53: 21.986353 | V53: 20.789991 | W53: 9.19598 | X53: -150.75579 | Y53: 8.960454 | AA53: =B53 -> NCEN_F-H2in-CH4out | AB53: =C53 -> Ethane | AC53: =SUM(AF53:AN53)+AP53+AQ53 -> 802.11377 | AD53: =SUM(AF53:AN53)+AS53+AT53 -> 802.11377 | AE53: =AC53-AD53 -> 0 | AF53: =E53/H53*W53 -> 22.447718 | AG53: =F53/H53*W53*-1 -> 0 | AH53: =G53/H53*V53 -> 0 | AI53: =1/H53*U53 -> 452.54756 | AJ53: =I53/H53*Y53 -> 0 | AK53: =J53/H53*Y53*-1 -> -19.827291 | AL53: =O53/H53/(0.9*8760) -> 236.76831 | AM53: =P53/H53/(0.9*8760) -> 129.5863 | AN53: =Q53/H53 -> -49.257271 | AO53: =BE53+BF53+BG53 -> 0.40489574 | AP53: =(S53+T53)*-1*(K53+M53)/H53 -> 0 | AQ53: =AO53*S53 -> 29.848444 | AR53: =BE53+BF53 -> 0.40489574 | AS53: =T53*(K53+M53)*-1/H53 -> 0 | AT53: =AR53*S53 -> 29.848444 | AV53: =22/7 -> 3.1428571 | AW53: 0.20320575 | AX53: 0.18289084 | AZ53: =1/H53*AW53 -> 4.1826066 | BA53: =I53/H53*AX53 -> 0 | BB53: =AZ53+BA53 -> 4.1826066 | BD53: =AV53 -> 3.1428571 | BE53: =J53/H53*AX53 -> 0.40469264 | BF53: =(L53+N53)/H53 -> 0.00020309729 | BG53: =(K53+M53)/H53 -> 0 | BH53: =SUM(BD53:BG53) -> 3.5477529 | BJ53: =BB53-BH53 -> 0.63485377
B54: CEN_F-H2in-CH4out | C54: Ethane | E54: 0.11859412 | F54: 0 | G54: 0 | H54: 0.048583519 | I54: 0 | J54: 0.10750343 | K54: 0 | L54: 9.8671813e-06 | M54: 0 | N54: 0 | O54: 90689.948 | P54: 49635.759 | Q54: -2.3930916 | S54: 73.71884 | T54: -23.276809 | U54: 21.986353 | V54: 20.789991 | W54: 9.19598 | X54: -150.75579 | Y54: 8.960454 | AA54: =B54 -> CEN_F-H2in-CH4out | AB54: =C54 -> Ethane | AC54: =SUM(AF54:AN54)+AP54+AQ54 -> 802.11377 | AD54: =SUM(AF54:AN54)+AS54+AT54 -> 802.11377 | AE54: =AC54-AD54 -> 0 | AF54: =E54/H54*W54 -> 22.447718 | AG54: =F54/H54*W54*-1 -> 0 | AH54: =G54/H54*V54 -> 0 | AI54: =1/H54*U54 -> 452.54756 | AJ54: =I54/H54*Y54 -> 0 | AK54: =J54/H54*Y54*-1 -> -19.827291 | AL54: =O54/H54/(0.9*8760) -> 236.76831 | AM54: =P54/H54/(0.9*8760) -> 129.5863 | AN54: =Q54/H54 -> -49.257271 | AO54: =BE54+BF54+BG54 -> 0.40489574 | AP54: =(S54+T54)*-1*(K54+M54)/H54 -> 0 | AQ54: =AO54*S54 -> 29.848444 | AR54: =BE54+BF54 -> 0.40489574 | AS54: =T54*(K54+M54)*-1/H54 -> 0 | AT54: =AR54*S54 -> 29.848444 | AV54: =22/7 -> 3.1428571 | AW54: 0.20320575 | AX54: 0.18289084 | AZ54: =1/H54*AW54 -> 4.1826066 | BA54: =I54/H54*AX54 -> 0 | BB54: =AZ54+BA54 -> 4.1826066 | BD54: =AV54 -> 3.1428571 | BE54: =J54/H54*AX54 -> 0.40469264 | BF54: =(L54+N54)/H54 -> 0.00020309729 | BG54: =(K54+M54)/H54 -> 0 | BH54: =SUM(BD54:BG54) -> 3.5477529 | BJ54: =BB54-BH54 -> 0.63485377
B55: SE_F-H2in-CH4out | C55: Ethane | E55: 0.11859412 | F55: 0 | G55: 0 | H55: 0.048583519 | I55: 0 | J55: 0.10750343 | K55: 0 | L55: 9.8671813e-06 | M55: 0 | N55: 0 | O55: 90689.948 | P55: 49635.759 | Q55: -2.3930916 | S55: 73.71884 | T55: -23.276809 | U55: 21.986353 | V55: 20.789991 | W55: 9.19598 | X55: -150.75579 | Y55: 8.960454 | AA55: =B55 -> SE_F-H2in-CH4out | AB55: =C55 -> Ethane | AC55: =SUM(AF55:AN55)+AP55+AQ55 -> 802.11377 | AD55: =SUM(AF55:AN55)+AS55+AT55 -> 802.11377 | AE55: =AC55-AD55 -> 0 | AF55: =E55/H55*W55 -> 22.447718 | AG55: =F55/H55*W55*-1 -> 0 | AH55: =G55/H55*V55 -> 0 | AI55: =1/H55*U55 -> 452.54756 | AJ55: =I55/H55*Y55 -> 0 | AK55: =J55/H55*Y55*-1 -> -19.827291 | AL55: =O55/H55/(0.9*8760) -> 236.76831 | AM55: =P55/H55/(0.9*8760) -> 129.5863 | AN55: =Q55/H55 -> -49.257271 | AO55: =BE55+BF55+BG55 -> 0.40489574 | AP55: =(S55+T55)*-1*(K55+M55)/H55 -> 0 | AQ55: =AO55*S55 -> 29.848444 | AR55: =BE55+BF55 -> 0.40489574 | AS55: =T55*(K55+M55)*-1/H55 -> 0 | AT55: =AR55*S55 -> 29.848444 | AV55: =22/7 -> 3.1428571 | AW55: 0.20320575 | AX55: 0.18289084 | AZ55: =1/H55*AW55 -> 4.1826066 | BA55: =I55/H55*AX55 -> 0 | BB55: =AZ55+BA55 -> 4.1826066 | BD55: =AV55 -> 3.1428571 | BE55: =J55/H55*AX55 -> 0.40469264 | BF55: =(L55+N55)/H55 -> 0.00020309729 | BG55: =(K55+M55)/H55 -> 0 | BH55: =SUM(BD55:BG55) -> 3.5477529 | BJ55: =BB55-BH55 -> 0.63485377
B56: MIDAT_F-H2in-CH4out | C56: Ethane | E56: 0.11859412 | F56: 0 | G56: 0 | H56: 0.048583519 | I56: 0 | J56: 0.10750343 | K56: 0 | L56: 9.8671813e-06 | M56: 0 | N56: 0 | O56: 90689.948 | P56: 49635.759 | Q56: -2.3930916 | S56: 73.71884 | T56: -23.276809 | U56: 21.986353 | V56: 20.789991 | W56: 9.19598 | X56: -150.75579 | Y56: 8.960454 | AA56: =B56 -> MIDAT_F-H2in-CH4out | AB56: =C56 -> Ethane | AC56: =SUM(AF56:AN56)+AP56+AQ56 -> 802.11377 | AD56: =SUM(AF56:AN56)+AS56+AT56 -> 802.11377 | AE56: =AC56-AD56 -> 0 | AF56: =E56/H56*W56 -> 22.447718 | AG56: =F56/H56*W56*-1 -> 0 | AH56: =G56/H56*V56 -> 0 | AI56: =1/H56*U56 -> 452.54756 | AJ56: =I56/H56*Y56 -> 0 | AK56: =J56/H56*Y56*-1 -> -19.827291 | AL56: =O56/H56/(0.9*8760) -> 236.76831 | AM56: =P56/H56/(0.9*8760) -> 129.5863 | AN56: =Q56/H56 -> -49.257271 | AO56: =BE56+BF56+BG56 -> 0.40489574 | AP56: =(S56+T56)*-1*(K56+M56)/H56 -> 0 | AQ56: =AO56*S56 -> 29.848444 | AR56: =BE56+BF56 -> 0.40489574 | AS56: =T56*(K56+M56)*-1/H56 -> 0 | AT56: =AR56*S56 -> 29.848444 | AV56: =22/7 -> 3.1428571 | AW56: 0.20320575 | AX56: 0.18289084 | AZ56: =1/H56*AW56 -> 4.1826066 | BA56: =I56/H56*AX56 -> 0 | BB56: =AZ56+BA56 -> 4.1826066 | BD56: =AV56 -> 3.1428571 | BE56: =J56/H56*AX56 -> 0.40469264 | BF56: =(L56+N56)/H56 -> 0.00020309729 | BG56: =(K56+M56)/H56 -> 0 | BH56: =SUM(BD56:BG56) -> 3.5477529 | BJ56: =BB56-BH56 -> 0.63485377
B57: NE_F-H2in-CH4out | C57: Ethane | E57: 0.11859412 | F57: 0 | G57: 0 | H57: 0.048583519 | I57: 0 | J57: 0.10750343 | K57: 0 | L57: 9.8671813e-06 | M57: 0 | N57: 0 | O57: 90689.948 | P57: 49635.759 | Q57: -2.3930916 | S57: 73.71884 | T57: -23.276809 | U57: 21.986353 | V57: 20.789991 | W57: 9.19598 | X57: -150.75579 | Y57: 8.960454 | AA57: =B57 -> NE_F-H2in-CH4out | AB57: =C57 -> Ethane | AC57: =SUM(AF57:AN57)+AP57+AQ57 -> 802.11377 | AD57: =SUM(AF57:AN57)+AS57+AT57 -> 802.11377 | AE57: =AC57-AD57 -> 0 | AF57: =E57/H57*W57 -> 22.447718 | AG57: =F57/H57*W57*-1 -> 0 | AH57: =G57/H57*V57 -> 0 | AI57: =1/H57*U57 -> 452.54756 | AJ57: =I57/H57*Y57 -> 0 | AK57: =J57/H57*Y57*-1 -> -19.827291 | AL57: =O57/H57/(0.9*8760) -> 236.76831 | AM57: =P57/H57/(0.9*8760) -> 129.5863 | AN57: =Q57/H57 -> -49.257271 | AO57: =BE57+BF57+BG57 -> 0.40489574 | AP57: =(S57+T57)*-1*(K57+M57)/H57 -> 0 | AQ57: =AO57*S57 -> 29.848444 | AR57: =BE57+BF57 -> 0.40489574 | AS57: =T57*(K57+M57)*-1/H57 -> 0 | AT57: =AR57*S57 -> 29.848444 | AV57: =22/7 -> 3.1428571 | AW57: 0.20320575 | AX57: 0.18289084 | AZ57: =1/H57*AW57 -> 4.1826066 | BA57: =I57/H57*AX57 -> 0 | BB57: =AZ57+BA57 -> 4.1826066 | BD57: =AV57 -> 3.1428571 | BE57: =J57/H57*AX57 -> 0.40469264 | BF57: =(L57+N57)/H57 -> 0.00020309729 | BG57: =(K57+M57)/H57 -> 0 | BH57: =SUM(BD57:BG57) -> 3.5477529 | BJ57: =BB57-BH57 -> 0.63485377
B58: CA_F-Ein | C58: Ethane | E58: 0 | F58: 0.155559 | G58: 0.164935 | H58: 0.048583519 | I58: 0 | J58: 0.10750343 | K58: 0 | L58: 9.8671813e-06 | M58: 0 | N58: 0 | O58: 120149.9 | P58: 65759.565 | Q58: -1.8949334 | S58: 73.71884 | T58: -23.276809 | U58: 21.986353 | V58: 20.789991 | W58: 9.19598 | X58: -150.75579 | Y58: 8.960454 | AA58: =B58 -> CA_F-Ein | AB58: =C58 -> Ethane | AC58: =SUM(AF58:AN58)+AP58+AQ58 -> 950.06218 | AD58: =SUM(AF58:AN58)+AS58+AT58 -> 950.06218 | AE58: =AC58-AD58 -> 0 | AF58: =E58/H58*W58 -> 0 | AG58: =F58/H58*W58*-1 -> -29.4445 | AH58: =G58/H58*V58 -> 70.57943 | AI58: =1/H58*U58 -> 452.54756 | AJ58: =I58/H58*Y58 -> 0 | AK58: =J58/H58*Y58*-1 -> -19.827291 | AL58: =O58/H58/(0.9*8760) -> 313.68072 | AM58: =P58/H58/(0.9*8760) -> 171.68144 | AN58: =Q58/H58 -> -39.003626 | AO58: =BE58+BF58+BG58 -> 0.40489574 | AP58: =(S58+T58)*-1*(K58+M58)/H58 -> 0 | AQ58: =AO58*S58 -> 29.848444 | AR58: =BE58+BF58 -> 0.40489574 | AS58: =T58*(K58+M58)*-1/H58 -> 0 | AT58: =AR58*S58 -> 29.848444 | AV58: =22/7 -> 3.1428571 | AW58: 0.20320575 | AX58: 0.18289084 | AZ58: =1/H58*AW58 -> 4.1826066 | BA58: =I58/H58*AX58 -> 0 | BB58: =AZ58+BA58 -> 4.1826066 | BD58: =AV58 -> 3.1428571 | BE58: =J58/H58*AX58 -> 0.40469264 | BF58: =(L58+N58)/H58 -> 0.00020309729 | BG58: =(K58+M58)/H58 -> 0 | BH58: =SUM(BD58:BG58) -> 3.5477529 | BJ58: =BB58-BH58 -> 0.63485377
B59: NW_F-Ein | C59: Ethane | E59: 0 | F59: 0.155559 | G59: 0.164935 | H59: 0.048583519 | I59: 0 | J59: 0.10750343 | K59: 0 | L59: 9.8671813e-06 | M59: 0 | N59: 0 | O59: 120149.9 | P59: 65759.565 | Q59: -1.8949334 | S59: 73.71884 | T59: -23.276809 | U59: 21.986353 | V59: 20.789991 | W59: 9.19598 | X59: -150.75579 | Y59: 8.960454 | AA59: =B59 -> NW_F-Ein | AB59: =C59 -> Ethane | AC59: =SUM(AF59:AN59)+AP59+AQ59 -> 950.06218 | AD59: =SUM(AF59:AN59)+AS59+AT59 -> 950.06218 | AE59: =AC59-AD59 -> 0 | AF59: =E59/H59*W59 -> 0 | AG59: =F59/H59*W59*-1 -> -29.4445 | AH59: =G59/H59*V59 -> 70.57943 | AI59: =1/H59*U59 -> 452.54756 | AJ59: =I59/H59*Y59 -> 0 | AK59: =J59/H59*Y59*-1 -> -19.827291 | AL59: =O59/H59/(0.9*8760) -> 313.68072 | AM59: =P59/H59/(0.9*8760) -> 171.68144 | AN59: =Q59/H59 -> -39.003626 | AO59: =BE59+BF59+BG59 -> 0.40489574 | AP59: =(S59+T59)*-1*(K59+M59)/H59 -> 0 | AQ59: =AO59*S59 -> 29.848444 | AR59: =BE59+BF59 -> 0.40489574 | AS59: =T59*(K59+M59)*-1/H59 -> 0 | AT59: =AR59*S59 -> 29.848444 | AV59: =22/7 -> 3.1428571 | AW59: 0.20320575 | AX59: 0.18289084 | AZ59: =1/H59*AW59 -> 4.1826066 | BA59: =I59/H59*AX59 -> 0 | BB59: =AZ59+BA59 -> 4.1826066 | BD59: =AV59 -> 3.1428571 | BE59: =J59/H59*AX59 -> 0.40469264 | BF59: =(L59+N59)/H59 -> 0.00020309729 | BG59: =(K59+M59)/H59 -> 0 | BH59: =SUM(BD59:BG59) -> 3.5477529 | BJ59: =BB59-BH59 -> 0.63485377
B60: SW_F-Ein | C60: Ethane | E60: 0 | F60: 0.155559 | G60: 0.164935 | H60: 0.048583519 | I60: 0 | J60: 0.10750343 | K60: 0 | L60: 9.8671813e-06 | M60: 0 | N60: 0 | O60: 120149.9 | P60: 65759.565 | Q60: -1.8949334 | S60: 73.71884 | T60: -23.276809 | U60: 21.986353 | V60: 20.789991 | W60: 9.19598 | X60: -150.75579 | Y60: 8.960454 | AA60: =B60 -> SW_F-Ein | AB60: =C60 -> Ethane | AC60: =SUM(AF60:AN60)+AP60+AQ60 -> 950.06218 | AD60: =SUM(AF60:AN60)+AS60+AT60 -> 950.06218 | AE60: =AC60-AD60 -> 0 | AF60: =E60/H60*W60 -> 0 | AG60: =F60/H60*W60*-1 -> -29.4445 | AH60: =G60/H60*V60 -> 70.57943 | AI60: =1/H60*U60 -> 452.54756 | AJ60: =I60/H60*Y60 -> 0 | AK60: =J60/H60*Y60*-1 -> -19.827291 | AL60: =O60/H60/(0.9*8760) -> 313.68072 | AM60: =P60/H60/(0.9*8760) -> 171.68144 | AN60: =Q60/H60 -> -39.003626 | AO60: =BE60+BF60+BG60 -> 0.40489574 | AP60: =(S60+T60)*-1*(K60+M60)/H60 -> 0 | AQ60: =AO60*S60 -> 29.848444 | AR60: =BE60+BF60 -> 0.40489574 | AS60: =T60*(K60+M60)*-1/H60 -> 0 | AT60: =AR60*S60 -> 29.848444 | AV60: =22/7 -> 3.1428571 | AW60: 0.20320575 | AX60: 0.18289084 | AZ60: =1/H60*AW60 -> 4.1826066 | BA60: =I60/H60*AX60 -> 0 | BB60: =AZ60+BA60 -> 4.1826066 | BD60: =AV60 -> 3.1428571 | BE60: =J60/H60*AX60 -> 0.40469264 | BF60: =(L60+N60)/H60 -> 0.00020309729 | BG60: =(K60+M60)/H60 -> 0 | BH60: =SUM(BD60:BG60) -> 3.5477529 | BJ60: =BB60-BH60 -> 0.63485377
B61: TX_F-Ein | C61: Ethane | E61: 0 | F61: 0.155559 | G61: 0.164935 | H61: 0.048583519 | I61: 0 | J61: 0.10750343 | K61: 0 | L61: 9.8671813e-06 | M61: 0 | N61: 0 | O61: 120149.9 | P61: 65759.565 | Q61: -1.8949334 | S61: 73.71884 | T61: -23.276809 | U61: 21.986353 | V61: 20.789991 | W61: 9.19598 | X61: -150.75579 | Y61: 8.960454 | AA61: =B61 -> TX_F-Ein | AB61: =C61 -> Ethane | AC61: =SUM(AF61:AN61)+AP61+AQ61 -> 950.06218 | AD61: =SUM(AF61:AN61)+AS61+AT61 -> 950.06218 | AE61: =AC61-AD61 -> 0 | AF61: =E61/H61*W61 -> 0 | AG61: =F61/H61*W61*-1 -> -29.4445 | AH61: =G61/H61*V61 -> 70.57943 | AI61: =1/H61*U61 -> 452.54756 | AJ61: =I61/H61*Y61 -> 0 | AK61: =J61/H61*Y61*-1 -> -19.827291 | AL61: =O61/H61/(0.9*8760) -> 313.68072 | AM61: =P61/H61/(0.9*8760) -> 171.68144 | AN61: =Q61/H61 -> -39.003626 | AO61: =BE61+BF61+BG61 -> 0.40489574 | AP61: =(S61+T61)*-1*(K61+M61)/H61 -> 0 | AQ61: =AO61*S61 -> 29.848444 | AR61: =BE61+BF61 -> 0.40489574 | AS61: =T61*(K61+M61)*-1/H61 -> 0 | AT61: =AR61*S61 -> 29.848444 | AV61: =22/7 -> 3.1428571 | AW61: 0.20320575 | AX61: 0.18289084 | AZ61: =1/H61*AW61 -> 4.1826066 | BA61: =I61/H61*AX61 -> 0 | BB61: =AZ61+BA61 -> 4.1826066 | BD61: =AV61 -> 3.1428571 | BE61: =J61/H61*AX61 -> 0.40469264 | BF61: =(L61+N61)/H61 -> 0.00020309729 | BG61: =(K61+M61)/H61 -> 0 | BH61: =SUM(BD61:BG61) -> 3.5477529 | BJ61: =BB61-BH61 -> 0.63485377
B62: NCEN_F-Ein | C62: Ethane | E62: 0 | F62: 0.155559 | G62: 0.164935 | H62: 0.048583519 | I62: 0 | J62: 0.10750343 | K62: 0 | L62: 9.8671813e-06 | M62: 0 | N62: 0 | O62: 120149.9 | P62: 65759.565 | Q62: -1.8949334 | S62: 73.71884 | T62: -23.276809 | U62: 21.986353 | V62: 20.789991 | W62: 9.19598 | X62: -150.75579 | Y62: 8.960454 | AA62: =B62 -> NCEN_F-Ein | AB62: =C62 -> Ethane | AC62: =SUM(AF62:AN62)+AP62+AQ62 -> 950.06218 | AD62: =SUM(AF62:AN62)+AS62+AT62 -> 950.06218 | AE62: =AC62-AD62 -> 0 | AF62: =E62/H62*W62 -> 0 | AG62: =F62/H62*W62*-1 -> -29.4445 | AH62: =G62/H62*V62 -> 70.57943 | AI62: =1/H62*U62 -> 452.54756 | AJ62: =I62/H62*Y62 -> 0 | AK62: =J62/H62*Y62*-1 -> -19.827291 | AL62: =O62/H62/(0.9*8760) -> 313.68072 | AM62: =P62/H62/(0.9*8760) -> 171.68144 | AN62: =Q62/H62 -> -39.003626 | AO62: =BE62+BF62+BG62 -> 0.40489574 | AP62: =(S62+T62)*-1*(K62+M62)/H62 -> 0 | AQ62: =AO62*S62 -> 29.848444 | AR62: =BE62+BF62 -> 0.40489574 | AS62: =T62*(K62+M62)*-1/H62 -> 0 | AT62: =AR62*S62 -> 29.848444 | AV62: =22/7 -> 3.1428571 | AW62: 0.20320575 | AX62: 0.18289084 | AZ62: =1/H62*AW62 -> 4.1826066 | BA62: =I62/H62*AX62 -> 0 | BB62: =AZ62+BA62 -> 4.1826066 | BD62: =AV62 -> 3.1428571 | BE62: =J62/H62*AX62 -> 0.40469264 | BF62: =(L62+N62)/H62 -> 0.00020309729 | BG62: =(K62+M62)/H62 -> 0 | BH62: =SUM(BD62:BG62) -> 3.5477529 | BJ62: =BB62-BH62 -> 0.63485377
B63: CEN_F-Ein | C63: Ethane | E63: 0 | F63: 0.155559 | G63: 0.164935 | H63: 0.048583519 | I63: 0 | J63: 0.10750343 | K63: 0 | L63: 9.8671813e-06 | M63: 0 | N63: 0 | O63: 120149.9 | P63: 65759.565 | Q63: -1.8949334 | S63: 73.71884 | T63: -23.276809 | U63: 21.986353 | V63: 20.789991 | W63: 9.19598 | X63: -150.75579 | Y63: 8.960454 | AA63: =B63 -> CEN_F-Ein | AB63: =C63 -> Ethane | AC63: =SUM(AF63:AN63)+AP63+AQ63 -> 950.06218 | AD63: =SUM(AF63:AN63)+AS63+AT63 -> 950.06218 | AE63: =AC63-AD63 -> 0 | AF63: =E63/H63*W63 -> 0 | AG63: =F63/H63*W63*-1 -> -29.4445 | AH63: =G63/H63*V63 -> 70.57943 | AI63: =1/H63*U63 -> 452.54756 | AJ63: =I63/H63*Y63 -> 0 | AK63: =J63/H63*Y63*-1 -> -19.827291 | AL63: =O63/H63/(0.9*8760) -> 313.68072 | AM63: =P63/H63/(0.9*8760) -> 171.68144 | AN63: =Q63/H63 -> -39.003626 | AO63: =BE63+BF63+BG63 -> 0.40489574 | AP63: =(S63+T63)*-1*(K63+M63)/H63 -> 0 | AQ63: =AO63*S63 -> 29.848444 | AR63: =BE63+BF63 -> 0.40489574 | AS63: =T63*(K63+M63)*-1/H63 -> 0 | AT63: =AR63*S63 -> 29.848444 | AV63: =22/7 -> 3.1428571 | AW63: 0.20320575 | AX63: 0.18289084 | AZ63: =1/H63*AW63 -> 4.1826066 | BA63: =I63/H63*AX63 -> 0 | BB63: =AZ63+BA63 -> 4.1826066 | BD63: =AV63 -> 3.1428571 | BE63: =J63/H63*AX63 -> 0.40469264 | BF63: =(L63+N63)/H63 -> 0.00020309729 | BG63: =(K63+M63)/H63 -> 0 | BH63: =SUM(BD63:BG63) -> 3.5477529 | BJ63: =BB63-BH63 -> 0.63485377
B64: SE_F-Ein | C64: Ethane | E64: 0 | F64: 0.155559 | G64: 0.164935 | H64: 0.048583519 | I64: 0 | J64: 0.10750343 | K64: 0 | L64: 9.8671813e-06 | M64: 0 | N64: 0 | O64: 120149.9 | P64: 65759.565 | Q64: -1.8949334 | S64: 73.71884 | T64: -23.276809 | U64: 21.986353 | V64: 20.789991 | W64: 9.19598 | X64: -150.75579 | Y64: 8.960454 | AA64: =B64 -> SE_F-Ein | AB64: =C64 -> Ethane | AC64: =SUM(AF64:AN64)+AP64+AQ64 -> 950.06218 | AD64: =SUM(AF64:AN64)+AS64+AT64 -> 950.06218 | AE64: =AC64-AD64 -> 0 | AF64: =E64/H64*W64 -> 0 | AG64: =F64/H64*W64*-1 -> -29.4445 | AH64: =G64/H64*V64 -> 70.57943 | AI64: =1/H64*U64 -> 452.54756 | AJ64: =I64/H64*Y64 -> 0 | AK64: =J64/H64*Y64*-1 -> -19.827291 | AL64: =O64/H64/(0.9*8760) -> 313.68072 | AM64: =P64/H64/(0.9*8760) -> 171.68144 | AN64: =Q64/H64 -> -39.003626 | AO64: =BE64+BF64+BG64 -> 0.40489574 | AP64: =(S64+T64)*-1*(K64+M64)/H64 -> 0 | AQ64: =AO64*S64 -> 29.848444 | AR64: =BE64+BF64 -> 0.40489574 | AS64: =T64*(K64+M64)*-1/H64 -> 0 | AT64: =AR64*S64 -> 29.848444 | AV64: =22/7 -> 3.1428571 | AW64: 0.20320575 | AX64: 0.18289084 | AZ64: =1/H64*AW64 -> 4.1826066 | BA64: =I64/H64*AX64 -> 0 | BB64: =AZ64+BA64 -> 4.1826066 | BD64: =AV64 -> 3.1428571 | BE64: =J64/H64*AX64 -> 0.40469264 | BF64: =(L64+N64)/H64 -> 0.00020309729 | BG64: =(K64+M64)/H64 -> 0 | BH64: =SUM(BD64:BG64) -> 3.5477529 | BJ64: =BB64-BH64 -> 0.63485377
... B75: Existing_NE_F-NGin-H2out | C75: Ethane | E75: 0 | F75: 0.155559 | G75: 0 | H75: 0.048583519 | I75: 0.16812274 | J75: 0 | K75: 0 | L75: 0.01967126 | M75: 0 | N75: 0.030748108 | O75: 90689.949 | P75: 49635.759 | Q75: -2.393333 | S75: 73.71884 | T75: -23.276809 | U75: 21.986353 | V75: 20.789991 | W75: 9.19598 | X75: -150.75579 | Y75: 8.960454 | AA75: =B75 -> Existing_NE_F-NGin-H2out | AB75: =C75 -> Ethane | AC75: =SUM(AF75:AN75)+AP75+AQ75 -> 847.70747 | AD75: =SUM(AF75:AN75)+AS75+AT75 -> 847.70747 | AE75: =AC75-AD75 -> 0 | AF75: =E75/H75*W75 -> 0 | AG75: =F75/H75*W75*-1 -> -29.4445 | AH75: =G75/H75*V75 -> 0 | AI75: =1/H75*U75 -> 452.54756 | AJ75: =I75/H75*Y75 -> 31.007554 | AK75: =J75/H75*Y75*-1 -> 0 | AL75: =O75/H75/(0.9*8760) -> 236.76831 | AM75: =P75/H75/(0.9*8760) -> 129.5863 | AN75: =Q75/H75 -> -49.26224 | AO75: =BE75+BF75+BG75 -> 1.0377875 | AP75: =(S75+T75)*-1*(K75+M75)/H75 -> 0 | AQ75: =AO75*S75 -> 76.50449 | AR75: =BE75+BF75 -> 1.0377875 | AS75: =T75*(K75+M75)*-1/H75 -> 0 | AT75: =AR75*S75 -> 76.50449 | AV75: =22/7 -> 3.1428571 | AW75: 0.20320575 | AX75: 0.18289084 | AZ75: =1/H75*AW75 -> 4.1826066 | BA75: =I75/H75*AX75 -> 0.63289175 | BB75: =AZ75+BA75 -> 4.8154984 | BD75: =AV75 -> 3.1428571 | BE75: =J75/H75*AX75 -> 0 | BF75: =(L75+N75)/H75 -> 1.0377875 | BG75: =(K75+M75)/H75 -> 0 | BH75: =SUM(BD75:BG75) -> 4.1806446 | BJ75: =BB75-BH75 -> 0.63485377
S76: 73.71884 | T76: -23.276809 | U76: 21.986353 | V76: 20.789991 | W76: 9.19598 | X76: -150.75579 | Y76: 8.960454 | AA76: =B76 -> 0 | AB76: =C76 -> 0 | AC76: =SUM(AF76:AN76)+AP76+AQ76 -> #DIV/0! | AD76: =SUM(AF76:AN76)+AS76+AT76 -> #DIV/0! | AE76: =AC76-AD76 -> #DIV/0! | AF76: =E76/H76*W76 -> #DIV/0! | AG76: =F76/H76*W76*-1 -> #DIV/0! | AH76: =G76/H76*V76 -> #DIV/0! | AI76: =1/H76*U76 -> #DIV/0! | AJ76: =I76/H76*Y76 -> #DIV/0! | AK76: =J76/H76*Y76*-1 -> #DIV/0! | AL76: =O76/H76/(0.9*8760) -> #DIV/0! | AM76: =P76/H76/(0.9*8760) -> #DIV/0! | AN76: =Q76/H76 -> #DIV/0! | AO76: =BE76+BF76+BG76 -> #DIV/0! | AP76: =(S76+T76)*-1*(K76+M76)/H76 -> #DIV/0! | AQ76: =AO76*S76 -> #DIV/0! | AR76: =BE76+BF76 -> #DIV/0! | AS76: =T76*(K76+M76)*-1/H76 -> #DIV/0! | AT76: =AR76*S76 -> #DIV/0! | AV76: =22/7 -> 3.1428571 | AW76: 0.20320575 | AX76: 0.18289084 | AZ76: =1/H76*AW76 -> #DIV/0! | BA76: =I76/H76*AX76 -> #DIV/0! | BB76: =AZ76+BA76 -> #DIV/0! | BD76: =AV76 -> 3.1428571 | BE76: =J76/H76*AX76 -> #DIV/0! | BF76: =(L76+N76)/H76 -> #DIV/0! | BG76: =(K76+M76)/H76 -> #DIV/0! | BH76: =SUM(BD76:BG76) -> #DIV/0! | BJ76: =BB76-BH76 -> #DIV/0!
S77: 73.71884 | T77: -23.276809 | U77: 21.986353 | V77: 20.789991 | W77: 9.19598 | X77: -150.75579 | Y77: 8.960454 | AA77: =B77 -> 0 | AB77: =C77 -> 0 | AC77: =SUM(AF77:AN77)+AP77+AQ77 -> #DIV/0! | AD77: =SUM(AF77:AN77)+AS77+AT77 -> #DIV/0! | AE77: =AC77-AD77 -> #DIV/0! | AF77: =E77/H77*W77 -> #DIV/0! | AG77: =F77/H77*W77*-1 -> #DIV/0! | AH77: =G77/H77*V77 -> #DIV/0! | AI77: =1/H77*U77 -> #DIV/0! | AJ77: =I77/H77*Y77 -> #DIV/0! | AK77: =J77/H77*Y77*-1 -> #DIV/0! | AL77: =O77/H77/(0.9*8760) -> #DIV/0! | AM77: =P77/H77/(0.9*8760) -> #DIV/0! | AN77: =Q77/H77 -> #DIV/0! | AO77: =BE77+BF77+BG77 -> #DIV/0! | AP77: =(S77+T77)*-1*(K77+M77)/H77 -> #DIV/0! | AQ77: =AO77*S77 -> #DIV/0! | AR77: =BE77+BF77 -> #DIV/0! | AS77: =T77*(K77+M77)*-1/H77 -> #DIV/0! | AT77: =AR77*S77 -> #DIV/0! | AV77: =22/7 -> 3.1428571 | AW77: 0.20320575 | AX77: 0.18289084 | AZ77: =1/H77*AW77 -> #DIV/0! | BA77: =I77/H77*AX77 -> #DIV/0! | BB77: =AZ77+BA77 -> #DIV/0! | BD77: =AV77 -> 3.1428571 | BE77: =J77/H77*AX77 -> #DIV/0! | BF77: =(L77+N77)/H77 -> #DIV/0! | BG77: =(K77+M77)/H77 -> #DIV/0! | BH77: =SUM(BD77:BG77) -> #DIV/0! | BJ77: =BB77-BH77 -> #DIV/0!
S78: 73.71884 | T78: -23.276809 | U78: 21.986353 | V78: 20.789991 | W78: 9.19598 | X78: -150.75579 | Y78: 8.960454 | AA78: =B78 -> 0 | AB78: =C78 -> 0 | AC78: =SUM(AF78:AN78)+AP78+AQ78 -> #DIV/0! | AD78: =SUM(AF78:AN78)+AS78+AT78 -> #DIV/0! | AE78: =AC78-AD78 -> #DIV/0! | AF78: =E78/H78*W78 -> #DIV/0! | AG78: =F78/H78*W78*-1 -> #DIV/0! | AH78: =G78/H78*V78 -> #DIV/0! | AI78: =1/H78*U78 -> #DIV/0! | AJ78: =I78/H78*Y78 -> #DIV/0! | AK78: =J78/H78*Y78*-1 -> #DIV/0! | AL78: =O78/H78/(0.9*8760) -> #DIV/0! | AM78: =P78/H78/(0.9*8760) -> #DIV/0! | AN78: =Q78/H78 -> #DIV/0! | AO78: =BE78+BF78+BG78 -> #DIV/0! | AP78: =(S78+T78)*-1*(K78+M78)/H78 -> #DIV/0! | AQ78: =AO78*S78 -> #DIV/0! | AR78: =BE78+BF78 -> #DIV/0! | AS78: =T78*(K78+M78)*-1/H78 -> #DIV/0! | AT78: =AR78*S78 -> #DIV/0! | AV78: =22/7 -> 3.1428571 | AW78: 0.20320575 | AX78: 0.18289084 | AZ78: =1/H78*AW78 -> #DIV/0! | BA78: =I78/H78*AX78 -> #DIV/0! | BB78: =AZ78+BA78 -> #DIV/0! | BD78: =AV78 -> 3.1428571 | BE78: =J78/H78*AX78 -> #DIV/0! | BF78: =(L78+N78)/H78 -> #DIV/0! | BG78: =(K78+M78)/H78 -> #DIV/0! | BH78: =SUM(BD78:BG78) -> #DIV/0! | BJ78: =BB78-BH78 -> #DIV/0!
S79: 73.71884 | T79: -23.276809 | U79: 21.986353 | V79: 20.789991 | W79: 9.19598 | X79: -150.75579 | Y79: 8.960454 | AA79: =B79 -> 0 | AB79: =C79 -> 0 | AC79: =SUM(AF79:AN79)+AP79+AQ79 -> #DIV/0! | AD79: =SUM(AF79:AN79)+AS79+AT79 -> #DIV/0! | AE79: =AC79-AD79 -> #DIV/0! | AF79: =E79/H79*W79 -> #DIV/0! | AG79: =F79/H79*W79*-1 -> #DIV/0! | AH79: =G79/H79*V79 -> #DIV/0! | AI79: =1/H79*U79 -> #DIV/0! | AJ79: =I79/H79*Y79 -> #DIV/0! | AK79: =J79/H79*Y79*-1 -> #DIV/0! | AL79: =O79/H79/(0.9*8760) -> #DIV/0! | AM79: =P79/H79/(0.9*8760) -> #DIV/0! | AN79: =Q79/H79 -> #DIV/0! | AO79: =BE79+BF79+BG79 -> #DIV/0! | AP79: =(S79+T79)*-1*(K79+M79)/H79 -> #DIV/0! | AQ79: =AO79*S79 -> #DIV/0! | AR79: =BE79+BF79 -> #DIV/0! | AS79: =T79*(K79+M79)*-1/H79 -> #DIV/0! | AT79: =AR79*S79 -> #DIV/0! | AV79: =22/7 -> 3.1428571 | AW79: 0.20320575 | AX79: 0.18289084 | AZ79: =1/H79*AW79 -> #DIV/0! | BA79: =I79/H79*AX79 -> #DIV/0! | BB79: =AZ79+BA79 -> #DIV/0! | BD79: =AV79 -> 3.1428571 | BE79: =J79/H79*AX79 -> #DIV/0! | BF79: =(L79+N79)/H79 -> #DIV/0! | BG79: =(K79+M79)/H79 -> #DIV/0! | BH79: =SUM(BD79:BG79) -> #DIV/0! | BJ79: =BB79-BH79 -> #DIV/0!
S80: 73.71884 | T80: -23.276809 | U80: 21.986353 | V80: 20.789991 | W80: 9.19598 | X80: -150.75579 | Y80: 8.960454 | AA80: =B80 -> 0 | AB80: =C80 -> 0 | AC80: =SUM(AF80:AN80)+AP80+AQ80 -> #DIV/0! | AD80: =SUM(AF80:AN80)+AS80+AT80 -> #DIV/0! | AE80: =AC80-AD80 -> #DIV/0! | AF80: =E80/H80*W80 -> #DIV/0! | AG80: =F80/H80*W80*-1 -> #DIV/0! | AH80: =G80/H80*V80 -> #DIV/0! | AI80: =1/H80*U80 -> #DIV/0! | AJ80: =I80/H80*Y80 -> #DIV/0! | AK80: =J80/H80*Y80*-1 -> #DIV/0! | AL80: =O80/H80/(0.9*8760) -> #DIV/0! | AM80: =P80/H80/(0.9*8760) -> #DIV/0! | AN80: =Q80/H80 -> #DIV/0! | AO80: =BE80+BF80+BG80 -> #DIV/0! | AP80: =(S80+T80)*-1*(K80+M80)/H80 -> #DIV/0! | AQ80: =AO80*S80 -> #DIV/0! | AR80: =BE80+BF80 -> #DIV/0! | AS80: =T80*(K80+M80)*-1/H80 -> #DIV/0! | AT80: =AR80*S80 -> #DIV/0! | AV80: =22/7 -> 3.1428571 | AW80: 0.20320575 | AX80: 0.18289084 | AZ80: =1/H80*AW80 -> #DIV/0! | BA80: =I80/H80*AX80 -> #DIV/0! | BB80: =AZ80+BA80 -> #DIV/0! | BD80: =AV80 -> 3.1428571 | BE80: =J80/H80*AX80 -> #DIV/0! | BF80: =(L80+N80)/H80 -> #DIV/0! | BG80: =(K80+M80)/H80 -> #DIV/0! | BH80: =SUM(BD80:BG80) -> #DIV/0! | BJ80: =BB80-BH80 -> #DIV/0!

Sheet lc_summary
A1: LCOE for steam/electric cracker ($/t-ethylene)
A2: id_LC | B2: h2_consumption | C2: h2_production | D2: elec_consumption | E2: ethane_consumption | F2: natgas_consumption | G2: natgas_production | H2: investment_cost | I2: fixed_om_cost | J2: variable_om_cost | K2: modified capture cost | L2: modified emissions cost | M2: LCOE ($/t-ethylene) | O2: id_LC | P2: h2_consumption | Q2: h2_production | R2: elec_consumption | S2: ethane_consumption | T2: natgas_consumption | U2: natgas_production | V2: investment_cost | W2: fixed_om_cost | X2: variable_om_cost | Y2: modified capture cost | Z2: modified emissions cost | AA2: LCOE ($/t-ethylene)
A3: =lc_detailed!AA4 -> CA_F-NGin-H2out | B3: =lc_detailed!AF4 -> 0 | C3: =lc_detailed!AG4 -> -28.958095 | D3: =lc_detailed!AH4 -> 0 | E3: =lc_detailed!AI4 -> 452.54756 | F3: =lc_detailed!AJ4 -> 35.716075 | G3: =lc_detailed!AK4 -> 0 | H3: =lc_detailed!AL4 -> 236.76831 | I3: =lc_detailed!AM4 -> 129.5863 | J3: =lc_detailed!AN4 -> -49.26224 | K3: =lc_detailed!AP4 -> 0 | L3: =lc_detailed!AQ4 -> 76.50449 | M3: =lc_detailed!AC4 -> 852.9024 | O3: {=_xlfn._xlws.SORT(A3:M65, 13, 1)} -> CA_F-H2in-CH4out | P3: 32.43071 | Q3: 0 | R3: 0 | S3: 452.54756 | T3: 0 | U3: -33.294772 | V3: 236.76831 | W3: 129.5863 | X3: -49.257271 | Y3: 0 | Z3: 29.848444 | AA3: 798.62928
A4: =lc_detailed!AA5 -> NW_F-NGin-H2out | B4: =lc_detailed!AF5 -> 0 | C4: =lc_detailed!AG5 -> -24.168845 | D4: =lc_detailed!AH5 -> 0 | E4: =lc_detailed!AI5 -> 452.54756 | F4: =lc_detailed!AJ5 -> 29.766159 | G4: =lc_detailed!AK5 -> 0 | H4: =lc_detailed!AL5 -> 236.76831 | I4: =lc_detailed!AM5 -> 129.5863 | J4: =lc_detailed!AN5 -> -49.26224 | K4: =lc_detailed!AP5 -> 0 | L4: =lc_detailed!AQ5 -> 76.50449 | M4: =lc_detailed!AC5 -> 851.74173 | O4: NW_F-H2in-CH4out | P4: 17.74091 | Q4: 0 | R4: 0 | S4: 452.54756 | T4: 0 | U4: -17.621453 | V4: 236.76831 | W4: 129.5863 | X4: -49.257271 | Y4: 0 | Z4: 29.848444 | AA4: 799.6128
A5: =lc_detailed!AA6 -> SW_F-NGin-H2out | B5: =lc_detailed!AF6 -> 0 | C5: =lc_detailed!AG6 -> -42.255518 | D5: =lc_detailed!AH6 -> 0 | E5: =lc_detailed!AI6 -> 452.54756 | F5: =lc_detailed!AJ6 -> 51.747732 | G5: =lc_detailed!AK6 -> 0 | H5: =lc_detailed!AL6 -> 236.76831 | I5: =lc_detailed!AM6 -> 129.5863 | J5: =lc_detailed!AN6 -> -49.26224 | K5: =lc_detailed!AP6 -> 0 | L5: =lc_detailed!AQ6 -> 76.50449 | M5: =lc_detailed!AC6 -> 855.63663 | O5: CA_F-H2in | P5: 1.877864 | Q5: 0 | R5: 0 | S5: 452.54756 | T5: 0 | U5: 0 | V5: 236.76831 | W5: 129.5863 | X5: -49.257271 | Y5: 0 | Z5: 29.848444 | AA5: 801.3712
A6: =lc_detailed!AA7 -> TX_F-NGin-H2out | B6: =lc_detailed!AF7 -> 0 | C6: =lc_detailed!AG7 -> -42.539115 | D6: =lc_detailed!AH7 -> 0 | E6: =lc_detailed!AI7 -> 452.54756 | F6: =lc_detailed!AJ7 -> 52.069111 | G6: =lc_detailed!AK7 -> 0 | H6: =lc_detailed!AL7 -> 236.76831 | I6: =lc_detailed!AM7 -> 129.5863 | J6: =lc_detailed!AN7 -> -49.26224 | K6: =lc_detailed!AP7 -> 0 | L6: =lc_detailed!AQ7 -> 76.50449 | M6: =lc_detailed!AC7 -> 855.67441 | O6: MIDAT_F-H2in | P6: 1.8818212 | Q6: 0 | R6: 0 | S6: 452.54756 | T6: 0 | U6: 0 | V6: 236.76831 | W6: 129.5863 | X6: -49.257271 | Y6: 0 | Z6: 29.848444 | AA6: 801.37516
A7: =lc_detailed!AA8 -> NCEN_F-NGin-H2out | B7: =lc_detailed!AF8 -> 0 | C7: =lc_detailed!AG8 -> -23.270616 | D7: =lc_detailed!AH8 -> 0 | E7: =lc_detailed!AI8 -> 452.54756 | F7: =lc_detailed!AJ8 -> 27.557882 | G7: =lc_detailed!AK8 -> 0 | H7: =lc_detailed!AL8 -> 236.76831 | I7: =lc_detailed!AM8 -> 129.5863 | J7: =lc_detailed!AN8 -> -49.26224 | K7: =lc_detailed!AP8 -> 0 | L7: =lc_detailed!AQ8 -> 76.50449 | M7: =lc_detailed!AC8 -> 850.43168 | O7: SE_F-H2in | P7: 2.2547191 | Q7: 0 | R7: 0 | S7: 452.54756 | T7: 0 | U7: 0 | V7: 236.76831 | W7: 129.5863 | X7: -49.257271 | Y7: 0 | Z7: 29.848444 | AA7: 801.74806
A8: =lc_detailed!AA9 -> CEN_F-NGin-H2out | B8: =lc_detailed!AF9 -> 0 | C8: =lc_detailed!AG9 -> -24.118021 | D8: =lc_detailed!AH9 -> 0 | E8: =lc_detailed!AI9 -> 452.54756 | F8: =lc_detailed!AJ9 -> 18.71319 | G8: =lc_detailed!AK9 -> 0 | H8: =lc_detailed!AL9 -> 236.76831 | I8: =lc_detailed!AM9 -> 129.5863 | J8: =lc_detailed!AN9 -> -49.26224 | K8: =lc_detailed!AP9 -> 0 | L8: =lc_detailed!AQ9 -> 76.50449 | M8: =lc_detailed!AC9 -> 840.73959 | O8: NW_F-H2in | P8: 2.2925913 | Q8: 0 | R8: 0 | S8: 452.54756 | T8: 0 | U8: 0 | V8: 236.76831 | W8: 129.5863 | X8: -49.257271 | Y8: 0 | Z8: 29.848444 | AA8: 801.78593
A9: =lc_detailed!AA10 -> SE_F-NGin-H2out | B9: =lc_detailed!AF10 -> 0 | C9: =lc_detailed!AG10 -> -29.4445 | D9: =lc_detailed!AH10 -> 0 | E9: =lc_detailed!AI10 -> 452.54756 | F9: =lc_detailed!AJ10 -> 31.007554 | G9: =lc_detailed!AK10 -> 0 | H9: =lc_detailed!AL10 -> 236.76831 | I9: =lc_detailed!AM10 -> 129.5863 | J9: =lc_detailed!AN10 -> -49.26224 | K9: =lc_detailed!AP10 -> 0 | L9: =lc_detailed!AQ10 -> 76.50449 | M9: =lc_detailed!AC10 -> 847.70747 | O9: SW_F-H2in | P9: 2.2925913 | Q9: 0 | R9: 0 | S9: 452.54756 | T9: 0 | U9: 0 | V9: 236.76831 | W9: 129.5863 | X9: -49.257271 | Y9: 0 | Z9: 29.848444 | AA9: 801.78593
A10: =lc_detailed!AA11 -> MIDAT_F-NGin-H2out | B10: =lc_detailed!AF11 -> 0 | C10: =lc_detailed!AG11 -> -28.958095 | D10: =lc_detailed!AH11 -> 0 | E10: =lc_detailed!AI11 -> 452.54756 | F10: =lc_detailed!AJ11 -> 35.716075 | G10: =lc_detailed!AK11 -> 0 | H10: =lc_detailed!AL11 -> 236.76831 | I10: =lc_detailed!AM11 -> 129.5863 | J10: =lc_detailed!AN11 -> -49.26224 | K10: =lc_detailed!AP11 -> 0 | L10: =lc_detailed!AQ11 -> 76.50449 | M10: =lc_detailed!AC11 -> 852.9024 | O10: TX_F-H2in | P10: 2.2925913 | Q10: 0 | R10: 0 | S10: 452.54756 | T10: 0 | U10: 0 | V10: 236.76831 | W10: 129.5863 | X10: -49.257271 | Y10: 0 | Z10: 29.848444 | AA10: 801.78593
A11: =lc_detailed!AA12 -> NE_F-NGin-H2out | B11: =lc_detailed!AF12 -> 0 | C11: =lc_detailed!AG12 -> -28.958095 | D11: =lc_detailed!AH12 -> 0 | E11: =lc_detailed!AI12 -> 452.54756 | F11: =lc_detailed!AJ12 -> 35.716075 | G11: =lc_detailed!AK12 -> 0 | H11: =lc_detailed!AL12 -> 236.76831 | I11: =lc_detailed!AM12 -> 129.5863 | J11: =lc_detailed!AN12 -> -49.26224 | K11: =lc_detailed!AP12 -> 0 | L11: =lc_detailed!AQ12 -> 76.50449 | M11: =lc_detailed!AC12 -> 852.9024 | O11: NCEN_F-H2in | P11: 2.2925913 | Q11: 0 | R11: 0 | S11: 452.54756 | T11: 0 | U11: 0 | V11: 236.76831 | W11: 129.5863 | X11: -49.257271 | Y11: 0 | Z11: 29.848444 | AA11: 801.78593
A12: =lc_detailed!AA13 -> CA_F-NGin | B12: =lc_detailed!AF13 -> 0 | C12: =lc_detailed!AG13 -> 0 | D12: =lc_detailed!AH13 -> 0 | E12: =lc_detailed!AI13 -> 452.54756 | F12: =lc_detailed!AJ13 -> 2.5800212 | G12: =lc_detailed!AK13 -> 0 | H12: =lc_detailed!AL13 -> 236.76831 | I12: =lc_detailed!AM13 -> 129.5863 | J12: =lc_detailed!AN13 -> -49.257271 | K12: =lc_detailed!AP13 -> 0 | L12: =lc_detailed!AQ13 -> 33.218736 | M12: =lc_detailed!AC13 -> 805.44365 | O12: CEN_F-H2in | P12: 2.2925913 | Q12: 0 | R12: 0 | S12: 452.54756 | T12: 0 | U12: 0 | V12: 236.76831 | W12: 129.5863 | X12: -49.257271 | Y12: 0 | Z12: 29.848444 | AA12: 801.78593
A13: =lc_detailed!AA14 -> NW_F-NGin | B13: =lc_detailed!AF14 -> 0 | C13: =lc_detailed!AG14 -> 0 | D13: =lc_detailed!AH14 -> 0 | E13: =lc_detailed!AI14 -> 452.54756 | F13: =lc_detailed!AJ14 -> 2.5800212 | G13: =lc_detailed!AK14 -> 0 | H13: =lc_detailed!AL14 -> 236.76831 | I13: =lc_detailed!AM14 -> 129.5863 | J13: =lc_detailed!AN14 -> -49.257271 | K13: =lc_detailed!AP14 -> 0 | L13: =lc_detailed!AQ14 -> 33.218736 | M13: =lc_detailed!AC14 -> 805.44365 | O13: TX_F-H2in-CH4out | P13: 22.447718 | Q13: 0 | R13: 0 | S13: 452.54756 | T13: 0 | U13: -19.827291 | V13: 236.76831 | W13: 129.5863 | X13: -49.257271 | Y13: 0 | Z13: 29.848444 | AA13: 802.11377
A14: =lc_detailed!AA15 -> SW_F-NGin | B14: =lc_detailed!AF15 -> 0 | C14: =lc_detailed!AG15 -> 0 | D14: =lc_detailed!AH15 -> 0 | E14: =lc_detailed!AI15 -> 452.54756 | F14: =lc_detailed!AJ15 -> 2.5800212 | G14: =lc_detailed!AK15 -> 0 | H14: =lc_detailed!AL15 -> 236.76831 | I14: =lc_detailed!AM15 -> 129.5863 | J14: =lc_detailed!AN15 -> -49.257271 | K14: =lc_detailed!AP15 -> 0 | L14: =lc_detailed!AQ15 -> 33.218736 | M14: =lc_detailed!AC15 -> 805.44365 | O14: NCEN_F-H2in-CH4out | P14: 22.447718 | Q14: 0 | R14: 0 | S14: 452.54756 | T14: 0 | U14: -19.827291 | V14: 236.76831 | W14: 129.5863 | X14: -49.257271 | Y14: 0 | Z14: 29.848444 | AA14: 802.11377
A15: =lc_detailed!AA16 -> TX_F-NGin | B15: =lc_detailed!AF16 -> 0 | C15: =lc_detailed!AG16 -> 0 | D15: =lc_detailed!AH16 -> 0 | E15: =lc_detailed!AI16 -> 452.54756 | F15: =lc_detailed!AJ16 -> 2.1502172 | G15: =lc_detailed!AK16 -> 0 | H15: =lc_detailed!AL16 -> 236.76831 | I15: =lc_detailed!AM16 -> 129.5863 | J15: =lc_detailed!AN16 -> -49.257271 | K15: =lc_detailed!AP16 -> 0 | L15: =lc_detailed!AQ16 -> 33.218736 | M15: =lc_detailed!AC16 -> 805.01385 | O15: CEN_F-H2in-CH4out | P15: 22.447718 | Q15: 0 | R15: 0 | S15: 452.54756 | T15: 0 | U15: -19.827291 | V15: 236.76831 | W15: 129.5863 | X15: -49.257271 | Y15: 0 | Z15: 29.848444 | AA15: 802.11377
... A65: =lc_detailed!AA66 -> NE_F-Ein | B65: =lc_detailed!AF66 -> 0 | C65: =lc_detailed!AG66 -> -29.4445 | D65: =lc_detailed!AH66 -> 70.57943 | E65: =lc_detailed!AI66 -> 452.54756 | F65: =lc_detailed!AJ66 -> 0 | G65: =lc_detailed!AK66 -> -19.827291 | H65: =lc_detailed!AL66 -> 313.68072 | I65: =lc_detailed!AM66 -> 171.68144 | J65: =lc_detailed!AN66 -> -39.003626 | K65: =lc_detailed!AP66 -> 0 | L65: =lc_detailed!AQ66 -> 29.848444 | M65: =lc_detailed!AC66 -> 950.06218 | O65: NE_F-Ein | P65: 0 | Q65: -29.4445 | R65: 70.57943 | S65: 452.54756 | T65: 0 | U65: -19.827291 | V65: 313.68072 | W65: 171.68144 | X65: -39.003626 | Y65: 0 | Z65: 29.848444 | AA65: 950.06218
